Workbook
Name LISTA2: #REF!
Name LISTA2: #REF!
Name LISTA: #REF!
Name LISTA: #REF!
Name CONDIÇÕES: LEGENDAS!$B$2:$B$15
Name Z_924C3F12_84CF_4ABF_87A7_8BDDD9B8FFC3_.wvu.Cols: #REF!
Name Z_8ACAB7D4_A245_4B01_A455_8574F923850F_.wvu.Cols: #REF!
Name QD: #REF!
Name Z_211FD241_5063_4A4F_BCF7_C47C7F4BF783_.wvu.Cols: #REF!
Name listadoida: #REF!
Name QD: #REF!
Name listaprodutos: #REF!

Sheet PEDIDOS
A1: PEDIDO | B1: CLIENTE | C1: QTY EM ESTOQUE | D1: ORDEM DE PRODUCAO | E1: MODELO | F1: CONTROL | G1: OPCIONAL | H1: ESQ ESF | I1: SITUACAO | J1: TRANSPORTADORA | K1: REDESPACHO | L1: NOTA FISCAL | M1: EXPEDIDO POR | N1: VEICULO | O1: DATA ENTREGA | P1: OBSERVAÇÃO | Q1: INTEGRADO POR | R1: APROVADO POR | S1: FINALIZADO POR | T1: DATA INTEGRAÇÃO | U1: DATA APROVAÇÃO | V1: DATA FINALIZAÇÃO | W1: VOLUMES | X1: DATA DA ENTREGA FUTURA | Y1: IMPRESSAO LOGISTICA | Z1: IMPRESSAO PRODUCAO | AA1: Estado | AB1: 🔒 Row ID | AC1: Qty
A2: 9315 | B2: ODY PARK | C2: 0 | D2: N INF | E2: FT240H35T | F2: TOUCH | G2: SOBREPOR | H2: NAO | I2: ENTREGUE | J2: DESTAK | K2: SEM REDESPACHO | L2: 10979 | M2: RUBENS F | N2: QJC5G74 - DESTAK - MOHAMAD KASSEM RAHHAL JUNIOR - 75084600954 - FIAT / DUCATO CHASSI L / PRATA / 2018 | O2: 45461.605 | P2: RETORNO OS - 2605 | T2: 45460 | U2: 45460 | V2: =O2 -> 45461.605 | AB2: CEpVgkCBTDG1O.g7S56G7g
A3: 18684-A | B3: ANDRADES PISCINAS E AQUECEDORES LTDA | C3: 41 | D3: 8A00240411003121 | E3: FTI125D40PT | F3: WI-FI | G3: NAO | H3: NAO | I3: ENTREGUE | J3: FITLOG | K3: SEM REDESPACHO | L3: 14061 | M3: Eduardo Gasperi (Expedição) | N3: KKY4B29 - V2 - RODRIGO NEZIO GRADICI - 07157615959 - FORD/CARGO 1317 E / CARAGA CAMINHAO / PRATA / 2010 | O3: 45489.644 | P3: PR170 - PEDIDO 15704 DA ANDRADE PISCINAS AGUARDANDO PAGAMENTO | T3: 45489.644 | V3: 45489.589 | AB3: gP.DutRRSzK5nyW2GD.yJw
A4: 18684-B | B4: ANDRADES PISCINAS E AQUECEDORES LTDA | C4: 41 | D4: 8A00240411003124 | E4: FTI125D40PT | F4: WI-FI | G4: NAO | H4: NAO | I4: ENTREGUE | J4: FITLOG | K4: SEM REDESPACHO | L4: 14061 | M4: Eduardo Gasperi (Expedição) | N4: KKY4B29 - V2 - RODRIGO NEZIO GRADICI - 07157615959 - FORD/CARGO 1317 E / CARAGA CAMINHAO / PRATA / 2010 | O4: 45489.644 | P4: PR176 - PEDIDO 15704 DA ANDRADE PISCINAS AGUARDANDO PAGAMENTO | T4: 45489.644 | V4: 45489.589 | AB4: w7Hs2zo1Sj21Y-qGz5Gqew
A5: PR177 | B5: ANDRADES PISCINAS E AQUECEDORES LTDA | C5: 41 | D5: 8A00240411003144 | E5: FTI125D40PT | F5: WI-FI | G5: NAO | H5: NAO | I5: FILIAL PARANA | J5: FITLOG | K5: SEM REDESPACHO | L5: 14061 | M5: Eduardo Gasperi (Expedição) | N5: KKY4B29 - V2 - RODRIGO NEZIO GRADICI - 07157615959 - FORD/CARGO 1317 E / CARAGA CAMINHAO / PRATA / 2010 | O5: 45489.644 | P5: PR177 - DISPONIVEL ULT CONTAGEM 04/11 | T5: 45489.644 | V5: 45489.589 | AB5: Tcma2JeES9W00VrrQ1zhPg
A6: 16454 | B6: PISCINA E LAZER | C6: 41 | D6: 8A00240411003115 | E6: FTI125D40PT | F6: WI-FI | G6: NAO | H6: NAO | I6: ENTREGUE | J6: EXPRESSO SAO MIGUEL | K6: SEM REDESPACHO | L6: 11969 | M6: Eduardo Gasperi (Expedição) | N6: KKY4B29 - V2 - RODRIGO NEZIO GRADICI - 07157615959 - FORD/CARGO 1317 E / CARAGA CAMINHAO / PRATA / 2010 | O6: 45608.453 | P6: PR184 - DISPONIVEL ULT CONTAGEM 04/11 ESTOQUE CURITIBA - PR 184 Pedido nº 1585 enviado pelo vendedor Renato criado em 11/11/2024 09:31:28 integrado por meio do Bendito no dia 11/11/2024 às 14:32:34 | Q6: Juliana Vieira | R6: Juliana Vieira | T6: 45608.453 | U6: 45608.453 | V6: 45608.453 | AB6: DWaTaqF8Su6ghTDxnrqqjw
A7: R14817 | B7: BR CERT LABORATORIOS LTDA. | C7: 12 | D7: 8F00240723280519 | E7: FTI45D40PT | G7: NAO | H7: NAO | I7: ENTREGUE | J7: FITLOG | K7: SEM REDESPACHO | L7: 12694 | M7: Jair Rodrigues (Logística) | O7: 45721 | P7: ORÇAMENTO Nº1287/2025 | Q7: Eline Velho | R7: Eline Velho | S7: Jair Rodrigues (Logística) | T7: 45716.565 | U7: 45716.565 | V7: 45716.587 | AB7: ho69gK3ERAS9-bddCsfFdQ
A8: 13832 | B8: UNIAO BR DE EDUCACAO E ASSITENCIA PUCRS | D8: 13832 | E8: FT40B35T | G8: NAO | H8: NAO | I8: ENTREGUE | J8: EXPRESSO SAO MIGUEL | K8: SEM REDESPACHO | L8: 12396 | M8: Eduardo Gasperi (Expedição) | N8: QJL1E51 - EXPRESSO SÃO MIGUEL - CLEIMAR CRESTANI - 07899108969 - VW / 17280 CRM 4X2 / BRANCO / 2017 | O8: 45665.636 | P8: MAQUINA CERTIFICAÇÃO INMETRO - PROVA | T8: 45665.636 | AB8: 5Smk4sB6RcqWjfxga99eZg
A9: 15537 | B9: BERCHA E TENCIANO LTDA | D9: 8B00240106003041 | E9: FTI55D40PT | F9: WI-FI | G9: NAO | H9: NAO | I9: ENTREGUE | J9: FITLOG | K9: SEM REDESPACHO | N9: OMG6C25 - FIT LOG - PAULO SERGIO AMARO - 03705266942 - M.BENZ / CARGA CAMINHAO / BRANCA / 2012 | O9: 45482 | P9: PR118 | T9: 45440 | U9: 45475 | V9: =O9 -> 45482 | AB9: cf1q6-QBQXmncHAlD5IvMw
A10: 15553 | B10: NAUSSAT PISCINAS | D10: 8B00231215003187 | E10: FTI75D40PT | F10: WI-FI | G10: NAO | H10: NAO | I10: ENTREGUE | J10: RETIRA | K10: SEM REDESPACHO | L10: 11171 | N10: FILIAL PARANA | O10: 45489 | P10: MAQUINA ESTOQUE PARTICULAR RENATO - COD.BARRAS - 31110003000092- 8B00231215003187 ANTES DA TABELA NOVA - ESSA MAQUINA ERA DO RENATO, FOI VENDIDA PRA ELE, ELE ATENDEU A NECESSIDADE DE UM CLIENTE VENDENDO A MAQUINA DELE PRO CLIENTE, SENDO ESSES DADOS ACIMA. NAO SEI QUAL É O PEDIDO ANTERIOR | Q10: Juliana Vieira | T10: 45489.741 | U10: 45489 | V10: OBSERVAÇÃO | AA10: PR | AB10: d6ixmBOgQnqJNVzraY5xuQ
A11: 15651 | B11: AQUALAR E/OU AQUALAR WATER SOLUTIONS | D11: 13514 | E11: FT180F35T | G11: SOBREPOR | H11: NAO | I11: ENTREGUE | J11: FITLOG | K11: SEM REDESPACHO | L11: 11208 | M11: Eduardo Gasperi (Expedição) | N11: MGH1012 - FIT LOG - ELIVELTO GONÇALVES DIAS - 07704779923 - VW / 8.150E DELIVERY / BRANCA / 2005 | O11: 45496.575 | P11: Quadro deslocado sobrepor. ENTRGAR N AQUALAR Mario-Autorizado( Composição de fechamento dos pre pedidos 751.752.823 e 824(integrados juntos) Pedido nº 752 enviado pelo vendedor Ricardo Henrique criado em 08/07/2024 14:18:08 integrado por meio do Bendito no dia 19/07/2024 às 10:27:08 POR FAVOR, NÃO ENTREGAR S/ENTRAR EM CONTATO COM O TELEFONE: 21 99512-4022 AO MENOS C/ 24H DE ANTECEDÊNCIA | Q11: Juliana Vieira | S11: Francisco/Rubens (Teste) | T11: 45492.447 | U11: 45492.452 | V11: 45495.671 | AA11: RJ | AB11: c8EoQN2fTsSTZrvQ1MM6Uw
A12: 15964 | B12: WILLIAN RAFAEL ALVES 06251787694 | D12: 8A00240514003010 | E12: FTI55D40PT | G12: NAO | H12: NAO | I12: ENTREGUE | J12: FITLOG | K12: SEM REDESPACHO | L12: 11472 | M12: Eduardo Gasperi (Expedição) | N12: ASE2851 - FIT LOG - RICARDO JORGE HAVIARA - 87153955968 - PEUGEOT / BOXER F350LH 23S / BRANCA / 2010 | O12: 45547.611 | P12: Frete com redespacho pela GRIFE - CNPJ: 25.406.384/0005-00 - GUARULHOS - R. IRAQUARA 24 - JARDIM IV CENTENARIO, GUARULHOS - SP, O cliente está com urgência da máquina. Pedido nº 1131 enviado pelo vendedor Luiz criado em 11/09/2024 10:34:20 integrado por meio do Bendito no dia 11/09/2024 às 10:36:18 O REDESPACHO SERA FOB - TRANSP. GRIFE - CNPJ:25.406.384/0005-00 - END: R IRAQUARA, 24, CEP: 07.161-550 | Q12: Juliana Vieira | R12: Juliana Vieira | S12: Eduardo Gasperi (Expedição) | T12: 45546.457 | U12: 45546.603 | V12: 45547.475 | AA12: MG | AB12: YE7yE-wZR6mYhh-R7oi5kg
A13: 16401 | B13: AQUAFIX EQUIPAMENTOS PARA PISCINAS | D13: 8B00240322003239 | E13: FTI105D40PT | F13: WI-FI | G13: NAO | H13: NAO | I13: ENTREGUE | J13: FITLOG | K13: SEM REDESPACHO | L13: 11933 | M13: Eduardo Gasperi (Expedição) | N13: KKY4B29 - V2 - RODRIGO NEZIO GRADICI - 07157615959 - FORD/CARGO 1317 E / CARAGA CAMINHAO / PRATA / 2010 | O13: 45489.644 | P13: ESTOQUE CURITIBA PR162 - O PEDIDO JA FOI RETIRADO PELO CLIENTE DA FILIAL PARANA, O PEDIDO ANTERIOR 15801 HAVIA SIDO CANCELADO, REABRIMOS O PEDIDO E MANTEREMOS A FORMA DE PAGAMENTO A VISTA, O PEDIDO AINDA NÃO CONSTA COMO PAGO. QUANDO O PEDIDO FOR PAGO FAVOR, FATURAR A NF E INFORMAR O JAIR | Q13: Juliana Vieira | R13: Juliana Vieira | T13: 45602.665 | U13: 45602.664 | V13: 45489.588 | AA13: PR | AB13: OVd2mcz0RSecKYwngcpZYg
A14: 16528 | B14: VERANO | D14: 13787 | E14: FT20B35T | G14: NAO | H14: NAO | I14: ENTREGUE | J14: RETIRA | K14: SEM REDESPACHO | L14: 12131 | M14: Eduardo Gasperi (Expedição) | N14: RHE5C97 - RETIRA - MARCOS VINICIUS DA SILVA CRUZ - 93307217291 - VW / CARGA CAMIONETE / BRANCA / 2022 | O14: 45637.66 | P14: CLIENTE TEM DESCONTO EXTRA DE + 8% NA LINHA FT PREÇO R$ 6.297,51 PEDIDO CLIENTE 24811 Pedido nº 1649 enviado pelo vendedor Carlos Augusto criado em 20/11/2024 08:15:58 integrado por meio do Bendito no dia 20/11/2024 às 09:18:03 | Q14: Juliana Vieira | R14: Juliana Vieira | S14: Francisco/Rubens (Teste) | T14: 45616.4 | U14: 45616.412 | V14: 45630.588 | AA14: SC | AB14: SORlhv1sRsCwRr2qBjI9kw
A15: 16713 | B15: MULTCOLOR | D15: 8F00241005160010 | E15: FTI75D40PT | G15: NAO | H15: NAO | I15: ENTREGUE | J15: FITLOG | K15: SEM REDESPACHO | L15: 12243 | M15: Eduardo Gasperi (Expedição) | N15: KET4256 - FITLOG - LEONARDO DE SOUSA ROCHA - 02043623931 - VW / 18.310 / BRANCA / 2003 | O15: 45645.731 | P15: cliente : ricardo martinez (parana) - (constar em NF) Pedido nº 1755 enviado pelo vendedor Fábio criado em 04/12/2024 10:09:17 integrado por meio do Bendito no dia 04/12/2024 às 10:16:40 | Q15: Juliana Vieira | R15: Juliana Vieira | S15: Jair Rodrigues (Logística) | T15: 45630.455 | U15: 45630.465 | V15: 45643.756 | Y15: -12166 | AA15: SP | AB15: vmtL7lMAS7ixxlsqVkDCrQ
A16: 16728 | B16: ROGER A.D BOARO | D16: 8F00240812180128 | E16: FTI45D40PT | G16: NAO | H16: NAO | I16: ENTREGUE | J16: FITLOG | K16: SEM REDESPACHO | L16: 12179 | M16: Eduardo Gasperi (Expedição) | N16: ASE2851 - FIT LOG - RICARDO JORGE HAVIARA - 87153955968 - PEUGEOT / BOXER F350LH 23S / BRANCA / 2010 | O16: 45637.626 | P16: AGUARDANDO ANALISE FINANCEIRA. O desconto no pedido foi autorizado pelo Mario pelo frete cotado no valor de R$163,33 Número da cotação: 164133 Mario-autorizado | Q16: Juliana Vieira | R16: Juliana Vieira | S16: Eduardo Gasperi (Expedição) | T16: 45636.448 | U16: 45636.449 | V16: 45636.45 | AA16: PR | AB16: yZR1RvSzRsWtnLP.QAtaMg
A17: 16792 | B17: Laboratório do Sol Aquecedores | D17: 13818 | E17: FTI145DPTBR | G17: NAO | H17: NAO | I17: ENTREGUE | J17: EXPRESSO SAO MIGUEL | K17: SEM REDESPACHO | L17: 12257 | M17: Eduardo Gasperi (Expedição) | N17: RLL3I15 - RETIRA - GUILHERME OURIQUES - - RENAUT / MASTER / BRANCA / 2022 | O17: 45652.491 | P17: VALOR DA BOMBA R$20852,00 - NA COR PRETA entrada+30/45/60/75/90 ds Pedido nº 1724 enviado pelo vendedor Carlos Augusto criado em 29/11/2024 15:02:54 integrado por meio do Bendito no dia 30/11/2024 às 07:28:48 | Q17: Juliana Vieira | R17: Juliana Vieira | S17: Rubens | T17: 45642.676 | U17: 45642.676 | V17: 45644 | AA17: SC | AB17: Ar3bnGnURhOWGqeCabtJkQ
A18: 17016 | B18: ILUSTRE SISTEMA DE ILUMINACAO | D18: 8F00241118050033 | E18: FTI75D40PT | G18: NAO | H18: NAO | I18: ENTREGUE | J18: FITLOG | K18: FORMATO | L18: 12554 | M18: Eduardo Gasperi (Expedição) | N18: MGH1012 - FITLOG - GIORLY BOMBUL - 11305672224 - VW / DELIVERY / BRANCA / 2015 | O18: 45691.595 | P18: R$10.221,86 em 10 x no cartão . Passar o link para Bruno Sampaio . TRANSPORTADORA : FORMATO TRANSPORTES LTDA-CNPJ: 13.727.240/0001-34 RUA RIO GRANDE DP PIAUI-130 CIDADE ARACILIA GUARULHOS SP -FONE 11 25367215- Pedido nº 2043 enviado pelo vendedor Mario criado em 31/01/2025 14:01:01 integrado por meio do Bendito no dia 31/01/2025 às 14:01:11 FORMATO TRANSPORTES LTDA-CNPJ: 13.727.240/0001-34 RUA RIO GRANDE DP PIAUI-130 CIDADE ARACILIA GUARULHOS SP -FONE 1125367215 | Q18: Eline Velho | R18: Eline Velho | S18: Eduardo Gasperi (Expedição) | T18: 45688.732 | U18: 45688.732 | V18: 45691.36 | AA18: BA | AB18: WTZySRbTRCSmb3.GCvH.iA
A19: 17042 | B19: NERCI MOREIRA | D19: 8F00241021270016 | E19: FTI105D40PT | G19: NAO | H19: NAO | I19: ENTREGUE | J19: EXPRESSO SAO MIGUEL | K19: SEM REDESPACHO | L19: 12580 | M19: Eduardo Gasperi (Expedição) | N19: RAA3F11 - EXPRESSO SÃO MIGUEL - ALIDEIA JUCHEM CRESTANI - 04171883903 - I KIA / UK2500 HD SC / BRANCA / 2022 | O19: 45694.598 | P19: OP ANTIGA 13958 ESTE PEDIDO COMPLETA O PEDIDO 17002, QUE DEVEERIA TER SIDO ENTREGUE 2 MAQUINAS E FOI ENTREGUE APENAS 1. Pedido nº 2032 enviado pelo vendedor Renato criado em 30/01/2025 13:24:04 integrado por meio do Bendito no dia 30/01/2025 às 14:19:51 | Q19: Eline Velho | R19: Jair Rodrigues | S19: Eduardo Gasperi (Expedição) | T19: 45693.512 | U19: 45693.551 | V19: 45694.345 | AA19: PR | AB19: ZB5icL8hQR-R.Fu.y94tEA
A20: 17181 | B20: GAROPABA PISCINAS | D20: 13954 | E20: FTI55DPTBR | G20: NAO | H20: NAO | I20: ENTREGUE | J20: RETIRA | K20: SEM REDESPACHO | L20: 12705 | M20: Jair Rodrigues (Logística) | N20: MHL9974 - RETIRA - VERA LUCIA CARDOSO LEMOS - 46915338004 - VW / SAVEIRO / PRETA / 2015 | O20: 45726.44 | P20: cliente retira . 07/03/25 Pedido nº 2186 enviado pelo vendedor Mario criado em 07/03/2025 15:01:18 integrado por meio do Bendito no dia 07/03/2025 às 15:01:28 | Q20: Eline Velho | R20: Eline Velho | T20: 45723.629 | U20: 45723.629 | AA20: SC | AB20: gr9Z3G9uSsWBLLxTf44U6A
A21: 17654 | B21: EXPRESSO SAO MIGUEL | D21: 8F00240723280539 | E21: FTI45D40PT | G21: NAO | H21: NAO | I21: ENTREGUE | J21: EXPRESSO SAO MIGUEL | K21: SEM REDESPACHO | L21: 13152 | P21: SAÍDA REFERENTE A RESSARCIMENTO DE MÁQUINA AVARIADA. - PEDIDO 17284 - NF-e 12866 APÓLICE DE SEGURO Nº | Q21: Jair Rodrigues (Logística) | R21: Jair Rodrigues (Logística) | S21: Jair Rodrigues (Logística) | T21: 45806.744 | U21: 45806.744 | V21: 45806.744 | AB21: WKuDpHSHRv2HpZudKA7Uuw
A22: 11488 | B22: BENE E BENI COMÉRCIO DE PISCINAS LTDA | D22: 11831 | E22: FT160F35T | F22: TOUCH | G22: SOBREPOR | H22: NAO | I22: ENTREGUE | J22: FITLOG | K22: SEM REDESPACHO | L22: 9744 | O22: 45198 | P22: FRETE CIF. | T22: 45195 | U22: 45195 | V22: 45197 | AB22: 0ih7WFstRquMj-AVoJEftw
A23: 13619-A | B23: ACQUANEW PISCINAS LTDA | C23: {=COUNTIFS('Estoque V2'!A:A,E23:E5893,'Estoque V2'!D:D,0,'Estoque V2'!C:C,F23)} -> 0 | D23: 8B00230924003126 | E23: FTI55D40CZ | F23: WI-FI | G23: NAO | H23: NAO | I23: ENTREGUE | J23: EXPRESSO SAO MIGUEL | K23: SEM REDESPACHO | L23: 9813-10212 | O23: 45308 | P23: CONDIÇÃO DE PAGAMENTO APROVADA PELO MARIO | T23: 45183 | U23: 45305 | V23: 45308 | AB23: GENH4wujRJCgI4PfoqIHxw
A24: 13619-B | B24: ACQUANEW PISCINAS LTDA | C24: 0 | D24: 8B00230927003031 | E24: FTI75D40CZ | F24: WI-FI | G24: NAO | H24: NAO | I24: ENTREGUE | J24: EXPRESSO SAO MIGUEL | K24: SEM REDESPACHO | L24: 9813-10212 | O24: 45308 | P24: CONDIÇÃO DE PAGAMENTO APROVADA PELO MARIO | T24: 45183 | U24: 45305 | V24: 45308 | AB24: dy6GHuyzTkiwO3DgMRdHBA
A25: 13619-C | B25: ACQUANEW PISCINAS LTDA | C25: 0 | D25: 8B00230927003060 | E25: FTI75D40CZ | F25: WI-FI | G25: NAO | H25: NAO | I25: ENTREGUE | J25: EXPRESSO SAO MIGUEL | K25: SEM REDESPACHO | L25: 9813-10212 | O25: 45308 | P25: CONDIÇÃO DE PAGAMENTO APROVADA PELO MARIO | T25: 45183 | U25: 45305 | V25: 45308 | AB25: lUdU1o.kSiO2CsJ4CE7PAw
A26: 13619-D | B26: ACQUANEW PISCINAS LTDA | C26: 0 | D26: 8B00230927003098 | E26: FTI105D40CZ | F26: WI-FI | G26: NAO | H26: NAO | I26: ENTREGUE | J26: EXPRESSO SAO MIGUEL | K26: SEM REDESPACHO | L26: 9813-10212 | O26: 45308 | P26: CONDIÇÃO DE PAGAMENTO APROVADA PELO MARIO | T26: 45183 | U26: 45305 | V26: 45308 | AB26: JhmbP0IbQUO7fTsPqLQvYQ
A27: 13619-E | B27: ACQUANEW PISCINAS LTDA | C27: 0 | D27: 8B00230927003112 | E27: FTI125D40CZ | F27: WI-FI | G27: NAO | H27: NAO | I27: ENTREGUE | J27: EXPRESSO SAO MIGUEL | K27: SEM REDESPACHO | L27: 9813-10212 | O27: 45308 | P27: CONDIÇÃO DE PAGAMENTO APROVADA PELO MARIO | T27: 45183 | U27: 45305 | V27: 45308 | AB27: J2ywZGqNRv2edywv8Ilq4Q
A28: 13619-F | B28: ACQUANEW PISCINAS LTDA | C28: 0 | D28: 8B00230924003178 | E28: FTI55D40CZ | F28: WI-FI | G28: NAO | H28: NAO | I28: ENTREGUE | J28: EXPRESSO SAO MIGUEL | K28: SEM REDESPACHO | L28: 9813-10212 | O28: 45308 | P28: CONDIÇÃO DE PAGAMENTO APROVADA PELO MARIO | T28: 45183 | U28: 45305 | V28: 45308 | AB28: DDu1qcXZQR6OJohn2Jj57g
A29: 13621-A | B29: ADRIANI APARECIDA BOTTEGA | C29: 0 | D29: 8B00230927003077 | E29: FTI75D40CZ | F29: WI-FI | G29: NAO | H29: NAO | I29: ENTREGUE | J29: EXPRESSO SAO MIGUEL | K29: SEM REDESPACHO | L29: 9861 | O29: 45310 | T29: 45197 | U29: 45307 | V29: 45310 | AB29: zLu7RaOaTBmZmmGDutM2YA
A30: 13621-B | B30: ADRIANI APARECIDA BOTTEGA | C30: 0 | D30: 8B00230927003055 | E30: FTI75D40CZ | F30: WI-FI | G30: NAO | H30: NAO | I30: ENTREGUE | J30: EXPRESSO SAO MIGUEL | K30: SEM REDESPACHO | L30: 9861 | O30: 45310 | T30: 45197 | U30: 45307 | V30: 45310 | AB30: TvJvz-r3Sp6dwFEKpGdOsg
A31: 13623-A | B31: CR DOS SANTOS | C31: 0 | D31: 11715 | E31: FT20B35T | F31: TOUCH | G31: SOBREPOR | H31: NAO | I31: ENTREGUE | J31: EXPRESSO M.LOG | K31: SEM REDESPACHO | L31: 9725 | O31: 45195 | T31: 45187 | U31: 45187 | V31: 45190 | AB31: zxFZlTq5SbKsdbm4k6o1UA
A32: 13623-B | B32: CR DOS SANTOS | C32: 0 | D32: 11789 | E32: FT40B35T | F32: TOUCH | G32: SOBREPOR | H32: NAO | I32: ENTREGUE | J32: EXPRESSO M.LOG | K32: SEM REDESPACHO | L32: 9725 | O32: 45195 | T32: 45187 | U32: 45187 | V32: 45190 | AB32: E0L224e-TYmQ1tWfYhX84g
A33: 13623-C | B33: CR DOS SANTOS | C33: 0 | D33: 11790 | E33: FT40B35T | F33: TOUCH | G33: SOBREPOR | H33: NAO | I33: ENTREGUE | J33: EXPRESSO M.LOG | K33: SEM REDESPACHO | L33: 9725 | O33: 45195 | T33: 45187 | U33: 45187 | V33: 45190 | AB33: Cp20CV7mTcWAK8KzHaOmpA
A34: 13623-D | B34: CR DOS SANTOS | C34: 0 | D34: 11791 | E34: FT50B35T | F34: TOUCH | G34: SOBREPOR | H34: NAO | I34: ENTREGUE | J34: EXPRESSO M.LOG | K34: SEM REDESPACHO | L34: 9725 | O34: 45195 | T34: 45187 | U34: 45187 | V34: 45190 | AB34: VqSwe38xRAmxh-3OI8hbKg
A35: 13623-E | B35: CR DOS SANTOS | C35: 0 | D35: 11806 | E35: AMOSTRA FT-25/40 | F35: TOUCH | G35: NAO | H35: NAO | I35: ENTREGUE | J35: EXPRESSO M.LOG | K35: SEM REDESPACHO | L35: 9725 | O35: 45195 | T35: 45187 | U35: 45187 | V35: 45194 | AB35: UlFQ9IlvQgSTs8fJH30gVg
A36: 13625 | B36: CR DOS SANTOS | C36: 0 | D36: 11793 | E36: FT160F35T | F36: TOUCH | G36: SOBREPOR | H36: NAO | I36: ENTREGUE | J36: EXPRESSO M.LOG | K36: SEM REDESPACHO | L36: 9699 | O36: 45190 | T36: 45187 | U36: 45187 | V36: 45190 | AB36: o6Kxd5G1SBm3WbEKUDVzWA
A37: 13627-A | B37: CR DOS SANTOS | C37: 137 | D37: 8B00230924003185 | E37: FTI55D40PT | F37: WI-FI | G37: NAO | H37: NAO | I37: ENTREGUE | J37: EXPRESSO M.LOG | K37: SEM REDESPACHO | L37: 9814-10249 | O37: 45309 | T37: 45187 | U37: 45306 | V37: 45309 | AB37: BTa..KDLSG-3OwZW2864TA
A38: 13627-B | B38: CR DOS SANTOS | C38: 0 | D38: 8B00230927003064 | E38: FTI75D40CZ | F38: WI-FI | G38: NAO | H38: NAO | I38: ENTREGUE | J38: EXPRESSO M.LOG | K38: SEM REDESPACHO | L38: 9814-10249 | O38: 45309 | T38: 45187 | U38: 45306 | V38: 45309 | AB38: a-5d1CQR5S2W1vugvBQGg3g
A39: 13629 | B39: ESSENCIAL CASA LAZER LTDA | C39: 0 | D39: 11166 | E39: FT60D35T | F39: TOUCH | G39: NAO | H39: NAO | I39: ENTREGUE | J39: EXPRESSO SAO MIGUEL | K39: SEM REDESPACHO | L39: 9668 | O39: 45183 | P39: VENDA PELA FROMTHERM, MAS RETIRA PELO ESTOQUE DA BOLHA AZUL ENTRADA 5MIL + 30/60 -NS 12639 -NF 9107-OP 11166 | T39: 45195 | U39: 45178 | V39: 45182 | AB39: 1S3pWmqkSRucEb88040hjg
A40: 13631 | B40: ELIANE MARIA DOS SANTOS PINHEIRO | C40: 0 | D40: 11794 | E40: FT40B35T | F40: TOUCH | G40: SOBREPOR | H40: NAO | I40: ENTREGUE | J40: DESTAK | K40: BOM JESUS | L40: 9720 | O40: 45194 | T40: 45187 | U40: 45187 | V40: 45190 | AB40: X8pmrO5dSBmNmXVnw1SWig
A41: 13633 | B41: SIMONE COMÉRCIO DE PISCINAS EIRELLI | C41: 0 | D41: 11783 | E41: FT40B35 | F41: PDX | G41: NAO | H41: NAO | I41: ENTREGUE | J41: BRUSVILLE | K41: SEM REDESPACHO | L41: 9683 | O41: 45188 | P41: QUADRO PDX SERÁ EXTERNO - ENVIAR PRONTO PARA ESTE USO | T41: 45183 | U41: 45183 | V41: 45188 | AB41: iY-tnz0bTp64X08qNf550g
A42: 13638 | B42: BROGNONI & BASSO CONSTRUCOES DE PISCINAS LTDA | C42: 0 | D42: 11799 | E42: FT80B35T | F42: TOUCH | G42: SOBREPOR | H42: NAO | I42: ENTREGUE | J42: FITLOG | K42: SEM REDESPACHO | L42: 9723 | O42: 45194 | P42: 50% DE SINAL E 50% NO DESPACHO DO EQUIPAMENTO COM FRETE CIF | T42: 45184 | U42: 45184 | V42: 45194 | AB42: vhiB-MnzSbq3sFd6JWZEKQ
A43: 13640 | B43: FLIPPER PISCINAS | C43: 0 | D43: 11521 | E43: FT20B35 | F43: PDX | G43: NAO | H43: NAO | I43: ENTREGUE | J43: DISK & TENHA | K43: SEM REDESPACHO | L43: 9677 | O43: 45184 | T43: 45183 | U43: 45183 | V43: 45183 | AB43: bXGt67XGQcieV.WDykkKXA
A44: 13642 | B44: ACQUATHERM | C44: 0 | D44: 11800 | E44: FT50B35T | F44: TOUCH | G44: NAO | H44: NAO | I44: ENTREGUE | J44: DISK & TENHA | K44: SEM REDESPACHO | L44: 9719 | O44: 45194 | P44: ESTE PEDIDO SUBSTITUI O PEDIDO 13503 - ACQUATHERM POR ERRO DE DIGITAÇÃO DO REPRESENTANTE, FOI COMPRADO FT50 E DIGITADO FT40 - JÁ ESTÁ PAGO ESTA BOMBA | T44: 45190 | U44: 45190 | V44: 45191 | AB44: XWXor2U1QgmgLRl-ahShkw
A45: 13645 | B45: LS BOMBAS E ASSISTENCIA TECNICA LTDA | C45: 0 | D45: 11634 | E45: FT100F35T | F45: TOUCH | G45: SOBREPOR | H45: NAO | I45: ENTREGUE | J45: DESTAK | K45: VALEN | L45: 9678 | O45: 45188 | T45: 45184 | U45: 45184 | V45: 45187 | AB45: xUNwbZnyTZKadanLkfYKgQ
A46: 13649 | B46: SÓ LAZER PISCINAS | C46: 0 | D46: 10594 | E46: FT40B35T | F46: TOUCH | G46: NAO | H46: NAO | I46: ENTREGUE | J46: FITLOG | K46: SEM REDESPACHO | L46: 9682 | O46: 45188 | P46: CLIENTE : 500708 MICHAEL BANI - CONSTAR EM NF DESCONTAR DA CONTA CORRENTE - DESCONTO DE 10% + 3% | T46: 45187 | U46: 45187 | V46: 45188 | AB46: 8XklGGM8QhiCGTW7e.6PDQ
A47: 13651 | B47: BROGNONI & BASSO CONSTRUCOES DE PISCINAS LTDA | C47: 0 | D47: 11809 | E47: FT50B35T | F47: TOUCH | G47: NAO | H47: NAO | I47: ENTREGUE | J47: FITLOG | K47: SEM REDESPACHO | L47: 9749 | O47: 45198 | P47: PAGAMENTO: 50% DE SINAL E 50% QUANDO EQUIPAMENTO FOR DESPACHADO COM FRETE CIF. | T47: 45190 | U47: 45190 | V47: 45194 | AB47: VRwqK7NcSuepSpPL6pPzgQ
A48: 13653 | B48: GRANEL PISCINAS INDÚSTRIA E COMÉRCIO LTDA | C48: 0 | D48: 11788 | E48: FT40B35T | F48: TOUCH | G48: NAO | H48: NAO | I48: ENTREGUE | J48: DESTAK | K48: VT | L48: 9698 | O48: 45190 | P48: REDESPACHO PELA V.T. TRANSPORTES | T48: 45184 | U48: 45184 | V48: 45190 | AB48: UhNfFYWVQvS2rVOKINgsZg
A49: 13655-A | B49: STEINFIBER PISCINAS | C49: 0 | D49: 11784 | E49: FT240L35T | F49: TOUCH | G49: NAO | H49: NAO | I49: ENTREGUE | J49: RETIRA | K49: SEM REDESPACHO | L49: 9697 | O49: 45191 | P49: PEDIDO ACCR DEGELO COBRADO ADICIONAL DE 4% | T49: 45184 | U49: 45184 | V49: 45189 | AB49: 91xBOQPWRrWuKIpC.8kNQg
A50: 13657 | B50: SÉRGIO R. HANG | C50: 0 | D50: 11617 | E50: FT80J35T | F50: TOUCH | G50: NAO | H50: NAO | I50: ENTREGUE | J50: RETIRA | K50: SEM REDESPACHO | L50: 9718 | O50: 45218 | P50: CLIENTE: SOLTEC COM. DE PISC E BANH. LTDA PAGA AO RETIRAR NA FÁBRICA | T50: 45190 | U50: 45190 | V50: 45191 | AB50: dYrUMxDWR0qOn7o65Fxv.g
A51: 13659 | B51: STILLO DAGUA | C51: 0 | D51: 11786 | E51: FT100J35T | F51: TOUCH | G51: NAO | H51: NAO | I51: ENTREGUE | J51: RETIRA | K51: SEM REDESPACHO | L51: 9691 | O51: 45197 | P51: PEDIDO 12982 - TALMIDIN | T51: 45184 | U51: 45184 | V51: 45187 | AB51: Zae-jjBGS9qvUge07CgSaQ
A52: 13661-A | B52: SPECIAN LUZ PISCINAS | C52: 90 | D52: 8B00230927003082 | E52: FTI75D40PT | F52: WI-FI | G52: NAO | H52: NAO | I52: ENTREGUE | J52: EXPRESSO SAO MIGUEL | K52: SEM REDESPACHO | L52: 9767-10223 | O52: 45308 | T52: 45190 | U52: 45305 | V52: 45308 | AB52: dmJuvT6qTe2NPHEB1oyAow
A53: 13661-B | B53: SPECIAN LUZ PISCINAS | C53: 11 | D53: 8B00230927003110 | E53: FTI105D40PT | F53: WI-FI | G53: NAO | H53: NAO | I53: ENTREGUE | J53: EXPRESSO SAO MIGUEL | K53: SEM REDESPACHO | L53: 9767-10223 | O53: 45308 | T53: 45190 | U53: 45305 | V53: 45308 | AB53: wtLSZOQETfCjXiPSjfg3Zw
A54: 13661-C | B54: SPECIAN LUZ PISCINAS | C54: 34 | D54: 8B00230927003120 | E54: FTI125D40PT | F54: WI-FI | G54: NAO | H54: NAO | I54: ENTREGUE | J54: EXPRESSO SAO MIGUEL | K54: SEM REDESPACHO | L54: 9767-10223 | O54: 45308 | T54: 45190 | U54: 45305 | V54: 45308 | AB54: zh9hjEeoTEuZb03h4OBJqA
A55: 13661-D | B55: SPECIAN LUZ PISCINAS | C55: 137 | D55: 8B00230924003189 | E55: FTI55D40PT | F55: WI-FI | G55: NAO | H55: NAO | I55: ENTREGUE | J55: EXPRESSO SAO MIGUEL | K55: SEM REDESPACHO | L55: 9767-10223 | O55: 45308 | T55: 45190 | U55: 45305 | V55: 45308 | AB55: CZJuaN-RSyWo96HmsFi6dQ
A56: 13661-E | B56: SPECIAN LUZ PISCINAS | C56: 137 | D56: 8B00230924003184 | E56: FTI55D40PT | F56: WI-FI | G56: NAO | H56: NAO | I56: ENTREGUE | J56: EXPRESSO SAO MIGUEL | K56: SEM REDESPACHO | L56: 9767-10223 | O56: 45308 | T56: 45190 | U56: 45305 | V56: 45308 | AB56: 5Ay2e7TeQ0qYlws3QSCdkQ
A57: 13661-F | B57: SPECIAN LUZ PISCINAS | C57: 137 | D57: 8B00230924003192 | E57: FTI55D40PT | F57: WI-FI | G57: NAO | H57: NAO | I57: ENTREGUE | J57: EXPRESSO SAO MIGUEL | K57: SEM REDESPACHO | L57: 9767-10223 | O57: 45308 | T57: 45190 | U57: 45305 | V57: 45308 | AB57: waXqrj3YR-WV0l5wTmlUVQ
A58: 13661-G | B58: SPECIAN LUZ PISCINAS | C58: 137 | D58: 8B00230924003193 | E58: FTI55D40PT | F58: WI-FI | G58: NAO | H58: NAO | I58: ENTREGUE | J58: EXPRESSO SAO MIGUEL | K58: SEM REDESPACHO | L58: 9767-10223 | O58: 45308 | T58: 45190 | U58: 45305 | V58: 45308 | AB58: h2eza9tFRtuC6OrabI5LWw
A59: 13661-H | B59: SPECIAN LUZ PISCINAS | C59: 137 | D59: 8B00230924003191 | E59: FTI55D40PT | F59: WI-FI | G59: NAO | H59: NAO | I59: ENTREGUE | J59: EXPRESSO SAO MIGUEL | K59: SEM REDESPACHO | L59: 9767-10223 | O59: 45310 | T59: 45190 | U59: 45307 | V59: 45310 | AB59: Lyu8b.DBS7mdSy6NLMLzOA
A60: 13663 | B60: JULIANA DANTAS DE ARAÚJO SANTOS CAMARGO | C60: 0 | D60: 11787 | E60: FT40B35T | F60: TOUCH | G60: SOBREPOR | H60: NAO | I60: ENTREGUE | J60: DESTAK | K60: BOM JESUS | L60: 9692 | O60: 45189 | P60: VENDA INDICADA PELA AGUAS E VAPORES | T60: 45187 | U60: 45187 | V60: 45189 | AB60: zoI0JI-sQm2izzoynU-e7A
A61: 13665 | B61: AVIZ | C61: 0 | D61: 11587 | E61: FT25B35T | F61: TOUCH | G61: NAO | H61: NAO | I61: ENTREGUE | J61: TW | K61: SEM REDESPACHO | L61: 9681 | O61: 45188 | P61: RESERVA 11587 | T61: 45187 | U61: 45187 | V61: 45187 | AB61: xh5A8TcMRI-5gdmNsLAW8Q
A62: 13667-A | B62: AG INCORPORADORA DE IMOVEIS LTDA | C62: 0 | D62: 8B00230927003093 | E62: FTI105D40CZ | F62: WI-FI | G62: NAO | H62: NAO | I62: ENTREGUE | J62: EXPRESSO SAO MIGUEL | K62: SEM REDESPACHO | L62: 9688-10219 | O62: 45308 | T62: 45187 | U62: 45305 | V62: 45308 | AB62: KwxvMDWkSGm.n9aWqR3Ysg
A63: 13667-B | B63: AG INCORPORADORA DE IMOVEIS LTDA | C63: 0 | D63: 8B00230927003108 | E63: FTI105D40CZ | F63: WI-FI | G63: NAO | H63: NAO | I63: ENTREGUE | J63: EXPRESSO SAO MIGUEL | K63: SEM REDESPACHO | L63: 9688-10219 | O63: 45308 | T63: 45187 | U63: 45305 | V63: 45308 | AB63: gafIGf.kQzOO8KLdE9baaA
A64: 13667-C | B64: AG INCORPORADORA DE IMOVEIS LTDA | C64: 0 | D64: 8B00230924003170 | E64: FTI55D40CZ | F64: WI-FI | G64: NAO | H64: NAO | I64: ENTREGUE | J64: EXPRESSO SAO MIGUEL | K64: SEM REDESPACHO | L64: 9688-10219 | O64: 45308 | T64: 45187 | U64: 45305 | V64: 45308 | AB64: wAneqJD9RjuyRmpViiQ1QA
A65: 13667-D | B65: AG INCORPORADORA DE IMOVEIS LTDA | C65: 0 | D65: 8B00230924003145 | E65: FTI55D40CZ | F65: WI-FI | G65: NAO | H65: NAO | I65: ENTREGUE | J65: EXPRESSO SAO MIGUEL | K65: SEM REDESPACHO | L65: 9688-10219 | O65: 45308 | T65: 45187 | U65: 45305 | V65: 45308 | AB65: ZHCXNQHUTZetBJFmMdRwkw
A66: 13667-E | B66: AG INCORPORADORA DE IMOVEIS LTDA | C66: 0 | D66: 8B00230924003134 | E66: FTI55D40CZ | F66: WI-FI | G66: NAO | H66: NAO | I66: ENTREGUE | J66: EXPRESSO SAO MIGUEL | K66: SEM REDESPACHO | L66: 9688-10219 | O66: 45308 | T66: 45187 | U66: 45305 | V66: 45308 | AB66: 7vZYGxejTymiD-0oiCjfxw
A67: 13667-F | B67: AG INCORPORADORA DE IMOVEIS LTDA | C67: 0 | D67: 8B00230924003175 | E67: FTI55D40CZ | F67: WI-FI | G67: NAO | H67: NAO | I67: ENTREGUE | J67: EXPRESSO SAO MIGUEL | K67: SEM REDESPACHO | L67: 9688-10219 | O67: 45308 | T67: 45187 | U67: 45305 | V67: 45308 | AB67: eNgcElZBRb2Vakv1ejBBfQ
A68: 13667-G | B68: AG INCORPORADORA DE IMOVEIS LTDA | C68: 0 | D68: 8B00230924003124 | E68: FTI55D40CZ | F68: WI-FI | G68: NAO | H68: NAO | I68: ENTREGUE | J68: EXPRESSO SAO MIGUEL | K68: SEM REDESPACHO | L68: 9688-10219 | O68: 45310 | T68: 45187 | U68: 45307 | V68: 45310 | AB68: eAW6w1E4S2it8YRDkmrGuw
A69: 13669 | B69: CASA & VERDE- ARTIGOS PARA LAZER LTDA | C69: 0 | D69: 11792 | E69: FT40B35T | F69: TOUCH | G69: EMBUTIR | H69: NAO | I69: ENTREGUE | J69: FITLOG | K69: SEM REDESPACHO | L69: 9696 | O69: 45190 | T69: 45187 | U69: 45187 | V69: 45190 | AB69: m.DqDvv4SLG3cThkKLSgxg
A70: 13674-A | B70: FARNEZZI MATERIAIS DE CONTRUÇÃO LTDA | C70: 0 | D70: 11583 | E70: FT20B35T | F70: TOUCH | G70: NAO | H70: NAO | I70: ENTREGUE | J70: DESTAK | K70: RODOCAP | L70: 9717 | O70: 45194 | P70: TRANSPORTADORA RODOCAP - VOU ENVIAR POR EMAIL A COTAÇÃO DO FRETE PARA ANEXAR A NF. DESCONTO 40% + 5% | T70: 45188 | U70: 45188 | V70: 45189 | AB70: sF-8i9d7TxuYk86cpe-a6g
A71: 13674-B | B71: FARNEZZI MATERIAIS DE CONTRUÇÃO LTDA | C71: 0 | D71: 11795 | E71: FT100D35T | F71: TOUCH | G71: NAO | H71: NAO | I71: ENTREGUE | J71: DESTAK | K71: RODOCAP | L71: 9717 | O71: 45194 | P71: TRANSPORTADORA RODOCAP - VOU ENVIAR POR EMAIL A COTAÇÃO DO FRETE PARA ANEXAR A NF. DESCONTO 40% + 5% | T71: 45188 | U71: 45188 | V71: 45191 | AB71: Lo3XtTl-RnSWqqpptyrBLA
A72: 13676 | B72: SOL E AR | C72: 0 | D72: 11644 | E72: FT40D35T | F72: TOUCH | G72: SOBREPOR | H72: NAO | I72: ENTREGUE | J72: DESTAK | K72: MINAS STAR | L72: 9693 | O72: 45189 | P72: TRANSPORTADORA MINAS STAR DESCONTO 40% + 10% NR OC 24177, CONSTAR NA OBS DA NF. | T72: 45187 | U72: 45187 | V72: 45189 | AB72: W0xnC582SVijDxxC8C3NQQ
A73: 13678 | B73: DONATTI DISTRIBUIDORA LTDA | C73: 0 | D73: 11796 | E73: FT40B35 | F73: PDX | G73: NAO | H73: NAO | I73: ENTREGUE | J73: EXPRESSO SAO MIGUEL | K73: SEM REDESPACHO | L73: 9716 | O73: 45194 | T73: 45188 | U73: 45188 | V73: 45190 | AB73: nkEQK0PpSSqI.ehKwNiSdA
A74: 13680 | B74: IMPERIO COMERCIO DE PISCINAS E PRODUTOS | C74: 0 | D74: 11329 | E74: FT40D35T | F74: TOUCH | G74: SOBREPOR | H74: NAO | I74: ENTREGUE | J74: RETIRA | K74: SEM REDESPACHO | L74: 9686 | O74: 45189 | P74: PEDIDO RETIRADO PELO ESTOQUE BOLHA NS 13308 NF 9493 | T74: 45188 | U74: 45188 | V74: 45189 | AB74: h2h26U90R.C.52GTc4TKrw
A75: 13684 | B75: SOL E AR | C75: 0 | D75: 11716 | E75: FT20B35T | F75: TOUCH | G75: SOBREPOR | H75: NAO | I75: ENTREGUE | J75: DESTAK | K75: MINAS STAR | L75: 9695 | O75: 45190 | P75: TRANSPORTADORA :MINAS STAR DESCONTOS : 40% + 10% OC 24167 CONSTAR NA OBS DA NF | T75: 45189 | U75: 45189 | V75: 45190 | AB75: dWLTPvi-T9-eUET309nW5g
A76: 13686 | B76: BOLHA AZUL COM. VAREJISTA DE PISCINAS | C76: 0 | D76: 11630 | E76: FT40B35T | F76: TOUCH | G76: NAO | H76: NAO | I76: ENTREGUE | J76: RETIRA | K76: SEM REDESPACHO | L76: 9702 | O76: 45190 | P76: RETIRA DO ESTOQUE BOLHA AZUL -NS 13308 - NF 9493 | T76: 45189 | U76: 45189 | V76: 45190 | AB76: a-Wm3ca6kTwWWIHDohGOqKQ
A77: 13688 | B77: JOÃO CARLOS SOUZA DA SILVA LTDA | C77: 0 | D77: 11811 | E77: FT80F35T | F77: TOUCH | G77: NAO | H77: NAO | I77: ENTREGUE | J77: EXPRESSO SAO MIGUEL | K77: SEM REDESPACHO | L77: 9736 | O77: 45197 | T77: 45190 | U77: 45190 | V77: 45194 | AB77: JoZuQKikQz-WzgFQrWGeDg
A78: 13692 | B78: AGUA VIVA PISCINAS | C78: 90 | D78: 8B00230927003085 | E78: FTI75D40PT | F78: WI-FI | G78: NAO | H78: NAO | I78: ENTREGUE | J78: DESTAK | K78: DICA | L78: 9687-10250 | O78: 45309 | P78: VENDA PROGRAMADA, ENVIAR O BOLETO DA ENTRADA. | T78: 45189 | U78: 45306 | V78: 45309 | AB78: xL0GfMH7Rwq.19Ue7H1BXA
A79: 13694-A | B79: INFRAH HIDRAULICA | C79: 0 | D79: 11797 | E79: FT180F35T | F79: TOUCH | G79: SOBREPOR | H79: NAO | I79: ENTREGUE | J79: ACEVILLE | K79: SEM REDESPACHO | L79: 9715 | O79: 45194 | P79: ATENÇÃO: ENTREGAR NO ENDEREÇO RUA JOAQUIM FERREIRA,124, BAIRRO AGUA BRANCA-SÃO PAULO(COND. RAIL) COPIAR EMIAL: ALISSON@INFRAH.COM ENTREGA: 7 DIAS - Q DESL SOB. | T79: 45189 | U79: 45189 | V79: 45191 | AB79: a-xty5fgiTd23nGjBPzZOiw
A80: 13694-B | B80: INFRAH HIDRAULICA | C80: 0 | D80: 11798 | E80: FT180F35T | F80: TOUCH | G80: SOBREPOR | H80: NAO | I80: ENTREGUE | J80: ACEVILLE | K80: SEM REDESPACHO | L80: 9715 | O80: 45194 | P80: ATENÇÃO: ENTREGAR NO ENDEREÇO RUA JOAQUIM FERREIRA,124, BAIRRO AGUA BRANCA-SÃO PAULO(COND. RAIL) COPIAR EMIAL: ALISSON@INFRAH.COM ENTREGA: 7 DIAS - Q DESL SOB. | T80: 45189 | U80: 45189 | V80: 45191 | AB80: RBvCMLMfTsmp903Z5qwlkw
A81: 13696 | B81: ANDRÉ DANTAS DE OLIVEIRA | C81: 0 | D81: 11841 | E81: FT100J35T | F81: TOUCH | G81: SOBREPOR | H81: NAO | I81: ENTREGUE | J81: DESTAK | K81: BOM JESUS | L81: 9735 | O81: 45197 | P81: ANDREZINHODANTAS@GMAIL.COM - VENDA INDICADA AGUAS E VAPORES (RN) | T81: 45196 | U81: 45196 | V81: 45196 | AB81: a-rJXXojMQg6oneO2I-h6jg
A82: 13698 | B82: VITORIA PISCINAS E ECO JARDIM PROD EQUIP | C82: 0 | D82: 11713 | E82: FT20B35T | F82: TOUCH | G82: SOBREPOR | H82: NAO | I82: ENTREGUE | J82: MOVVI | K82: SEM REDESPACHO | L82: 9714 | O82: 45194 | P82: COTAR FRETE E EMBUTIR NA NF | T82: 45190 | U82: 45190 | V82: 45191 | AB82: AT3ZP3wES36f067.gGb5Cw
A83: 13700 | B83: AVIZ | C83: 0 | D83: 11464 | E83: FT25B35T | F83: TOUCH | G83: NAO | H83: NAO | I83: ENTREGUE | J83: TW | K83: SEM REDESPACHO | L83: 9713 | O83: 45194 | T83: 45190 | U83: 45190 | V83: 45191 | AB83: y0scsR4DQbuAbCI6amfVqg
A84: 13704 | B84: BROGNONI & BASSO CONSTRUCOES DE PISCINAS LTDA | C84: 0 | D84: 11712 | E84: FT20B35T | F84: TOUCH | G84: NAO | H84: NAO | I84: ENTREGUE | J84: FITLOG | K84: SEM REDESPACHO | L84: 9703 | O84: 45191 | P84: PAGAMENTO: 50% DE SINAL + 50% QUANDO EQUIPAMENTO FOR DESPACHADO POR FRETE CIF. | T84: 45189 | U84: 45189 | V84: 45189 | AB84: 7bexcYlHQyiF1xzwS9tNsg
A85: 13706 | B85: ROGER JOSÉ DE AMORIM 89158520600 | C85: 0 | D85: 11482 | E85: FT40B35T | F85: TOUCH | G85: NAO | H85: NAO | I85: ENTREGUE | J85: DESTAK | K85: EXPRESSO RAQUEL | L85: 9694 | O85: 45190 | P85: NUM. RESERVA 11482. REDESPACHO PELA EXPRESSO RAQUEL | T85: 45189 | U85: 45189 | V85: 45190 | AB85: R5VXMrpCSQGC70MxtMKn3Q
A86: 13708-A | B86: LAR PISCINAS | C86: 0 | D86: 11819 | E86: FT160F35 | F86: PDX | G86: NAO | H86: NAO | I86: ENTREGUE | J86: FITLOG | K86: SEM REDESPACHO | L86: 9748 | O86: 45198 | P86: 1+7 X COM ENTRADA VIA PIX R$8.025,00 ATENÇÃO NA ENTREGA, MANDAR COM DISPOSITIVO PARA DESCAGARREGAR OU AJUDANTES. | T86: 45194 | U86: 45194 | V86: 45195 | AB86: nqG7pUzVSGeWGoVYADVahA
A87: 13708-B | B87: LAR PISCINAS | C87: 0 | D87: 11820 | E87: FT160F35 | F87: PDX | G87: NAO | H87: NAO | I87: ENTREGUE | J87: FITLOG | K87: SEM REDESPACHO | L87: 9748 | O87: 45198 | P87: 1+7 X COM ENTRADA VIA PIX R$8.025,00 ATENÇÃO NA ENTREGA, MANDAR COM DISPOSITIVO PARA DESCAGARREGAR OU AJUDANTES. | T87: 45194 | U87: 45194 | V87: 45195 | AB87: FLMofZzhSy-Xc3tiEeyw5g
A88: 13708-C | B88: LAR PISCINAS | C88: 0 | D88: 11589 | E88: FT25B35 | F88: PDX | G88: NAO | H88: NAO | I88: ENTREGUE | J88: FITLOG | K88: SEM REDESPACHO | L88: 9748 | O88: 45198 | P88: 1+7 X COM ENTRADA VIA PIX R$8.025,00 ATENÇÃO NA ENTREGA, MANDAR COM DISPOSITIVO PARA DESCAGARREGAR OU AJUDANTES. | T88: 45194 | U88: 45194 | V88: 45197 | AB88: kjClJZUCSuiGS-RV42DQ6g
A89: 13708-D | B89: LAR PISCINAS | C89: 0 | D89: 11465 | E89: FT25B35 | F89: PDX | G89: NAO | H89: NAO | I89: ENTREGUE | J89: FITLOG | K89: SEM REDESPACHO | L89: 9748 | O89: 45198 | P89: 1+7 X COM ENTRADA VIA PIX R$8.025,00 ATENÇÃO NA ENTREGA, MANDAR COM DISPOSITIVO PARA DESCAGARREGAR OU AJUDANTES. | T89: 45194 | U89: 45194 | V89: 45197 | AB89: Vc36FhBfTDS8-vrijZJmbw
A90: 13708-E | B90: LAR PISCINAS | C90: 0 | D90: 11466 | E90: FT25B35 | F90: PDX | G90: NAO | H90: NAO | I90: ENTREGUE | J90: FITLOG | K90: SEM REDESPACHO | L90: 9748 | O90: 45198 | P90: 1+7 X COM ENTRADA VIA PIX R$8.025,00 ATENÇÃO NA ENTREGA, MANDAR COM DISPOSITIVO PARA DESCAGARREGAR OU AJUDANTES. | T90: 45194 | U90: 45194 | V90: 45197 | AB90: QTBZsNhRTcSJGMV5kcv6gg
A91: 13708-F | B91: LAR PISCINAS | C91: 0 | D91: 11588 | E91: FT25B35 | F91: PDX | G91: NAO | H91: NAO | I91: ENTREGUE | J91: FITLOG | K91: SEM REDESPACHO | L91: 9748 | O91: 45198 | P91: 1+7 X COM ENTRADA VIA PIX R$8.025,00 ATENÇÃO NA ENTREGA, MANDAR COM DISPOSITIVO PARA DESCAGARREGAR OU AJUDANTES. | T91: 45194 | U91: 45194 | V91: 45197 | AB91: OScsqg42QSi.Mmf4p-ayhg
A92: 13710 | B92: CENTER POOL PISCINAS E AQUECEDORES | C92: 0 | D92: 11807 | E92: FT180F35T | F92: TOUCH | G92: SOBREPOR | H92: NAO | I92: ENTREGUE | J92: EXPRESSO SAO MIGUEL | K92: SEM REDESPACHO | L92: 9729 | O92: 45196 | T92: 45190 | U92: 45190 | V92: 45195 | AB92: j0.wdtS7TWqWpAPdZTMOog
A93: 13712 | B93: NADE PISCINAS LTDA | C93: 0 | D93: 11635 | E93: FT100F35T | F93: TOUCH | G93: SOBREPOR | H93: NAO | I93: ENTREGUE | J93: EXPRESSO SAO MIGUEL | K93: SEM REDESPACHO | L93: 9712 | O93: 45195 | P93: FRETE CIF | T93: 45190 | U93: 45190 | V93: 45191 | AB93: oQY5kkHWQcGWQKduxjfQMQ
A94: 13714-A | B94: CASA DO ELETRICISTA MCR | C94: 0 | D94: 8B00230924003119 | E94: FTI55D40CZ | F94: WI-FI | G94: NAO | H94: NAO | I94: ENTREGUE | J94: EXPRESSO SAO MIGUEL | K94: SEM REDESPACHO | L94: 10220 | O94: 45308 | T94: 45198 | U94: 45305 | V94: 45308 | AB94: VltpHpuSTjOa4jlltCfcZA
A95: 13714-B | B95: CASA DO ELETRICISTA MCR | C95: 0 | D95: 8B00230924003149 | E95: FTI55D40CZ | F95: WI-FI | G95: NAO | H95: NAO | I95: ENTREGUE | J95: EXPRESSO SAO MIGUEL | K95: SEM REDESPACHO | L95: 10220 | O95: 45308 | T95: 45198 | U95: 45305 | V95: 45308 | AB95: 2cWUpKbwSqWc-ZX1E1Kz8Q
A96: 13716 | B96: MICHEL ANGELO PETENUCI | C96: 0 | D96: 11606 | E96: FT160H35T | F96: TOUCH | G96: SOBREPOR | H96: NAO | I96: ENTREGUE | J96: EXPRESSO SAO MIGUEL | K96: SEM REDESPACHO | L96: 9711 | O96: 45195 | T96: 45190 | U96: 45190 | V96: 45191 | AB96: nmL218j5S8m8Z21-8.RCNQ
A97: 13718 | B97: SOL E AR | C97: 0 | D97: 11714 | E97: FT20B35T | F97: TOUCH | G97: EMBUTIR | H97: NAO | I97: ENTREGUE | J97: DESTAK | K97: MINAS STAR | L97: 9710 | O97: 45194 | P97: SUBSTITUIÇÃO PEDIDO 12063 - OS: 2312 | T97: 45190 | U97: 45190 | V97: 45191 | AB97: mV-brqX5SwyYSIPdnEzMfA
A98: 13719 | B98: JATO DAGUA PISCINAS | C98: 0 | D98: 11801 | E98: FT40B35T | F98: TOUCH | G98: NAO | H98: NAO | I98: ENTREGUE | J98: ACEVILLE | K98: SEM REDESPACHO | L98: 9709 | O98: 45194 | T98: 45190 | U98: 45190 | V98: 45194 | AB98: S7PCPj-zQC24JLKy-UXA2g
A99: 13721 | B99: JATO DAGUA PISCINAS | C99: 0 | D99: 11808 | E99: FT100J35T | F99: TOUCH | G99: NAO | H99: NAO | I99: ENTREGUE | J99: ACEVILLE | K99: SEM REDESPACHO | L99: 9734 | O99: 45197 | T99: 45190 | U99: 45190 | V99: 45194 | AB99: a-1UwE.9tSSa69soAEwSkKg
A100: 13725 | B100: BOLHA AZUL COM. VAREJISTA DE PISCINAS | C100: 0 | D100: 11274 <- OP DA BOLHA | E100: FT100H35T | F100: TOUCH | G100: NAO | H100: NAO | I100: ENTREGUE | J100: RETIRA | K100: SEM REDESPACHO | L100: 9727 | O100: 45195 | P100: RETIRA DO ESTOQUE BOLHA - OP 11274 - NS 12639 - NF 9135 | T100: 45195 | U100: 45195 | V100: 45195 | AB100: lid752IIQiucBFt8xWYvfQ
...

Sheet CONSULTAS
B1: CLIENTE/NOME FANTASIA | C1: QTY EM ESTOQUE | D1: ORDEM DE PROD INFOR. DE PROD. | E1: MODELO | F1: CONTROL | G1: TIPO DE QUADRO | H1: ESQ ESF | I1: SITUAÇÃO | J1: TRANSPORTADORA | K1: REDESPACHO | L1: NUMERO DA NOTA FISCAL | M1: EXPEDIDO POR | N1: VEICULO | O1: DATA DE ENTREGA | P1: OBSERVAÇÃO | Q1: INSERIDO POR | R1: APROVADO POR | S1: FINALIZADO POR | T1: INTEGRAÇÃO DO PEDIDO | U1: APROVAÇÃO PEDIDO | V1: FINALIZAÇÃO DA IDENTIFICAÇÃO | W1: 🔒 Row ID | X1: FORMA PGTO | Y1: DATA_PAGTO | Z1: VALOR | AA1: UF | AB1: REP | AC1: OBS GERAIS
A2: =IFERROR(__xludf.DUMMYFUNCTION("SORT(FILTER(PEDIDOS!A1:P547,(PEDIDOS!I1:I547=""PRODUÇÃO"")+(PEDIDOS!I1:I547=""EM ABERTO"")+(PEDIDOS!I1:I547=""PRIORIDADE"")+(PEDIDOS!I1:I547=""TESTAR"")),9,TRUE )"),"18788-B") -> 18788-B | B2: =IFERROR(__xludf.DUMMYFUNCTION("""COMPUTED_VALUE"""),"PRO LAZER") -> PRO LAZER | C2: =IFERROR(__xludf.DUMMYFUNCTION("""COMPUTED_VALUE"""),0.0) -> 0 | D2: =IFERROR(__xludf.DUMMYFUNCTION("""COMPUTED_VALUE"""),"20374") -> 20374 | E2: =IFERROR(__xludf.DUMMYFUNCTION("""COMPUTED_VALUE"""),"FTI145DPTBR") -> FTI145DPTBR | F2: =IFERROR(__xludf.DUMMYFUNCTION("""COMPUTED_VALUE"""),"WI-FI") -> WI-FI | G2: =IFERROR(__xludf.DUMMYFUNCTION("""COMPUTED_VALUE"""),"NAO") -> NAO | H2: =IFERROR(__xludf.DUMMYFUNCTION("""COMPUTED_VALUE"""),"NAO") -> NAO | I2: =IFERROR(__xludf.DUMMYFUNCTION("""COMPUTED_VALUE"""),"EM ABERTO") -> EM ABERTO | J2: =IFERROR(__xludf.DUMMYFUNCTION("""COMPUTED_VALUE"""),"MINUANO") -> MINUANO | K2: =IFERROR(__xludf.DUMMYFUNCTION("""COMPUTED_VALUE"""),"SEM REDESPACHO") -> SEM REDESPACHO | P2: =IFERROR(__xludf.DUMMYFUNCTION("""COMPUTED_VALUE"""),"EXPRESSO SAO MIGUEL S/A / (049) 3361-6627Obs.Interna: Prazo de acordo com Mario via wats app. aguardar cliente confirmar transportadora. informar prazo de entrega/ fabricação das máquinas / E-mail para nota fiscal: , E-mail de cobrança: , Telefone para c"&"ontato") -> EXPRESSO SAO MIGUEL S/A / (049) 3361-6627Obs.Interna: Prazo de acordo com Mario via wats app. aguardar cliente confirmar transportadora. informar prazo de entrega/ fabricação das máquinas / E-mail para nota fiscal: , E-mail de cobrança: , Telefone para contato
A3: =IFERROR(__xludf.DUMMYFUNCTION("""COMPUTED_VALUE"""),"18812") -> 18812 | B3: =IFERROR(__xludf.DUMMYFUNCTION("""COMPUTED_VALUE"""),"LOJA DAS PISCINAS") -> LOJA DAS PISCINAS | C3: =IFERROR(__xludf.DUMMYFUNCTION("""COMPUTED_VALUE"""),0.0) -> 0 | E3: =IFERROR(__xludf.DUMMYFUNCTION("""COMPUTED_VALUE"""),"FTI45DPTBR") -> FTI45DPTBR | F3: =IFERROR(__xludf.DUMMYFUNCTION("""COMPUTED_VALUE"""),"WI-FI") -> WI-FI | G3: =IFERROR(__xludf.DUMMYFUNCTION("""COMPUTED_VALUE"""),"NAO") -> NAO | H3: =IFERROR(__xludf.DUMMYFUNCTION("""COMPUTED_VALUE"""),"NAO") -> NAO | I3: =IFERROR(__xludf.DUMMYFUNCTION("""COMPUTED_VALUE"""),"EM ABERTO") -> EM ABERTO | J3: =IFERROR(__xludf.DUMMYFUNCTION("""COMPUTED_VALUE"""),"EXPRESSO SAO MIGUEL") -> EXPRESSO SAO MIGUEL | K3: =IFERROR(__xludf.DUMMYFUNCTION("""COMPUTED_VALUE"""),"SEM REDESPACHO") -> SEM REDESPACHO | P3: =IFERROR(__xludf.DUMMYFUNCTION("""COMPUTED_VALUE"""),"EXPRESSO SAO MIGUEL S/A / (051) 3586-2013E-mail para nota fiscal: , E-mail de cobrança: , Telefone para contato") -> EXPRESSO SAO MIGUEL S/A / (051) 3586-2013E-mail para nota fiscal: , E-mail de cobrança: , Telefone para contato
A4: =IFERROR(__xludf.DUMMYFUNCTION("""COMPUTED_VALUE"""),"18857-A") -> 18857-A | B4: =IFERROR(__xludf.DUMMYFUNCTION("""COMPUTED_VALUE"""),"CASA DA PISCINA MATO GROSSO") -> CASA DA PISCINA MATO GROSSO | C4: =IFERROR(__xludf.DUMMYFUNCTION("""COMPUTED_VALUE"""),0.0) -> 0 | E4: =IFERROR(__xludf.DUMMYFUNCTION("""COMPUTED_VALUE"""),"FH40B60T") -> FH40B60T | F4: =IFERROR(__xludf.DUMMYFUNCTION("""COMPUTED_VALUE"""),"TOUCH") -> TOUCH | G4: =IFERROR(__xludf.DUMMYFUNCTION("""COMPUTED_VALUE"""),"SOBREPOR") -> SOBREPOR | H4: =IFERROR(__xludf.DUMMYFUNCTION("""COMPUTED_VALUE"""),"NAO") -> NAO | I4: =IFERROR(__xludf.DUMMYFUNCTION("""COMPUTED_VALUE"""),"EM ABERTO") -> EM ABERTO | J4: =IFERROR(__xludf.DUMMYFUNCTION("""COMPUTED_VALUE"""),"RODONAVES") -> RODONAVES | K4: =IFERROR(__xludf.DUMMYFUNCTION("""COMPUTED_VALUE"""),"SEM REDESPACHO") -> SEM REDESPACHO | P4: =IFERROR(__xludf.DUMMYFUNCTION("""COMPUTED_VALUE"""),"EXPRESSO SAO MIGUEL S/A / (051) 3586-2013Informação Adicional: TRANSPORTADORA: PICCOLI TRANSPORTES- CNPJ 01.496.359/0002-45 - Rua Viela Urga-nº557 -Bairro Vila Nova Bonsucesso- Guarulhos -cep 07175-332 SP - 1139880170 / Obs.Interna: AVISAR PRODUÇÃO- QUAD"&"RO DESLOCADO . / E-mail para nota fiscal: , E-mail de cobrança: , Telefone para contato") -> EXPRESSO SAO MIGUEL S/A / (051) 3586-2013Informação Adicional: TRANSPORTADORA: PICCOLI TRANSPORTES- CNPJ 01.496.359/0002-45 - Rua Viela Urga-nº557 -Bairro Vila Nova Bonsucesso- Guarulhos -cep 07175-332 SP - 1139880170 / Obs.Interna: AVISAR PRODUÇÃO- QUADRO DESLOCADO . / E-mail para nota fiscal: , E-mail de cobrança: , Telefone para contato
A5: =IFERROR(__xludf.DUMMYFUNCTION("""COMPUTED_VALUE"""),"18857-B") -> 18857-B | B5: =IFERROR(__xludf.DUMMYFUNCTION("""COMPUTED_VALUE"""),"CASA DA PISCINA MATO GROSSO") -> CASA DA PISCINA MATO GROSSO | C5: =IFERROR(__xludf.DUMMYFUNCTION("""COMPUTED_VALUE"""),0.0) -> 0 | D5: =IFERROR(__xludf.DUMMYFUNCTION("""COMPUTED_VALUE"""),20435.0) -> 20435 | E5: =IFERROR(__xludf.DUMMYFUNCTION("""COMPUTED_VALUE"""),"FH80B60T") -> FH80B60T | F5: =IFERROR(__xludf.DUMMYFUNCTION("""COMPUTED_VALUE"""),"TOUCH") -> TOUCH | G5: =IFERROR(__xludf.DUMMYFUNCTION("""COMPUTED_VALUE"""),"SOBREPOR") -> SOBREPOR | H5: =IFERROR(__xludf.DUMMYFUNCTION("""COMPUTED_VALUE"""),"NAO") -> NAO | I5: =IFERROR(__xludf.DUMMYFUNCTION("""COMPUTED_VALUE"""),"EM ABERTO") -> EM ABERTO | J5: =IFERROR(__xludf.DUMMYFUNCTION("""COMPUTED_VALUE"""),"RODONAVES") -> RODONAVES | K5: =IFERROR(__xludf.DUMMYFUNCTION("""COMPUTED_VALUE"""),"SEM REDESPACHO") -> SEM REDESPACHO | P5: =IFERROR(__xludf.DUMMYFUNCTION("""COMPUTED_VALUE"""),"EXPRESSO SAO MIGUEL S/A / (051) 3586-2013Informação Adicional: TRANSPORTADORA: PICCOLI TRANSPORTES- CNPJ 01.496.359/0002-45 - Rua Viela Urga-nº557 -Bairro Vila Nova Bonsucesso- Guarulhos -cep 07175-332 SP - 1139880170 / Obs.Interna: AVISAR PRODUÇÃO- QUAD"&"RO DESLOCADO . / E-mail para nota fiscal: , E-mail de cobrança: , Telefone para contato") -> EXPRESSO SAO MIGUEL S/A / (051) 3586-2013Informação Adicional: TRANSPORTADORA: PICCOLI TRANSPORTES- CNPJ 01.496.359/0002-45 - Rua Viela Urga-nº557 -Bairro Vila Nova Bonsucesso- Guarulhos -cep 07175-332 SP - 1139880170 / Obs.Interna: AVISAR PRODUÇÃO- QUADRO DESLOCADO . / E-mail para nota fiscal: , E-mail de cobrança: , Telefone para contato
A6: =IFERROR(__xludf.DUMMYFUNCTION("""COMPUTED_VALUE"""),"18859") -> 18859 | B6: =IFERROR(__xludf.DUMMYFUNCTION("""COMPUTED_VALUE"""),"AQUAVIL PISCINAS LTDA") -> AQUAVIL PISCINAS LTDA | C6: =IFERROR(__xludf.DUMMYFUNCTION("""COMPUTED_VALUE"""),0.0) -> 0 | D6: =IFERROR(__xludf.DUMMYFUNCTION("""COMPUTED_VALUE"""),"20373") -> 20373 | E6: =IFERROR(__xludf.DUMMYFUNCTION("""COMPUTED_VALUE"""),"FTI145DPTBR") -> FTI145DPTBR | F6: =IFERROR(__xludf.DUMMYFUNCTION("""COMPUTED_VALUE"""),"WI-FI") -> WI-FI | G6: =IFERROR(__xludf.DUMMYFUNCTION("""COMPUTED_VALUE"""),"NAO") -> NAO | H6: =IFERROR(__xludf.DUMMYFUNCTION("""COMPUTED_VALUE"""),"NAO") -> NAO | I6: =IFERROR(__xludf.DUMMYFUNCTION("""COMPUTED_VALUE"""),"EM ABERTO") -> EM ABERTO | J6: =IFERROR(__xludf.DUMMYFUNCTION("""COMPUTED_VALUE"""),"FITLOG") -> FITLOG | K6: =IFERROR(__xludf.DUMMYFUNCTION("""COMPUTED_VALUE"""),"SEM REDESPACHO") -> SEM REDESPACHO | P6: =IFERROR(__xludf.DUMMYFUNCTION("""COMPUTED_VALUE"""),"FITLOG TRANSPORTES E LOGISTICA LTDA / (048) 996277956E-mail para nota fiscal: , E-mail de cobrança: , Telefone para contato") -> FITLOG TRANSPORTES E LOGISTICA LTDA / (048) 996277956E-mail para nota fiscal: , E-mail de cobrança: , Telefone para contato
A7: =IFERROR(__xludf.DUMMYFUNCTION("""COMPUTED_VALUE"""),"18862") -> 18862 | B7: =IFERROR(__xludf.DUMMYFUNCTION("""COMPUTED_VALUE"""),"2 CORACOES PISCINAS E DECORACOES") -> 2 CORACOES PISCINAS E DECORACOES | C7: =IFERROR(__xludf.DUMMYFUNCTION("""COMPUTED_VALUE"""),0.0) -> 0 | E7: =IFERROR(__xludf.DUMMYFUNCTION("""COMPUTED_VALUE"""),"FTI45DPTBR") -> FTI45DPTBR | F7: =IFERROR(__xludf.DUMMYFUNCTION("""COMPUTED_VALUE"""),"WI-FI") -> WI-FI | G7: =IFERROR(__xludf.DUMMYFUNCTION("""COMPUTED_VALUE"""),"NAO") -> NAO | H7: =IFERROR(__xludf.DUMMYFUNCTION("""COMPUTED_VALUE"""),"NAO") -> NAO | I7: =IFERROR(__xludf.DUMMYFUNCTION("""COMPUTED_VALUE"""),"EM ABERTO") -> EM ABERTO | J7: =IFERROR(__xludf.DUMMYFUNCTION("""COMPUTED_VALUE"""),"EXPRESSO SAO MIGUEL") -> EXPRESSO SAO MIGUEL | K7: =IFERROR(__xludf.DUMMYFUNCTION("""COMPUTED_VALUE"""),"SEM REDESPACHO") -> SEM REDESPACHO | P7: =IFERROR(__xludf.DUMMYFUNCTION("""COMPUTED_VALUE"""),"EXPRESSO SAO MIGUEL S/A / (051) 3586-2013E-mail para nota fiscal: , E-mail de cobrança: , Telefone para contato") -> EXPRESSO SAO MIGUEL S/A / (051) 3586-2013E-mail para nota fiscal: , E-mail de cobrança: , Telefone para contato
A8: =IFERROR(__xludf.DUMMYFUNCTION("""COMPUTED_VALUE"""),"18867-A") -> 18867-A | B8: =IFERROR(__xludf.DUMMYFUNCTION("""COMPUTED_VALUE"""),"DJA COMERCIO DE PISCINAS LTDA - ME") -> DJA COMERCIO DE PISCINAS LTDA - ME | C8: =IFERROR(__xludf.DUMMYFUNCTION("""COMPUTED_VALUE"""),0.0) -> 0 | E8: =IFERROR(__xludf.DUMMYFUNCTION("""COMPUTED_VALUE"""),"FTI145DPTBR") -> FTI145DPTBR | F8: =IFERROR(__xludf.DUMMYFUNCTION("""COMPUTED_VALUE"""),"WI-FI") -> WI-FI | G8: =IFERROR(__xludf.DUMMYFUNCTION("""COMPUTED_VALUE"""),"NAO") -> NAO | H8: =IFERROR(__xludf.DUMMYFUNCTION("""COMPUTED_VALUE"""),"NAO") -> NAO | I8: =IFERROR(__xludf.DUMMYFUNCTION("""COMPUTED_VALUE"""),"EM ABERTO") -> EM ABERTO | J8: =IFERROR(__xludf.DUMMYFUNCTION("""COMPUTED_VALUE"""),"FITLOG") -> FITLOG | K8: =IFERROR(__xludf.DUMMYFUNCTION("""COMPUTED_VALUE"""),"SEM REDESPACHO") -> SEM REDESPACHO | P8: =IFERROR(__xludf.DUMMYFUNCTION("""COMPUTED_VALUE"""),"FITLOG TRANSPORTES E LOGISTICA LTDA / (048) 996277956Informação Adicional: Frete CIF / E-mail para nota fiscal: , E-mail de cobrança: , Telefone para contato") -> FITLOG TRANSPORTES E LOGISTICA LTDA / (048) 996277956Informação Adicional: Frete CIF / E-mail para nota fiscal: , E-mail de cobrança: , Telefone para contato
A9: =IFERROR(__xludf.DUMMYFUNCTION("""COMPUTED_VALUE"""),"18867-B") -> 18867-B | B9: =IFERROR(__xludf.DUMMYFUNCTION("""COMPUTED_VALUE"""),"DJA COMERCIO DE PISCINAS LTDA - ME") -> DJA COMERCIO DE PISCINAS LTDA - ME | C9: =IFERROR(__xludf.DUMMYFUNCTION("""COMPUTED_VALUE"""),0.0) -> 0 | E9: =IFERROR(__xludf.DUMMYFUNCTION("""COMPUTED_VALUE"""),"FTI145DPTBR") -> FTI145DPTBR | F9: =IFERROR(__xludf.DUMMYFUNCTION("""COMPUTED_VALUE"""),"WI-FI") -> WI-FI | G9: =IFERROR(__xludf.DUMMYFUNCTION("""COMPUTED_VALUE"""),"NAO") -> NAO | H9: =IFERROR(__xludf.DUMMYFUNCTION("""COMPUTED_VALUE"""),"NAO") -> NAO | I9: =IFERROR(__xludf.DUMMYFUNCTION("""COMPUTED_VALUE"""),"EM ABERTO") -> EM ABERTO | J9: =IFERROR(__xludf.DUMMYFUNCTION("""COMPUTED_VALUE"""),"FITLOG") -> FITLOG | K9: =IFERROR(__xludf.DUMMYFUNCTION("""COMPUTED_VALUE"""),"SEM REDESPACHO") -> SEM REDESPACHO | P9: =IFERROR(__xludf.DUMMYFUNCTION("""COMPUTED_VALUE"""),"FITLOG TRANSPORTES E LOGISTICA LTDA / (048) 996277956Informação Adicional: Frete CIF / E-mail para nota fiscal: , E-mail de cobrança: , Telefone para contato") -> FITLOG TRANSPORTES E LOGISTICA LTDA / (048) 996277956Informação Adicional: Frete CIF / E-mail para nota fiscal: , E-mail de cobrança: , Telefone para contato
A10: =IFERROR(__xludf.DUMMYFUNCTION("""COMPUTED_VALUE"""),"18871-B") -> 18871-B | B10: =IFERROR(__xludf.DUMMYFUNCTION("""COMPUTED_VALUE"""),"STEINFIBER") -> STEINFIBER | C10: =IFERROR(__xludf.DUMMYFUNCTION("""COMPUTED_VALUE"""),0.0) -> 0 | E10: =IFERROR(__xludf.DUMMYFUNCTION("""COMPUTED_VALUE"""),"FTI145LPTBR") -> FTI145LPTBR | F10: =IFERROR(__xludf.DUMMYFUNCTION("""COMPUTED_VALUE"""),"WI-FI") -> WI-FI | G10: =IFERROR(__xludf.DUMMYFUNCTION("""COMPUTED_VALUE"""),"NAO") -> NAO | H10: =IFERROR(__xludf.DUMMYFUNCTION("""COMPUTED_VALUE"""),"NAO") -> NAO | I10: =IFERROR(__xludf.DUMMYFUNCTION("""COMPUTED_VALUE"""),"EM ABERTO") -> EM ABERTO | J10: =IFERROR(__xludf.DUMMYFUNCTION("""COMPUTED_VALUE"""),"RETIRA") -> RETIRA | K10: =IFERROR(__xludf.DUMMYFUNCTION("""COMPUTED_VALUE"""),"SEM REDESPACHO") -> SEM REDESPACHO | P10: =IFERROR(__xludf.DUMMYFUNCTION("""COMPUTED_VALUE"""),"CLIENTE RETIRA / (0) Informação Adicional: PREÇO NEGOCIADO R$ 18.600,00 - ALTERAR NO PEDIDO - AUTORIZADO POR PRISCILLA ENTREGA: 01 MÁQUINA DIA 20/10 E AS OUTRAS 06 MAXIMO DIA 05/11 / E-mail para nota fiscal: , E-mail de cobrança: , Telefone para contat"&"o") -> CLIENTE RETIRA / (0) Informação Adicional: PREÇO NEGOCIADO R$ 18.600,00 - ALTERAR NO PEDIDO - AUTORIZADO POR PRISCILLA ENTREGA: 01 MÁQUINA DIA 20/10 E AS OUTRAS 06 MAXIMO DIA 05/11 / E-mail para nota fiscal: , E-mail de cobrança: , Telefone para contato
A11: =IFERROR(__xludf.DUMMYFUNCTION("""COMPUTED_VALUE"""),"18871-C") -> 18871-C | B11: =IFERROR(__xludf.DUMMYFUNCTION("""COMPUTED_VALUE"""),"STEINFIBER") -> STEINFIBER | C11: =IFERROR(__xludf.DUMMYFUNCTION("""COMPUTED_VALUE"""),0.0) -> 0 | E11: =IFERROR(__xludf.DUMMYFUNCTION("""COMPUTED_VALUE"""),"FTI145LPTBR") -> FTI145LPTBR | F11: =IFERROR(__xludf.DUMMYFUNCTION("""COMPUTED_VALUE"""),"WI-FI") -> WI-FI | G11: =IFERROR(__xludf.DUMMYFUNCTION("""COMPUTED_VALUE"""),"NAO") -> NAO | H11: =IFERROR(__xludf.DUMMYFUNCTION("""COMPUTED_VALUE"""),"NAO") -> NAO | I11: =IFERROR(__xludf.DUMMYFUNCTION("""COMPUTED_VALUE"""),"EM ABERTO") -> EM ABERTO | J11: =IFERROR(__xludf.DUMMYFUNCTION("""COMPUTED_VALUE"""),"RETIRA") -> RETIRA | K11: =IFERROR(__xludf.DUMMYFUNCTION("""COMPUTED_VALUE"""),"SEM REDESPACHO") -> SEM REDESPACHO | P11: =IFERROR(__xludf.DUMMYFUNCTION("""COMPUTED_VALUE"""),"CLIENTE RETIRA / (0) Informação Adicional: PREÇO NEGOCIADO R$ 18.600,00 - ALTERAR NO PEDIDO - AUTORIZADO POR PRISCILLA ENTREGA: 01 MÁQUINA DIA 20/10 E AS OUTRAS 06 MAXIMO DIA 05/11 / E-mail para nota fiscal: , E-mail de cobrança: , Telefone para contat"&"o") -> CLIENTE RETIRA / (0) Informação Adicional: PREÇO NEGOCIADO R$ 18.600,00 - ALTERAR NO PEDIDO - AUTORIZADO POR PRISCILLA ENTREGA: 01 MÁQUINA DIA 20/10 E AS OUTRAS 06 MAXIMO DIA 05/11 / E-mail para nota fiscal: , E-mail de cobrança: , Telefone para contato
A12: =IFERROR(__xludf.DUMMYFUNCTION("""COMPUTED_VALUE"""),"18871-D") -> 18871-D | B12: =IFERROR(__xludf.DUMMYFUNCTION("""COMPUTED_VALUE"""),"STEINFIBER") -> STEINFIBER | C12: =IFERROR(__xludf.DUMMYFUNCTION("""COMPUTED_VALUE"""),0.0) -> 0 | E12: =IFERROR(__xludf.DUMMYFUNCTION("""COMPUTED_VALUE"""),"FTI145LPTBR") -> FTI145LPTBR | F12: =IFERROR(__xludf.DUMMYFUNCTION("""COMPUTED_VALUE"""),"WI-FI") -> WI-FI | G12: =IFERROR(__xludf.DUMMYFUNCTION("""COMPUTED_VALUE"""),"NAO") -> NAO | H12: =IFERROR(__xludf.DUMMYFUNCTION("""COMPUTED_VALUE"""),"NAO") -> NAO | I12: =IFERROR(__xludf.DUMMYFUNCTION("""COMPUTED_VALUE"""),"EM ABERTO") -> EM ABERTO | J12: =IFERROR(__xludf.DUMMYFUNCTION("""COMPUTED_VALUE"""),"RETIRA") -> RETIRA | K12: =IFERROR(__xludf.DUMMYFUNCTION("""COMPUTED_VALUE"""),"SEM REDESPACHO") -> SEM REDESPACHO | P12: =IFERROR(__xludf.DUMMYFUNCTION("""COMPUTED_VALUE"""),"CLIENTE RETIRA / (0) Informação Adicional: PREÇO NEGOCIADO R$ 18.600,00 - ALTERAR NO PEDIDO - AUTORIZADO POR PRISCILLA ENTREGA: 01 MÁQUINA DIA 20/10 E AS OUTRAS 06 MAXIMO DIA 05/11 / E-mail para nota fiscal: , E-mail de cobrança: , Telefone para contat"&"o") -> CLIENTE RETIRA / (0) Informação Adicional: PREÇO NEGOCIADO R$ 18.600,00 - ALTERAR NO PEDIDO - AUTORIZADO POR PRISCILLA ENTREGA: 01 MÁQUINA DIA 20/10 E AS OUTRAS 06 MAXIMO DIA 05/11 / E-mail para nota fiscal: , E-mail de cobrança: , Telefone para contato
A13: =IFERROR(__xludf.DUMMYFUNCTION("""COMPUTED_VALUE"""),"18871-E") -> 18871-E | B13: =IFERROR(__xludf.DUMMYFUNCTION("""COMPUTED_VALUE"""),"STEINFIBER") -> STEINFIBER | C13: =IFERROR(__xludf.DUMMYFUNCTION("""COMPUTED_VALUE"""),0.0) -> 0 | E13: =IFERROR(__xludf.DUMMYFUNCTION("""COMPUTED_VALUE"""),"FTI145LPTBR") -> FTI145LPTBR | F13: =IFERROR(__xludf.DUMMYFUNCTION("""COMPUTED_VALUE"""),"WI-FI") -> WI-FI | G13: =IFERROR(__xludf.DUMMYFUNCTION("""COMPUTED_VALUE"""),"NAO") -> NAO | H13: =IFERROR(__xludf.DUMMYFUNCTION("""COMPUTED_VALUE"""),"NAO") -> NAO | I13: =IFERROR(__xludf.DUMMYFUNCTION("""COMPUTED_VALUE"""),"EM ABERTO") -> EM ABERTO | J13: =IFERROR(__xludf.DUMMYFUNCTION("""COMPUTED_VALUE"""),"RETIRA") -> RETIRA | K13: =IFERROR(__xludf.DUMMYFUNCTION("""COMPUTED_VALUE"""),"SEM REDESPACHO") -> SEM REDESPACHO | P13: =IFERROR(__xludf.DUMMYFUNCTION("""COMPUTED_VALUE"""),"CLIENTE RETIRA / (0) Informação Adicional: PREÇO NEGOCIADO R$ 18.600,00 - ALTERAR NO PEDIDO - AUTORIZADO POR PRISCILLA ENTREGA: 01 MÁQUINA DIA 20/10 E AS OUTRAS 06 MAXIMO DIA 05/11 / E-mail para nota fiscal: , E-mail de cobrança: , Telefone para contat"&"o") -> CLIENTE RETIRA / (0) Informação Adicional: PREÇO NEGOCIADO R$ 18.600,00 - ALTERAR NO PEDIDO - AUTORIZADO POR PRISCILLA ENTREGA: 01 MÁQUINA DIA 20/10 E AS OUTRAS 06 MAXIMO DIA 05/11 / E-mail para nota fiscal: , E-mail de cobrança: , Telefone para contato
A14: =IFERROR(__xludf.DUMMYFUNCTION("""COMPUTED_VALUE"""),"18871-F") -> 18871-F | B14: =IFERROR(__xludf.DUMMYFUNCTION("""COMPUTED_VALUE"""),"STEINFIBER") -> STEINFIBER | C14: =IFERROR(__xludf.DUMMYFUNCTION("""COMPUTED_VALUE"""),0.0) -> 0 | E14: =IFERROR(__xludf.DUMMYFUNCTION("""COMPUTED_VALUE"""),"FTI145LPTBR") -> FTI145LPTBR | F14: =IFERROR(__xludf.DUMMYFUNCTION("""COMPUTED_VALUE"""),"WI-FI") -> WI-FI | G14: =IFERROR(__xludf.DUMMYFUNCTION("""COMPUTED_VALUE"""),"NAO") -> NAO | H14: =IFERROR(__xludf.DUMMYFUNCTION("""COMPUTED_VALUE"""),"NAO") -> NAO | I14: =IFERROR(__xludf.DUMMYFUNCTION("""COMPUTED_VALUE"""),"EM ABERTO") -> EM ABERTO | J14: =IFERROR(__xludf.DUMMYFUNCTION("""COMPUTED_VALUE"""),"RETIRA") -> RETIRA | K14: =IFERROR(__xludf.DUMMYFUNCTION("""COMPUTED_VALUE"""),"SEM REDESPACHO") -> SEM REDESPACHO | P14: =IFERROR(__xludf.DUMMYFUNCTION("""COMPUTED_VALUE"""),"CLIENTE RETIRA / (0) Informação Adicional: PREÇO NEGOCIADO R$ 18.600,00 - ALTERAR NO PEDIDO - AUTORIZADO POR PRISCILLA ENTREGA: 01 MÁQUINA DIA 20/10 E AS OUTRAS 06 MAXIMO DIA 05/11 / E-mail para nota fiscal: , E-mail de cobrança: , Telefone para contat"&"o") -> CLIENTE RETIRA / (0) Informação Adicional: PREÇO NEGOCIADO R$ 18.600,00 - ALTERAR NO PEDIDO - AUTORIZADO POR PRISCILLA ENTREGA: 01 MÁQUINA DIA 20/10 E AS OUTRAS 06 MAXIMO DIA 05/11 / E-mail para nota fiscal: , E-mail de cobrança: , Telefone para contato
A15: =IFERROR(__xludf.DUMMYFUNCTION("""COMPUTED_VALUE"""),"18871-G") -> 18871-G | B15: =IFERROR(__xludf.DUMMYFUNCTION("""COMPUTED_VALUE"""),"STEINFIBER") -> STEINFIBER | C15: =IFERROR(__xludf.DUMMYFUNCTION("""COMPUTED_VALUE"""),0.0) -> 0 | E15: =IFERROR(__xludf.DUMMYFUNCTION("""COMPUTED_VALUE"""),"FTI145LPTBR") -> FTI145LPTBR | F15: =IFERROR(__xludf.DUMMYFUNCTION("""COMPUTED_VALUE"""),"WI-FI") -> WI-FI | G15: =IFERROR(__xludf.DUMMYFUNCTION("""COMPUTED_VALUE"""),"NAO") -> NAO | H15: =IFERROR(__xludf.DUMMYFUNCTION("""COMPUTED_VALUE"""),"NAO") -> NAO | I15: =IFERROR(__xludf.DUMMYFUNCTION("""COMPUTED_VALUE"""),"EM ABERTO") -> EM ABERTO | J15: =IFERROR(__xludf.DUMMYFUNCTION("""COMPUTED_VALUE"""),"RETIRA") -> RETIRA | K15: =IFERROR(__xludf.DUMMYFUNCTION("""COMPUTED_VALUE"""),"SEM REDESPACHO") -> SEM REDESPACHO | P15: =IFERROR(__xludf.DUMMYFUNCTION("""COMPUTED_VALUE"""),"CLIENTE RETIRA / (0) Informação Adicional: PREÇO NEGOCIADO R$ 18.600,00 - ALTERAR NO PEDIDO - AUTORIZADO POR PRISCILLA ENTREGA: 01 MÁQUINA DIA 20/10 E AS OUTRAS 06 MAXIMO DIA 05/11 / E-mail para nota fiscal: , E-mail de cobrança: , Telefone para contat"&"o") -> CLIENTE RETIRA / (0) Informação Adicional: PREÇO NEGOCIADO R$ 18.600,00 - ALTERAR NO PEDIDO - AUTORIZADO POR PRISCILLA ENTREGA: 01 MÁQUINA DIA 20/10 E AS OUTRAS 06 MAXIMO DIA 05/11 / E-mail para nota fiscal: , E-mail de cobrança: , Telefone para contato
A16: =IFERROR(__xludf.DUMMYFUNCTION("""COMPUTED_VALUE"""),"18886") -> 18886 | B16: =IFERROR(__xludf.DUMMYFUNCTION("""COMPUTED_VALUE"""),"VITAL PISCINAS") -> VITAL PISCINAS | C16: =IFERROR(__xludf.DUMMYFUNCTION("""COMPUTED_VALUE"""),0.0) -> 0 | D16: =IFERROR(__xludf.DUMMYFUNCTION("""COMPUTED_VALUE"""),20375.0) -> 20375 | E16: =IFERROR(__xludf.DUMMYFUNCTION("""COMPUTED_VALUE"""),"FTI145DPTBR") -> FTI145DPTBR | F16: =IFERROR(__xludf.DUMMYFUNCTION("""COMPUTED_VALUE"""),"WI-FI") -> WI-FI | G16: =IFERROR(__xludf.DUMMYFUNCTION("""COMPUTED_VALUE"""),"NAO") -> NAO | H16: =IFERROR(__xludf.DUMMYFUNCTION("""COMPUTED_VALUE"""),"NAO") -> NAO | I16: =IFERROR(__xludf.DUMMYFUNCTION("""COMPUTED_VALUE"""),"EM ABERTO") -> EM ABERTO | J16: =IFERROR(__xludf.DUMMYFUNCTION("""COMPUTED_VALUE"""),"ACEVILLE") -> ACEVILLE | K16: =IFERROR(__xludf.DUMMYFUNCTION("""COMPUTED_VALUE"""),"SEM REDESPACHO") -> SEM REDESPACHO | P16: =IFERROR(__xludf.DUMMYFUNCTION("""COMPUTED_VALUE"""),"ACEVILLE TRANSPORTES LTDA / (048) 99823-5770E-mail para nota fiscal: , E-mail de cobrança: , Telefone para contato") -> ACEVILLE TRANSPORTES LTDA / (048) 99823-5770E-mail para nota fiscal: , E-mail de cobrança: , Telefone para contato
A17: =IFERROR(__xludf.DUMMYFUNCTION("""COMPUTED_VALUE"""),"18911") -> 18911 | B17: =IFERROR(__xludf.DUMMYFUNCTION("""COMPUTED_VALUE"""),"DEPOSITO BEIRA RIO") -> DEPOSITO BEIRA RIO | C17: =IFERROR(__xludf.DUMMYFUNCTION("""COMPUTED_VALUE"""),0.0) -> 0 | E17: =IFERROR(__xludf.DUMMYFUNCTION("""COMPUTED_VALUE"""),"FTI45DPTBR") -> FTI45DPTBR | F17: =IFERROR(__xludf.DUMMYFUNCTION("""COMPUTED_VALUE"""),"WI-FI") -> WI-FI | G17: =IFERROR(__xludf.DUMMYFUNCTION("""COMPUTED_VALUE"""),"NAO") -> NAO | H17: =IFERROR(__xludf.DUMMYFUNCTION("""COMPUTED_VALUE"""),"NAO") -> NAO | I17: =IFERROR(__xludf.DUMMYFUNCTION("""COMPUTED_VALUE"""),"EM ABERTO") -> EM ABERTO | J17: =IFERROR(__xludf.DUMMYFUNCTION("""COMPUTED_VALUE"""),"RODONAVES") -> RODONAVES | K17: =IFERROR(__xludf.DUMMYFUNCTION("""COMPUTED_VALUE"""),"SEM REDESPACHO") -> SEM REDESPACHO | P17: =IFERROR(__xludf.DUMMYFUNCTION("""COMPUTED_VALUE"""),"Pedido gerado através do PedidoEletronico.com - Transportadora / telefone: RODONAVES TRANSPORTES E ENCOMENDAS LTDA / (016) 3965-2141E-mail para nota fiscal: , E-mail de cobrança: , Telefone para contato") -> Pedido gerado através do PedidoEletronico.com - Transportadora / telefone: RODONAVES TRANSPORTES E ENCOMENDAS LTDA / (016) 3965-2141E-mail para nota fiscal: , E-mail de cobrança: , Telefone para contato
A18: =IFERROR(__xludf.DUMMYFUNCTION("""COMPUTED_VALUE"""),"18923-A") -> 18923-A | B18: =IFERROR(__xludf.DUMMYFUNCTION("""COMPUTED_VALUE"""),"HYDRONIC SOLUTIONS") -> HYDRONIC SOLUTIONS | C18: =IFERROR(__xludf.DUMMYFUNCTION("""COMPUTED_VALUE"""),0.0) -> 0 | E18: =IFERROR(__xludf.DUMMYFUNCTION("""COMPUTED_VALUE"""),"FH80F60W") -> FH80F60W | G18: =IFERROR(__xludf.DUMMYFUNCTION("""COMPUTED_VALUE"""),"NAO") -> NAO | H18: =IFERROR(__xludf.DUMMYFUNCTION("""COMPUTED_VALUE"""),"NAO") -> NAO | I18: =IFERROR(__xludf.DUMMYFUNCTION("""COMPUTED_VALUE"""),"EM ABERTO") -> EM ABERTO | J18: =IFERROR(__xludf.DUMMYFUNCTION("""COMPUTED_VALUE"""),"FITLOG") -> FITLOG | K18: =IFERROR(__xludf.DUMMYFUNCTION("""COMPUTED_VALUE"""),"SEM REDESPACHO") -> SEM REDESPACHO | P18: =IFERROR(__xludf.DUMMYFUNCTION("""COMPUTED_VALUE"""),"Pedido gerado através do PedidoEletronico.com - Transportadora / telefone: FITLOG TRANSPORTES E LOGISTICA LTDA / (048) 996277956Obs.Interna: entrega futura. Entregar hotel BIARRITZ COPACABANA Rua Aires Saldanha 54 Copacabana cep 22440 032 RJ . Maquinas "&"ja implantadas anteriormente. Pedido para correção de endereço de entrega . Ligar para o Luiz antes de entregar 21 9 6518 9999 / E-mail para nota fiscal: , E-mail de cobrança: , Telefone para contato") -> Pedido gerado através do PedidoEletronico.com - Transportadora / telefone: FITLOG TRANSPORTES E LOGISTICA LTDA / (048) 996277956Obs.Interna: entrega futura. Entregar hotel BIARRITZ COPACABANA Rua Aires Saldanha 54 Copacabana cep 22440 032 RJ . Maquinas ja implantadas anteriormente. Pedido para correção de endereço de entrega . Ligar para o Luiz antes de entregar 21 9 6518 9999 / E-mail para nota fiscal: , E-mail de cobrança: , Telefone para contato
A19: =IFERROR(__xludf.DUMMYFUNCTION("""COMPUTED_VALUE"""),"18932-A") -> 18932-A | B19: =IFERROR(__xludf.DUMMYFUNCTION("""COMPUTED_VALUE"""),"INFRAH ENGENHARIA , INSTALACOES E SISTEMAS DE AQUECIMENTO LTDA") -> INFRAH ENGENHARIA , INSTALACOES E SISTEMAS DE AQUECIMENTO LTDA | C19: =IFERROR(__xludf.DUMMYFUNCTION("""COMPUTED_VALUE"""),0.0) -> 0 | E19: =IFERROR(__xludf.DUMMYFUNCTION("""COMPUTED_VALUE"""),"FH160L60T") -> FH160L60T | F19: =IFERROR(__xludf.DUMMYFUNCTION("""COMPUTED_VALUE"""),"TOUCH") -> TOUCH | G19: =IFERROR(__xludf.DUMMYFUNCTION("""COMPUTED_VALUE"""),"NAO") -> NAO | H19: =IFERROR(__xludf.DUMMYFUNCTION("""COMPUTED_VALUE"""),"NAO") -> NAO | I19: =IFERROR(__xludf.DUMMYFUNCTION("""COMPUTED_VALUE"""),"EM ABERTO") -> EM ABERTO | J19: =IFERROR(__xludf.DUMMYFUNCTION("""COMPUTED_VALUE"""),"FITLOG") -> FITLOG | K19: =IFERROR(__xludf.DUMMYFUNCTION("""COMPUTED_VALUE"""),"SEM REDESPACHO") -> SEM REDESPACHO | P19: =IFERROR(__xludf.DUMMYFUNCTION("""COMPUTED_VALUE"""),"Pedido reprocessado ao alterar dados do cliente 21/10/2025 14:08:08 usuário: P000697112 ABATER O VALOR DE R$ 60.000,00 DA COMISSÃO QUE A INFRAH TEM A RECEBER DO HOTEL VILLA LOBOS E PARCELAR O RESTANTE. CONVERSAR COM A PRISCILLA, POIS ESSE PEDIDO SAIRÁ CO"&"M UM VALOR DE NF. MENOR. Pedido gerado através do PedidoEletronico.com - Transportadora / telefone: FITLOG TRANSPORTES E LOGISTICA LTDA / (048) 996277956Informação Adicional: ENDEREÇO DE ENTREGA: HOTEL ÍBIS BUDGET PAULISTA - RUA DA CONSOLAÇÃO, 2.303 - CO"&"NSOLAÇÃO - SÃO PAULO - SP - CEP: 01301-100, LIGAR PARA O ALISSON ANTES DE ENTREGAR - (11) 9 9473 5150. / E-mail para nota fiscal: , E-mail de cobrança: , Telefone para contato") -> Pedido reprocessado ao alterar dados do cliente 21/10/2025 14:08:08 usuário: P000697112 ABATER O VALOR DE R$ 60.000,00 DA COMISSÃO QUE A INFRAH TEM A RECEBER DO HOTEL VILLA LOBOS E PARCELAR O RESTANTE. CONVERSAR COM A PRISCILLA, POIS ESSE PEDIDO SAIRÁ COM UM VALOR DE NF. MENOR. Pedido gerado através do PedidoEletronico.com - Transportadora / telefone: FITLOG TRANSPORTES E LOGISTICA LTDA / (048) 996277956Informação Adicional: ENDEREÇO DE ENTREGA: HOTEL ÍBIS BUDGET PAULISTA - RUA DA CONSOLAÇÃO, 2.303 - CONSOLAÇÃO - SÃO PAULO - SP - CEP: 01301-100, LIGAR PARA O ALISSON ANTES DE ENTREGAR - (11) 9 9473 5150. / E-mail para nota fiscal: , E-mail de cobrança: , Telefone para contato
A20: =IFERROR(__xludf.DUMMYFUNCTION("""COMPUTED_VALUE"""),"18932-B") -> 18932-B | B20: =IFERROR(__xludf.DUMMYFUNCTION("""COMPUTED_VALUE"""),"INFRAH ENGENHARIA , INSTALACOES E SISTEMAS DE AQUECIMENTO LTDA") -> INFRAH ENGENHARIA , INSTALACOES E SISTEMAS DE AQUECIMENTO LTDA | C20: =IFERROR(__xludf.DUMMYFUNCTION("""COMPUTED_VALUE"""),0.0) -> 0 | E20: =IFERROR(__xludf.DUMMYFUNCTION("""COMPUTED_VALUE"""),"FH160L60T") -> FH160L60T | F20: =IFERROR(__xludf.DUMMYFUNCTION("""COMPUTED_VALUE"""),"TOUCH") -> TOUCH | G20: =IFERROR(__xludf.DUMMYFUNCTION("""COMPUTED_VALUE"""),"NAO") -> NAO | H20: =IFERROR(__xludf.DUMMYFUNCTION("""COMPUTED_VALUE"""),"NAO") -> NAO | I20: =IFERROR(__xludf.DUMMYFUNCTION("""COMPUTED_VALUE"""),"EM ABERTO") -> EM ABERTO | J20: =IFERROR(__xludf.DUMMYFUNCTION("""COMPUTED_VALUE"""),"FITLOG") -> FITLOG | K20: =IFERROR(__xludf.DUMMYFUNCTION("""COMPUTED_VALUE"""),"SEM REDESPACHO") -> SEM REDESPACHO | P20: =IFERROR(__xludf.DUMMYFUNCTION("""COMPUTED_VALUE"""),"Pedido reprocessado ao alterar dados do cliente 21/10/2025 14:08:08 usuário: P000697112 ABATER O VALOR DE R$ 60.000,00 DA COMISSÃO QUE A INFRAH TEM A RECEBER DO HOTEL VILLA LOBOS E PARCELAR O RESTANTE. CONVERSAR COM A PRISCILLA, POIS ESSE PEDIDO SAIRÁ CO"&"M UM VALOR DE NF. MENOR. Pedido gerado através do PedidoEletronico.com - Transportadora / telefone: FITLOG TRANSPORTES E LOGISTICA LTDA / (048) 996277956Informação Adicional: ENDEREÇO DE ENTREGA: HOTEL ÍBIS BUDGET PAULISTA - RUA DA CONSOLAÇÃO, 2.303 - CO"&"NSOLAÇÃO - SÃO PAULO - SP - CEP: 01301-100, LIGAR PARA O ALISSON ANTES DE ENTREGAR - (11) 9 9473 5150. / E-mail para nota fiscal: , E-mail de cobrança: , Telefone para contato") -> Pedido reprocessado ao alterar dados do cliente 21/10/2025 14:08:08 usuário: P000697112 ABATER O VALOR DE R$ 60.000,00 DA COMISSÃO QUE A INFRAH TEM A RECEBER DO HOTEL VILLA LOBOS E PARCELAR O RESTANTE. CONVERSAR COM A PRISCILLA, POIS ESSE PEDIDO SAIRÁ COM UM VALOR DE NF. MENOR. Pedido gerado através do PedidoEletronico.com - Transportadora / telefone: FITLOG TRANSPORTES E LOGISTICA LTDA / (048) 996277956Informação Adicional: ENDEREÇO DE ENTREGA: HOTEL ÍBIS BUDGET PAULISTA - RUA DA CONSOLAÇÃO, 2.303 - CONSOLAÇÃO - SÃO PAULO - SP - CEP: 01301-100, LIGAR PARA O ALISSON ANTES DE ENTREGAR - (11) 9 9473 5150. / E-mail para nota fiscal: , E-mail de cobrança: , Telefone para contato
A21: =IFERROR(__xludf.DUMMYFUNCTION("""COMPUTED_VALUE"""),"18932-C") -> 18932-C | B21: =IFERROR(__xludf.DUMMYFUNCTION("""COMPUTED_VALUE"""),"INFRAH ENGENHARIA , INSTALACOES E SISTEMAS DE AQUECIMENTO LTDA") -> INFRAH ENGENHARIA , INSTALACOES E SISTEMAS DE AQUECIMENTO LTDA | C21: =IFERROR(__xludf.DUMMYFUNCTION("""COMPUTED_VALUE"""),0.0) -> 0 | E21: =IFERROR(__xludf.DUMMYFUNCTION("""COMPUTED_VALUE"""),"FH160L60T") -> FH160L60T | F21: =IFERROR(__xludf.DUMMYFUNCTION("""COMPUTED_VALUE"""),"TOUCH") -> TOUCH | G21: =IFERROR(__xludf.DUMMYFUNCTION("""COMPUTED_VALUE"""),"NAO") -> NAO | H21: =IFERROR(__xludf.DUMMYFUNCTION("""COMPUTED_VALUE"""),"NAO") -> NAO | I21: =IFERROR(__xludf.DUMMYFUNCTION("""COMPUTED_VALUE"""),"EM ABERTO") -> EM ABERTO | J21: =IFERROR(__xludf.DUMMYFUNCTION("""COMPUTED_VALUE"""),"FITLOG") -> FITLOG | K21: =IFERROR(__xludf.DUMMYFUNCTION("""COMPUTED_VALUE"""),"SEM REDESPACHO") -> SEM REDESPACHO | P21: =IFERROR(__xludf.DUMMYFUNCTION("""COMPUTED_VALUE"""),"Pedido reprocessado ao alterar dados do cliente 21/10/2025 14:08:08 usuário: P000697112 ABATER O VALOR DE R$ 60.000,00 DA COMISSÃO QUE A INFRAH TEM A RECEBER DO HOTEL VILLA LOBOS E PARCELAR O RESTANTE. CONVERSAR COM A PRISCILLA, POIS ESSE PEDIDO SAIRÁ CO"&"M UM VALOR DE NF. MENOR. Pedido gerado através do PedidoEletronico.com - Transportadora / telefone: FITLOG TRANSPORTES E LOGISTICA LTDA / (048) 996277956Informação Adicional: ENDEREÇO DE ENTREGA: HOTEL ÍBIS BUDGET PAULISTA - RUA DA CONSOLAÇÃO, 2.303 - CO"&"NSOLAÇÃO - SÃO PAULO - SP - CEP: 01301-100, LIGAR PARA O ALISSON ANTES DE ENTREGAR - (11) 9 9473 5150. / E-mail para nota fiscal: , E-mail de cobrança: , Telefone para contato") -> Pedido reprocessado ao alterar dados do cliente 21/10/2025 14:08:08 usuário: P000697112 ABATER O VALOR DE R$ 60.000,00 DA COMISSÃO QUE A INFRAH TEM A RECEBER DO HOTEL VILLA LOBOS E PARCELAR O RESTANTE. CONVERSAR COM A PRISCILLA, POIS ESSE PEDIDO SAIRÁ COM UM VALOR DE NF. MENOR. Pedido gerado através do PedidoEletronico.com - Transportadora / telefone: FITLOG TRANSPORTES E LOGISTICA LTDA / (048) 996277956Informação Adicional: ENDEREÇO DE ENTREGA: HOTEL ÍBIS BUDGET PAULISTA - RUA DA CONSOLAÇÃO, 2.303 - CONSOLAÇÃO - SÃO PAULO - SP - CEP: 01301-100, LIGAR PARA O ALISSON ANTES DE ENTREGAR - (11) 9 9473 5150. / E-mail para nota fiscal: , E-mail de cobrança: , Telefone para contato
A22: =IFERROR(__xludf.DUMMYFUNCTION("""COMPUTED_VALUE"""),"18932-D") -> 18932-D | B22: =IFERROR(__xludf.DUMMYFUNCTION("""COMPUTED_VALUE"""),"INFRAH ENGENHARIA , INSTALACOES E SISTEMAS DE AQUECIMENTO LTDA") -> INFRAH ENGENHARIA , INSTALACOES E SISTEMAS DE AQUECIMENTO LTDA | C22: =IFERROR(__xludf.DUMMYFUNCTION("""COMPUTED_VALUE"""),0.0) -> 0 | E22: =IFERROR(__xludf.DUMMYFUNCTION("""COMPUTED_VALUE"""),"FH160L60T") -> FH160L60T | F22: =IFERROR(__xludf.DUMMYFUNCTION("""COMPUTED_VALUE"""),"TOUCH") -> TOUCH | G22: =IFERROR(__xludf.DUMMYFUNCTION("""COMPUTED_VALUE"""),"NAO") -> NAO | H22: =IFERROR(__xludf.DUMMYFUNCTION("""COMPUTED_VALUE"""),"NAO") -> NAO | I22: =IFERROR(__xludf.DUMMYFUNCTION("""COMPUTED_VALUE"""),"EM ABERTO") -> EM ABERTO | J22: =IFERROR(__xludf.DUMMYFUNCTION("""COMPUTED_VALUE"""),"FITLOG") -> FITLOG | K22: =IFERROR(__xludf.DUMMYFUNCTION("""COMPUTED_VALUE"""),"SEM REDESPACHO") -> SEM REDESPACHO | P22: =IFERROR(__xludf.DUMMYFUNCTION("""COMPUTED_VALUE"""),"Pedido reprocessado ao alterar dados do cliente 21/10/2025 14:08:08 usuário: P000697112 ABATER O VALOR DE R$ 60.000,00 DA COMISSÃO QUE A INFRAH TEM A RECEBER DO HOTEL VILLA LOBOS E PARCELAR O RESTANTE. CONVERSAR COM A PRISCILLA, POIS ESSE PEDIDO SAIRÁ CO"&"M UM VALOR DE NF. MENOR. Pedido gerado através do PedidoEletronico.com - Transportadora / telefone: FITLOG TRANSPORTES E LOGISTICA LTDA / (048) 996277956Informação Adicional: ENDEREÇO DE ENTREGA: HOTEL ÍBIS BUDGET PAULISTA - RUA DA CONSOLAÇÃO, 2.303 - CO"&"NSOLAÇÃO - SÃO PAULO - SP - CEP: 01301-100, LIGAR PARA O ALISSON ANTES DE ENTREGAR - (11) 9 9473 5150. / E-mail para nota fiscal: , E-mail de cobrança: , Telefone para contato") -> Pedido reprocessado ao alterar dados do cliente 21/10/2025 14:08:08 usuário: P000697112 ABATER O VALOR DE R$ 60.000,00 DA COMISSÃO QUE A INFRAH TEM A RECEBER DO HOTEL VILLA LOBOS E PARCELAR O RESTANTE. CONVERSAR COM A PRISCILLA, POIS ESSE PEDIDO SAIRÁ COM UM VALOR DE NF. MENOR. Pedido gerado através do PedidoEletronico.com - Transportadora / telefone: FITLOG TRANSPORTES E LOGISTICA LTDA / (048) 996277956Informação Adicional: ENDEREÇO DE ENTREGA: HOTEL ÍBIS BUDGET PAULISTA - RUA DA CONSOLAÇÃO, 2.303 - CONSOLAÇÃO - SÃO PAULO - SP - CEP: 01301-100, LIGAR PARA O ALISSON ANTES DE ENTREGAR - (11) 9 9473 5150. / E-mail para nota fiscal: , E-mail de cobrança: , Telefone para contato
A23: =IFERROR(__xludf.DUMMYFUNCTION("""COMPUTED_VALUE"""),"18923-B") -> 18923-B | B23: =IFERROR(__xludf.DUMMYFUNCTION("""COMPUTED_VALUE"""),"HYDRONIC SOLUTIONS") -> HYDRONIC SOLUTIONS | C23: =IFERROR(__xludf.DUMMYFUNCTION("""COMPUTED_VALUE"""),0.0) -> 0 | E23: =IFERROR(__xludf.DUMMYFUNCTION("""COMPUTED_VALUE"""),"FH80F60W") -> FH80F60W | G23: =IFERROR(__xludf.DUMMYFUNCTION("""COMPUTED_VALUE"""),"NAO") -> NAO | H23: =IFERROR(__xludf.DUMMYFUNCTION("""COMPUTED_VALUE"""),"NAO") -> NAO | I23: =IFERROR(__xludf.DUMMYFUNCTION("""COMPUTED_VALUE"""),"EM ABERTO") -> EM ABERTO | J23: =IFERROR(__xludf.DUMMYFUNCTION("""COMPUTED_VALUE"""),"FITLOG") -> FITLOG | K23: =IFERROR(__xludf.DUMMYFUNCTION("""COMPUTED_VALUE"""),"SEM REDESPACHO") -> SEM REDESPACHO | P23: =IFERROR(__xludf.DUMMYFUNCTION("""COMPUTED_VALUE"""),"Pedido gerado através do PedidoEletronico.com - Transportadora / telefone: FITLOG TRANSPORTES E LOGISTICA LTDA / (048) 996277956Obs.Interna: entrega futura. Entregar hotel BIARRITZ COPACABANA Rua Aires Saldanha 54 Copacabana cep 22440 032 RJ . Maquinas "&"ja implantadas anteriormente. Pedido para correção de endereço de entrega . Ligar para o Luiz antes de entregar 21 9 6518 9999 / E-mail para nota fiscal: , E-mail de cobrança: , Telefone para contato") -> Pedido gerado através do PedidoEletronico.com - Transportadora / telefone: FITLOG TRANSPORTES E LOGISTICA LTDA / (048) 996277956Obs.Interna: entrega futura. Entregar hotel BIARRITZ COPACABANA Rua Aires Saldanha 54 Copacabana cep 22440 032 RJ . Maquinas ja implantadas anteriormente. Pedido para correção de endereço de entrega . Ligar para o Luiz antes de entregar 21 9 6518 9999 / E-mail para nota fiscal: , E-mail de cobrança: , Telefone para contato
A24: =IFERROR(__xludf.DUMMYFUNCTION("""COMPUTED_VALUE"""),"18793") -> 18793 | B24: =IFERROR(__xludf.DUMMYFUNCTION("""COMPUTED_VALUE"""),"DESJOYAUX ES") -> DESJOYAUX ES | C24: =IFERROR(__xludf.DUMMYFUNCTION("""COMPUTED_VALUE"""),1.0) -> 1 | D24: =IFERROR(__xludf.DUMMYFUNCTION("""COMPUTED_VALUE"""),20433.0) -> 20433 | E24: =IFERROR(__xludf.DUMMYFUNCTION("""COMPUTED_VALUE"""),"FTI75DPTBR") -> FTI75DPTBR | F24: =IFERROR(__xludf.DUMMYFUNCTION("""COMPUTED_VALUE"""),"WI-FI") -> WI-FI | G24: =IFERROR(__xludf.DUMMYFUNCTION("""COMPUTED_VALUE"""),"NAO") -> NAO | H24: =IFERROR(__xludf.DUMMYFUNCTION("""COMPUTED_VALUE"""),"NAO") -> NAO | I24: =IFERROR(__xludf.DUMMYFUNCTION("""COMPUTED_VALUE"""),"PRODUÇÃO") -> PRODUÇÃO | J24: =IFERROR(__xludf.DUMMYFUNCTION("""COMPUTED_VALUE"""),"FITLOG") -> FITLOG | K24: =IFERROR(__xludf.DUMMYFUNCTION("""COMPUTED_VALUE"""),"SEM REDESPACHO") -> SEM REDESPACHO | P24: =IFERROR(__xludf.DUMMYFUNCTION("""COMPUTED_VALUE"""),"FITLOG TRANSPORTES E LOGISTICA LTDA / (048) 996277956Informação Adicional: CAROLINA / E-mail para nota fiscal: , E-mail de cobrança: , Telefone para contato") -> FITLOG TRANSPORTES E LOGISTICA LTDA / (048) 996277956Informação Adicional: CAROLINA / E-mail para nota fiscal: , E-mail de cobrança: , Telefone para contato
A25: =IFERROR(__xludf.DUMMYFUNCTION("""COMPUTED_VALUE"""),"18871-A") -> 18871-A | B25: =IFERROR(__xludf.DUMMYFUNCTION("""COMPUTED_VALUE"""),"STEINFIBER") -> STEINFIBER | C25: =IFERROR(__xludf.DUMMYFUNCTION("""COMPUTED_VALUE"""),0.0) -> 0 | D25: =IFERROR(__xludf.DUMMYFUNCTION("""COMPUTED_VALUE"""),20385.0) -> 20385 | E25: =IFERROR(__xludf.DUMMYFUNCTION("""COMPUTED_VALUE"""),"FTI145LPTBR") -> FTI145LPTBR | F25: =IFERROR(__xludf.DUMMYFUNCTION("""COMPUTED_VALUE"""),"WI-FI") -> WI-FI | G25: =IFERROR(__xludf.DUMMYFUNCTION("""COMPUTED_VALUE"""),"NAO") -> NAO | H25: =IFERROR(__xludf.DUMMYFUNCTION("""COMPUTED_VALUE"""),"NAO") -> NAO | I25: =IFERROR(__xludf.DUMMYFUNCTION("""COMPUTED_VALUE"""),"PRODUÇÃO") -> PRODUÇÃO | J25: =IFERROR(__xludf.DUMMYFUNCTION("""COMPUTED_VALUE"""),"RETIRA") -> RETIRA | K25: =IFERROR(__xludf.DUMMYFUNCTION("""COMPUTED_VALUE"""),"SEM REDESPACHO") -> SEM REDESPACHO | P25: =IFERROR(__xludf.DUMMYFUNCTION("""COMPUTED_VALUE"""),"CLIENTE RETIRA / (0) Informação Adicional: PREÇO NEGOCIADO R$ 18.600,00 - ALTERAR NO PEDIDO - AUTORIZADO POR PRISCILLA ENTREGA: 01 MÁQUINA DIA 20/10 E AS OUTRAS 06 MAXIMO DIA 05/11 / E-mail para nota fiscal: , E-mail de cobrança: , Telefone para contat"&"o") -> CLIENTE RETIRA / (0) Informação Adicional: PREÇO NEGOCIADO R$ 18.600,00 - ALTERAR NO PEDIDO - AUTORIZADO POR PRISCILLA ENTREGA: 01 MÁQUINA DIA 20/10 E AS OUTRAS 06 MAXIMO DIA 05/11 / E-mail para nota fiscal: , E-mail de cobrança: , Telefone para contato
A26: =IFERROR(__xludf.DUMMYFUNCTION("""COMPUTED_VALUE"""),"18891") -> 18891 | B26: =IFERROR(__xludf.DUMMYFUNCTION("""COMPUTED_VALUE"""),"KYP COMERCIO DE EQUIPAMENTOS PARA PISCINAS LTDA") -> KYP COMERCIO DE EQUIPAMENTOS PARA PISCINAS LTDA | C26: =IFERROR(__xludf.DUMMYFUNCTION("""COMPUTED_VALUE"""),0.0) -> 0 | D26: =IFERROR(__xludf.DUMMYFUNCTION("""COMPUTED_VALUE"""),20377.0) -> 20377 | E26: =IFERROR(__xludf.DUMMYFUNCTION("""COMPUTED_VALUE"""),"FT80B35W") -> FT80B35W | F26: =IFERROR(__xludf.DUMMYFUNCTION("""COMPUTED_VALUE"""),"WI-FI") -> WI-FI | G26: =IFERROR(__xludf.DUMMYFUNCTION("""COMPUTED_VALUE"""),"NAO") -> NAO | H26: =IFERROR(__xludf.DUMMYFUNCTION("""COMPUTED_VALUE"""),"NAO") -> NAO | I26: =IFERROR(__xludf.DUMMYFUNCTION("""COMPUTED_VALUE"""),"TESTAR") -> TESTAR | J26: =IFERROR(__xludf.DUMMYFUNCTION("""COMPUTED_VALUE"""),"FITLOG") -> FITLOG | K26: =IFERROR(__xludf.DUMMYFUNCTION("""COMPUTED_VALUE"""),"SEM REDESPACHO") -> SEM REDESPACHO | P26: =IFERROR(__xludf.DUMMYFUNCTION("""COMPUTED_VALUE"""),"FITLOG TRANSPORTES E LOGISTICA LTDA / (048) 996277956E-mail para nota fiscal: , E-mail de cobrança: , Telefone para contato") -> FITLOG TRANSPORTES E LOGISTICA LTDA / (048) 996277956E-mail para nota fiscal: , E-mail de cobrança: , Telefone para contato
A27: =IFERROR(__xludf.DUMMYFUNCTION("""COMPUTED_VALUE"""),"18912") -> 18912 | B27: =IFERROR(__xludf.DUMMYFUNCTION("""COMPUTED_VALUE"""),"D.K. SOLUÇÕES") -> D.K. SOLUÇÕES | C27: =IFERROR(__xludf.DUMMYFUNCTION("""COMPUTED_VALUE"""),90.0) -> 90 | E27: =IFERROR(__xludf.DUMMYFUNCTION("""COMPUTED_VALUE"""),"FTI75D40PT") -> FTI75D40PT | F27: =IFERROR(__xludf.DUMMYFUNCTION("""COMPUTED_VALUE"""),"WI-FI") -> WI-FI | G27: =IFERROR(__xludf.DUMMYFUNCTION("""COMPUTED_VALUE"""),"NAO") -> NAO | H27: =IFERROR(__xludf.DUMMYFUNCTION("""COMPUTED_VALUE"""),"NAO") -> NAO | I27: =IFERROR(__xludf.DUMMYFUNCTION("""COMPUTED_VALUE"""),"TESTAR") -> TESTAR | J27: =IFERROR(__xludf.DUMMYFUNCTION("""COMPUTED_VALUE"""),"RETIRA") -> RETIRA | K27: =IFERROR(__xludf.DUMMYFUNCTION("""COMPUTED_VALUE"""),"SEM REDESPACHO") -> SEM REDESPACHO | P27: =IFERROR(__xludf.DUMMYFUNCTION("""COMPUTED_VALUE"""),"Pedido gerado através do PedidoEletronico.com - Transportadora / telefone: CLIENTE RETIRA / (0) Informação Adicional: cliente retira / E-mail para nota fiscal: , E-mail de cobrança: , Telefone para contato") -> Pedido gerado através do PedidoEletronico.com - Transportadora / telefone: CLIENTE RETIRA / (0) Informação Adicional: cliente retira / E-mail para nota fiscal: , E-mail de cobrança: , Telefone para contato
A28: =IFERROR(__xludf.DUMMYFUNCTION("""COMPUTED_VALUE"""),"18930") -> 18930 | B28: =IFERROR(__xludf.DUMMYFUNCTION("""COMPUTED_VALUE"""),"52.540.567 DARLENE BATISTA DE JESUS") -> 52.540.567 DARLENE BATISTA DE JESUS | C28: =IFERROR(__xludf.DUMMYFUNCTION("""COMPUTED_VALUE"""),137.0) -> 137 | E28: =IFERROR(__xludf.DUMMYFUNCTION("""COMPUTED_VALUE"""),"FTI55D40PT") -> FTI55D40PT | F28: =IFERROR(__xludf.DUMMYFUNCTION("""COMPUTED_VALUE"""),"WI-FI") -> WI-FI | G28: =IFERROR(__xludf.DUMMYFUNCTION("""COMPUTED_VALUE"""),"NAO") -> NAO | H28: =IFERROR(__xludf.DUMMYFUNCTION("""COMPUTED_VALUE"""),"NAO") -> NAO | I28: =IFERROR(__xludf.DUMMYFUNCTION("""COMPUTED_VALUE"""),"TESTAR") -> TESTAR | J28: =IFERROR(__xludf.DUMMYFUNCTION("""COMPUTED_VALUE"""),"EXPRESSO SAO MIGUEL") -> EXPRESSO SAO MIGUEL | K28: =IFERROR(__xludf.DUMMYFUNCTION("""COMPUTED_VALUE"""),"SEM REDESPACHO") -> SEM REDESPACHO | P28: =IFERROR(__xludf.DUMMYFUNCTION("""COMPUTED_VALUE"""),"Pedido reprocessado ao alterar dados do cliente 21/10/2025 11:52:24 usuário: JULIANA VIEIRA DA SILVA Pedido gerado através do PedidoEletronico.com - Transportadora / telefone: EXPRESSO SAO MIGUEL S/A / (049) 3361-6627E-mail para nota fiscal: , E-mail de "&"cobrança: , Telefone para contato") -> Pedido reprocessado ao alterar dados do cliente 21/10/2025 11:52:24 usuário: JULIANA VIEIRA DA SILVA Pedido gerado através do PedidoEletronico.com - Transportadora / telefone: EXPRESSO SAO MIGUEL S/A / (049) 3361-6627E-mail para nota fiscal: , E-mail de cobrança: , Telefone para contato
A29: =IFERROR(__xludf.DUMMYFUNCTION("""COMPUTED_VALUE"""),"18928-A") -> 18928-A | B29: =IFERROR(__xludf.DUMMYFUNCTION("""COMPUTED_VALUE"""),"C NUNES & CIA LTDA") -> C NUNES & CIA LTDA | C29: =IFERROR(__xludf.DUMMYFUNCTION("""COMPUTED_VALUE"""),90.0) -> 90 | E29: =IFERROR(__xludf.DUMMYFUNCTION("""COMPUTED_VALUE"""),"FTI75D40PT") -> FTI75D40PT | F29: =IFERROR(__xludf.DUMMYFUNCTION("""COMPUTED_VALUE"""),"WI-FI") -> WI-FI | G29: =IFERROR(__xludf.DUMMYFUNCTION("""COMPUTED_VALUE"""),"NAO") -> NAO | H29: =IFERROR(__xludf.DUMMYFUNCTION("""COMPUTED_VALUE"""),"NAO") -> NAO | I29: =IFERROR(__xludf.DUMMYFUNCTION("""COMPUTED_VALUE"""),"TESTAR") -> TESTAR | J29: =IFERROR(__xludf.DUMMYFUNCTION("""COMPUTED_VALUE"""),"EXPRESSO SAO MIGUEL") -> EXPRESSO SAO MIGUEL | K29: =IFERROR(__xludf.DUMMYFUNCTION("""COMPUTED_VALUE"""),"SEM REDESPACHO") -> SEM REDESPACHO | P29: =IFERROR(__xludf.DUMMYFUNCTION("""COMPUTED_VALUE"""),"Pedido gerado através do PedidoEletronico.com - Transportadora / telefone: EXPRESSO SAO MIGUEL S/A / (051) 3586-2013Informação Adicional: FAVOR CORRIGIR O VALOR DA MAQUINA 75 R$8.915,67 E 125 R$14.400,18 AUTORIZADO PELO MARIO DICK / Obs.Interna: Mario-El"&"ine autorizado para esse cliente . / E-mail para nota fiscal: , E-mail de cobrança: , Telefone para contato") -> Pedido gerado através do PedidoEletronico.com - Transportadora / telefone: EXPRESSO SAO MIGUEL S/A / (051) 3586-2013Informação Adicional: FAVOR CORRIGIR O VALOR DA MAQUINA 75 R$8.915,67 E 125 R$14.400,18 AUTORIZADO PELO MARIO DICK / Obs.Interna: Mario-Eline autorizado para esse cliente . / E-mail para nota fiscal: , E-mail de cobrança: , Telefone para contato
A30: =IFERROR(__xludf.DUMMYFUNCTION("""COMPUTED_VALUE"""),"18928-B") -> 18928-B | B30: =IFERROR(__xludf.DUMMYFUNCTION("""COMPUTED_VALUE"""),"C NUNES & CIA LTDA") -> C NUNES & CIA LTDA | C30: =IFERROR(__xludf.DUMMYFUNCTION("""COMPUTED_VALUE"""),34.0) -> 34 | E30: =IFERROR(__xludf.DUMMYFUNCTION("""COMPUTED_VALUE"""),"FTI125D40PT") -> FTI125D40PT | F30: =IFERROR(__xludf.DUMMYFUNCTION("""COMPUTED_VALUE"""),"WI-FI") -> WI-FI | G30: =IFERROR(__xludf.DUMMYFUNCTION("""COMPUTED_VALUE"""),"NAO") -> NAO | H30: =IFERROR(__xludf.DUMMYFUNCTION("""COMPUTED_VALUE"""),"NAO") -> NAO | I30: =IFERROR(__xludf.DUMMYFUNCTION("""COMPUTED_VALUE"""),"TESTAR") -> TESTAR | J30: =IFERROR(__xludf.DUMMYFUNCTION("""COMPUTED_VALUE"""),"EXPRESSO SAO MIGUEL") -> EXPRESSO SAO MIGUEL | K30: =IFERROR(__xludf.DUMMYFUNCTION("""COMPUTED_VALUE"""),"SEM REDESPACHO") -> SEM REDESPACHO | P30: =IFERROR(__xludf.DUMMYFUNCTION("""COMPUTED_VALUE"""),"Pedido gerado através do PedidoEletronico.com - Transportadora / telefone: EXPRESSO SAO MIGUEL S/A / (051) 3586-2013Informação Adicional: FAVOR CORRIGIR O VALOR DA MAQUINA 75 R$8.915,67 E 125 R$14.400,18 AUTORIZADO PELO MARIO DICK / Obs.Interna: Mario-El"&"ine autorizado para esse cliente . / E-mail para nota fiscal: , E-mail de cobrança: , Telefone para contato") -> Pedido gerado através do PedidoEletronico.com - Transportadora / telefone: EXPRESSO SAO MIGUEL S/A / (051) 3586-2013Informação Adicional: FAVOR CORRIGIR O VALOR DA MAQUINA 75 R$8.915,67 E 125 R$14.400,18 AUTORIZADO PELO MARIO DICK / Obs.Interna: Mario-Eline autorizado para esse cliente . / E-mail para nota fiscal: , E-mail de cobrança: , Telefone para contato

Sheet Estoque V2
A1: MODELO | B1: RG | C1: QUADRO | D1: FORMULA | E1: LOTE | F1: STATUS | G1: RESERVA | H1: ETAPA
A2: =IFERROR(__xludf.DUMMYFUNCTION("{ FILTER( IMPORTRANGE(""https://docs.google.com/spreadsheets/d/1Kzg7LngaUig6t2CLabS1fhZ-iD5idrmv1ZesIUVOy1M/edit?gid=1333359070"", ""'PRODUÇÃO 1 - ESCOPO'!E:G""), (IMPORTRANGE(""https://docs.google.com/spreadsheets/d/1Kzg7LngaUig6t2CLabS1fhZ-iD5"&"idrmv1ZesIUVOy1M/edit?gid=1333359070"", ""'PRODUÇÃO 1 - ESCOPO'!D:D"") <> """") * (NOT(REGEXMATCH(IMPORTRANGE(""https://docs.google.com/spreadsheets/d/1Kzg7LngaUig6t2CLabS1fhZ-iD5idrmv1ZesIUVOy1M/edit?gid=1333359070"", ""'PRODUÇÃO 1 - ESCOPO'!D:D""),"&" ""ENTREGUE""))) * (IMPORTRANGE(""https://docs.google.com/spreadsheets/d/1Kzg7LngaUig6t2CLabS1fhZ-iD5idrmv1ZesIUVOy1M/edit?gid=1333359070"", ""'PRODUÇÃO 1 - ESCOPO'!H:H"") = 4) ); FILTER( IMPORTRANGE(""https://docs.google.com/spreadsheets/d/1"&"Kzg7LngaUig6t2CLabS1fhZ-iD5idrmv1ZesIUVOy1M/edit?gid=2061903610"", ""'PRODUÇÃO 2 - F/ ESCOPO'!E:G""), (IMPORTRANGE(""https://docs.google.com/spreadsheets/d/1Kzg7LngaUig6t2CLabS1fhZ-iD5idrmv1ZesIUVOy1M/edit?gid=2061903610"", ""'PRODUÇÃO 2 - F/ ESCOPO'!"&"D:D"") <> """") * (NOT(REGEXMATCH(IMPORTRANGE(""https://docs.google.com/spreadsheets/d/1Kzg7LngaUig6t2CLabS1fhZ-iD5idrmv1ZesIUVOy1M/edit?gid=2061903610"", ""'PRODUÇÃO 2 - F/ ESCOPO'!D:D""), ""ENTREGUE""))) * (IMPORTRANGE(""https://docs.google.co"&"m/spreadsheets/d/1Kzg7LngaUig6t2CLabS1fhZ-iD5idrmv1ZesIUVOy1M/edit?gid=2061903610"", ""'PRODUÇÃO 2 - F/ ESCOPO'!H:H"") = 5) ) } "),"FT40B35") -> FT40B35 | B2: =IFERROR(__xludf.DUMMYFUNCTION("""COMPUTED_VALUE"""),13903.0) -> 13903 | C2: =IFERROR(__xludf.DUMMYFUNCTION("""COMPUTED_VALUE"""),"PDX") -> PDX | D2: =IF(OR(F2<>" ",G2<>"")=TRUE,1,0) -> 0 | E2: =IFERROR(__xludf.DUMMYFUNCTION("IFERROR(VLOOKUP(TO_TEXT(B2),PEDIDOS!D:L,9,0),IFERROR(VLOOKUP(B2*1,PEDIDOS!D:L,9,0),"" ""))")," ") | F2: =IFERROR(__xludf.DUMMYFUNCTION("IF(B2="""","""",IFERROR(VLOOKUP(TO_TEXT(B2),PEDIDOS!D:I,6,0),IFERROR(VLOOKUP(B2*1,PEDIDOS!D:I,6,0),"" "")))")," ")
A3: =IFERROR(__xludf.DUMMYFUNCTION("""COMPUTED_VALUE"""),"FTI55DPTBR") -> FTI55DPTBR | B3: =IFERROR(__xludf.DUMMYFUNCTION("""COMPUTED_VALUE"""),13977.0) -> 13977 | C3: =IFERROR(__xludf.DUMMYFUNCTION("""COMPUTED_VALUE"""),"INVERTER") -> INVERTER | D3: =IF(OR(F3<>" ",G3<>"")=TRUE,1,0) -> 0 | E3: =IFERROR(__xludf.DUMMYFUNCTION("IFERROR(VLOOKUP(TO_TEXT(B3),PEDIDOS!D:L,9,0),IFERROR(VLOOKUP(B3*1,PEDIDOS!D:L,9,0),"" ""))")," ") | F3: =IFERROR(__xludf.DUMMYFUNCTION("IF(B3="""","""",IFERROR(VLOOKUP(TO_TEXT(B3),PEDIDOS!D:I,6,0),IFERROR(VLOOKUP(B3*1,PEDIDOS!D:I,6,0),"" "")))")," ")
A4: =IFERROR(__xludf.DUMMYFUNCTION("""COMPUTED_VALUE"""),"FT40B35T") -> FT40B35T | B4: =IFERROR(__xludf.DUMMYFUNCTION("""COMPUTED_VALUE"""),14082.0) -> 14082 | C4: =IFERROR(__xludf.DUMMYFUNCTION("""COMPUTED_VALUE"""),"NORMAL") -> NORMAL | D4: =IF(OR(F4<>" ",G4<>"")=TRUE,1,0) -> 0 | E4: =IFERROR(__xludf.DUMMYFUNCTION("IFERROR(VLOOKUP(TO_TEXT(B4),PEDIDOS!D:L,9,0),IFERROR(VLOOKUP(B4*1,PEDIDOS!D:L,9,0),"" ""))")," ") | F4: =IFERROR(__xludf.DUMMYFUNCTION("IF(B4="""","""",IFERROR(VLOOKUP(TO_TEXT(B4),PEDIDOS!D:I,6,0),IFERROR(VLOOKUP(B4*1,PEDIDOS!D:I,6,0),"" "")))")," ")
A5: =IFERROR(__xludf.DUMMYFUNCTION("""COMPUTED_VALUE"""),"FTI55DPTBR") -> FTI55DPTBR | B5: =IFERROR(__xludf.DUMMYFUNCTION("""COMPUTED_VALUE"""),20072.0) -> 20072 | C5: =IFERROR(__xludf.DUMMYFUNCTION("""COMPUTED_VALUE"""),"WI-FI") -> WI-FI | D5: =IF(OR(F5<>" ",G5<>"")=TRUE,1,0) -> 0 | E5: =IFERROR(__xludf.DUMMYFUNCTION("IFERROR(VLOOKUP(TO_TEXT(B5),PEDIDOS!D:L,9,0),IFERROR(VLOOKUP(B5*1,PEDIDOS!D:L,9,0),"" ""))")," ") | F5: =IFERROR(__xludf.DUMMYFUNCTION("IF(B5="""","""",IFERROR(VLOOKUP(TO_TEXT(B5),PEDIDOS!D:I,6,0),IFERROR(VLOOKUP(B5*1,PEDIDOS!D:I,6,0),"" "")))")," ")
A6: =IFERROR(__xludf.DUMMYFUNCTION("""COMPUTED_VALUE"""),"FH40B60T") -> FH40B60T | B6: =IFERROR(__xludf.DUMMYFUNCTION("""COMPUTED_VALUE"""),20179.0) -> 20179 | C6: =IFERROR(__xludf.DUMMYFUNCTION("""COMPUTED_VALUE"""),"NORMAL") -> NORMAL | D6: =IF(OR(F6<>" ",G6<>"")=TRUE,1,0) -> 0 | E6: =IFERROR(__xludf.DUMMYFUNCTION("IFERROR(VLOOKUP(TO_TEXT(B6),PEDIDOS!D:L,9,0),IFERROR(VLOOKUP(B6*1,PEDIDOS!D:L,9,0),"" ""))")," ") | F6: =IFERROR(__xludf.DUMMYFUNCTION("IF(B6="""","""",IFERROR(VLOOKUP(TO_TEXT(B6),PEDIDOS!D:I,6,0),IFERROR(VLOOKUP(B6*1,PEDIDOS!D:I,6,0),"" "")))")," ")
A7: =IFERROR(__xludf.DUMMYFUNCTION("""COMPUTED_VALUE"""),"FT40B35W") -> FT40B35W | B7: =IFERROR(__xludf.DUMMYFUNCTION("""COMPUTED_VALUE"""),20184.0) -> 20184 | C7: =IFERROR(__xludf.DUMMYFUNCTION("""COMPUTED_VALUE"""),"WI-FI") -> WI-FI | D7: =IF(OR(F7<>" ",G7<>"")=TRUE,1,0) -> 0 | E7: =IFERROR(__xludf.DUMMYFUNCTION("IFERROR(VLOOKUP(TO_TEXT(B7),PEDIDOS!D:L,9,0),IFERROR(VLOOKUP(B7*1,PEDIDOS!D:L,9,0),"" ""))")," ") | F7: =IFERROR(__xludf.DUMMYFUNCTION("IF(B7="""","""",IFERROR(VLOOKUP(TO_TEXT(B7),PEDIDOS!D:I,6,0),IFERROR(VLOOKUP(B7*1,PEDIDOS!D:I,6,0),"" "")))")," ")
A8: =IFERROR(__xludf.DUMMYFUNCTION("""COMPUTED_VALUE"""),"FT40B35W") -> FT40B35W | B8: =IFERROR(__xludf.DUMMYFUNCTION("""COMPUTED_VALUE"""),20185.0) -> 20185 | C8: =IFERROR(__xludf.DUMMYFUNCTION("""COMPUTED_VALUE"""),"WI-FI") -> WI-FI | D8: =IF(OR(F8<>" ",G8<>"")=TRUE,1,0) -> 0 | E8: =IFERROR(__xludf.DUMMYFUNCTION("IFERROR(VLOOKUP(TO_TEXT(B8),PEDIDOS!D:L,9,0),IFERROR(VLOOKUP(B8*1,PEDIDOS!D:L,9,0),"" ""))")," ") | F8: =IFERROR(__xludf.DUMMYFUNCTION("IF(B8="""","""",IFERROR(VLOOKUP(TO_TEXT(B8),PEDIDOS!D:I,6,0),IFERROR(VLOOKUP(B8*1,PEDIDOS!D:I,6,0),"" "")))")," ")
A9: =IFERROR(__xludf.DUMMYFUNCTION("""COMPUTED_VALUE"""),"FT20B35W") -> FT20B35W | B9: =IFERROR(__xludf.DUMMYFUNCTION("""COMPUTED_VALUE"""),20232.0) -> 20232 | C9: =IFERROR(__xludf.DUMMYFUNCTION("""COMPUTED_VALUE"""),"WI-FI") -> WI-FI | D9: =IF(OR(F9<>" ",G9<>"")=TRUE,1,0) -> 0 | E9: =IFERROR(__xludf.DUMMYFUNCTION("IFERROR(VLOOKUP(TO_TEXT(B9),PEDIDOS!D:L,9,0),IFERROR(VLOOKUP(B9*1,PEDIDOS!D:L,9,0),"" ""))")," ") | F9: =IFERROR(__xludf.DUMMYFUNCTION("IF(B9="""","""",IFERROR(VLOOKUP(TO_TEXT(B9),PEDIDOS!D:I,6,0),IFERROR(VLOOKUP(B9*1,PEDIDOS!D:I,6,0),"" "")))")," ")
A10: =IFERROR(__xludf.DUMMYFUNCTION("""COMPUTED_VALUE"""),"FTI55DPTBR") -> FTI55DPTBR | B10: =IFERROR(__xludf.DUMMYFUNCTION("""COMPUTED_VALUE"""),20252.0) -> 20252 | C10: =IFERROR(__xludf.DUMMYFUNCTION("""COMPUTED_VALUE"""),"INVERTER") -> INVERTER | D10: =IF(OR(F10<>" ",G10<>"")=TRUE,1,0) -> 1 | E10: =IFERROR(__xludf.DUMMYFUNCTION("IFERROR(VLOOKUP(TO_TEXT(B10),PEDIDOS!D:L,9,0),IFERROR(VLOOKUP(B10*1,PEDIDOS!D:L,9,0),"" ""))")," ") | F10: =IFERROR(__xludf.DUMMYFUNCTION("IF(B10="""","""",IFERROR(VLOOKUP(TO_TEXT(B10),PEDIDOS!D:I,6,0),IFERROR(VLOOKUP(B10*1,PEDIDOS!D:I,6,0),"" "")))")," ") | G10: =IFERROR(__xludf.DUMMYFUNCTION("IF(B10="""","""",IFERROR(VLOOKUP(TO_TEXT(B10),PEDIDOS!D:L,7,0),IFERROR(VLOOKUP(B10*1,PEDIDOS!D:L,7,0),"" "")))")," ")
A11: =IFERROR(__xludf.DUMMYFUNCTION("""COMPUTED_VALUE"""),"FTI55DPTBR") -> FTI55DPTBR | B11: =IFERROR(__xludf.DUMMYFUNCTION("""COMPUTED_VALUE"""),20253.0) -> 20253 | C11: =IFERROR(__xludf.DUMMYFUNCTION("""COMPUTED_VALUE"""),"INVERTER") -> INVERTER | D11: =IF(OR(F11<>" ",G11<>"")=TRUE,1,0) -> 0 | E11: =IFERROR(__xludf.DUMMYFUNCTION("IFERROR(VLOOKUP(TO_TEXT(B11),PEDIDOS!D:L,9,0),IFERROR(VLOOKUP(B11*1,PEDIDOS!D:L,9,0),"" ""))")," ") | F11: =IFERROR(__xludf.DUMMYFUNCTION("IF(B11="""","""",IFERROR(VLOOKUP(TO_TEXT(B11),PEDIDOS!D:I,6,0),IFERROR(VLOOKUP(B11*1,PEDIDOS!D:I,6,0),"" "")))")," ")
A12: =IFERROR(__xludf.DUMMYFUNCTION("""COMPUTED_VALUE"""),"FTI55DPTBR") -> FTI55DPTBR | B12: =IFERROR(__xludf.DUMMYFUNCTION("""COMPUTED_VALUE"""),20254.0) -> 20254 | C12: =IFERROR(__xludf.DUMMYFUNCTION("""COMPUTED_VALUE"""),"INVERTER") -> INVERTER | D12: =IF(OR(F12<>" ",G12<>"")=TRUE,1,0) -> 0 | E12: =IFERROR(__xludf.DUMMYFUNCTION("IFERROR(VLOOKUP(TO_TEXT(B12),PEDIDOS!D:L,9,0),IFERROR(VLOOKUP(B12*1,PEDIDOS!D:L,9,0),"" ""))")," ") | F12: =IFERROR(__xludf.DUMMYFUNCTION("IF(B12="""","""",IFERROR(VLOOKUP(TO_TEXT(B12),PEDIDOS!D:I,6,0),IFERROR(VLOOKUP(B12*1,PEDIDOS!D:I,6,0),"" "")))")," ")
A13: =IFERROR(__xludf.DUMMYFUNCTION("""COMPUTED_VALUE"""),"FTI55DPTBR") -> FTI55DPTBR | B13: =IFERROR(__xludf.DUMMYFUNCTION("""COMPUTED_VALUE"""),20255.0) -> 20255 | C13: =IFERROR(__xludf.DUMMYFUNCTION("""COMPUTED_VALUE"""),"INVERTER") -> INVERTER | D13: =IF(OR(F13<>" ",G13<>"")=TRUE,1,0) -> 0 | E13: =IFERROR(__xludf.DUMMYFUNCTION("IFERROR(VLOOKUP(TO_TEXT(B13),PEDIDOS!D:L,9,0),IFERROR(VLOOKUP(B13*1,PEDIDOS!D:L,9,0),"" ""))")," ") | F13: =IFERROR(__xludf.DUMMYFUNCTION("IF(B13="""","""",IFERROR(VLOOKUP(TO_TEXT(B13),PEDIDOS!D:I,6,0),IFERROR(VLOOKUP(B13*1,PEDIDOS!D:I,6,0),"" "")))")," ")
A14: =IFERROR(__xludf.DUMMYFUNCTION("""COMPUTED_VALUE"""),"FTI55DPTBR") -> FTI55DPTBR | B14: =IFERROR(__xludf.DUMMYFUNCTION("""COMPUTED_VALUE"""),20282.0) -> 20282 | C14: =IFERROR(__xludf.DUMMYFUNCTION("""COMPUTED_VALUE"""),"INVERTER") -> INVERTER | D14: =IF(OR(F14<>" ",G14<>"")=TRUE,1,0) -> 0 | E14: =IFERROR(__xludf.DUMMYFUNCTION("IFERROR(VLOOKUP(TO_TEXT(B14),PEDIDOS!D:L,9,0),IFERROR(VLOOKUP(B14*1,PEDIDOS!D:L,9,0),"" ""))")," ") | F14: =IFERROR(__xludf.DUMMYFUNCTION("IF(B14="""","""",IFERROR(VLOOKUP(TO_TEXT(B14),PEDIDOS!D:I,6,0),IFERROR(VLOOKUP(B14*1,PEDIDOS!D:I,6,0),"" "")))")," ")
A15: =IFERROR(__xludf.DUMMYFUNCTION("""COMPUTED_VALUE"""),"FTI55DPTBR") -> FTI55DPTBR | B15: =IFERROR(__xludf.DUMMYFUNCTION("""COMPUTED_VALUE"""),20283.0) -> 20283 | C15: =IFERROR(__xludf.DUMMYFUNCTION("""COMPUTED_VALUE"""),"INVERTER") -> INVERTER | D15: =IF(OR(F15<>" ",G15<>"")=TRUE,1,0) -> 0 | E15: =IFERROR(__xludf.DUMMYFUNCTION("IFERROR(VLOOKUP(TO_TEXT(B15),PEDIDOS!D:L,9,0),IFERROR(VLOOKUP(B15*1,PEDIDOS!D:L,9,0),"" ""))")," ") | F15: =IFERROR(__xludf.DUMMYFUNCTION("IF(B15="""","""",IFERROR(VLOOKUP(TO_TEXT(B15),PEDIDOS!D:I,6,0),IFERROR(VLOOKUP(B15*1,PEDIDOS!D:I,6,0),"" "")))")," ")
A16: =IFERROR(__xludf.DUMMYFUNCTION("""COMPUTED_VALUE"""),"FTI55DPTBR") -> FTI55DPTBR | B16: =IFERROR(__xludf.DUMMYFUNCTION("""COMPUTED_VALUE"""),20284.0) -> 20284 | C16: =IFERROR(__xludf.DUMMYFUNCTION("""COMPUTED_VALUE"""),"INVERTER") -> INVERTER | D16: =IF(OR(F16<>" ",G16<>"")=TRUE,1,0) -> 0 | E16: =IFERROR(__xludf.DUMMYFUNCTION("IFERROR(VLOOKUP(TO_TEXT(B16),PEDIDOS!D:L,9,0),IFERROR(VLOOKUP(B16*1,PEDIDOS!D:L,9,0),"" ""))")," ") | F16: =IFERROR(__xludf.DUMMYFUNCTION("IF(B16="""","""",IFERROR(VLOOKUP(TO_TEXT(B16),PEDIDOS!D:I,6,0),IFERROR(VLOOKUP(B16*1,PEDIDOS!D:I,6,0),"" "")))")," ")
A17: =IFERROR(__xludf.DUMMYFUNCTION("""COMPUTED_VALUE"""),"FTI55DPTBR") -> FTI55DPTBR | B17: =IFERROR(__xludf.DUMMYFUNCTION("""COMPUTED_VALUE"""),20285.0) -> 20285 | C17: =IFERROR(__xludf.DUMMYFUNCTION("""COMPUTED_VALUE"""),"INVERTER") -> INVERTER | D17: =IF(OR(F17<>" ",G17<>"")=TRUE,1,0) -> 0 | E17: =IFERROR(__xludf.DUMMYFUNCTION("IFERROR(VLOOKUP(TO_TEXT(B17),PEDIDOS!D:L,9,0),IFERROR(VLOOKUP(B17*1,PEDIDOS!D:L,9,0),"" ""))")," ") | F17: =IFERROR(__xludf.DUMMYFUNCTION("IF(B17="""","""",IFERROR(VLOOKUP(TO_TEXT(B17),PEDIDOS!D:I,6,0),IFERROR(VLOOKUP(B17*1,PEDIDOS!D:I,6,0),"" "")))")," ")
A18: =IFERROR(__xludf.DUMMYFUNCTION("""COMPUTED_VALUE"""),"FTI45DPTBR") -> FTI45DPTBR | B18: =IFERROR(__xludf.DUMMYFUNCTION("""COMPUTED_VALUE"""),20365.0) -> 20365 | C18: =IFERROR(__xludf.DUMMYFUNCTION("""COMPUTED_VALUE"""),"INVERTER") -> INVERTER | D18: =IF(OR(F18<>" ",G18<>"")=TRUE,1,0) -> 1 | E18: =IFERROR(__xludf.DUMMYFUNCTION("IFERROR(VLOOKUP(TO_TEXT(B18),PEDIDOS!D:L,9,0),IFERROR(VLOOKUP(B18*1,PEDIDOS!D:L,9,0),"" ""))"),14226.0) -> 14226 | F18: =IFERROR(__xludf.DUMMYFUNCTION("IF(B18="""","""",IFERROR(VLOOKUP(TO_TEXT(B18),PEDIDOS!D:I,6,0),IFERROR(VLOOKUP(B18*1,PEDIDOS!D:I,6,0),"" "")))"),"ENTREGUE") -> ENTREGUE
A19: =IFERROR(__xludf.DUMMYFUNCTION("""COMPUTED_VALUE"""),"FT60F35T") -> FT60F35T | B19: =IFERROR(__xludf.DUMMYFUNCTION("""COMPUTED_VALUE"""),"9708") -> 9708 | C19: =IFERROR(__xludf.DUMMYFUNCTION("""COMPUTED_VALUE"""),"NORMAL") -> NORMAL | D19: =IF(OR(F19<>" ",G19<>"")=TRUE,1,0) -> 1 | E19: =IFERROR(__xludf.DUMMYFUNCTION("IFERROR(VLOOKUP(TO_TEXT(B19),PEDIDOS!D:L,9,0),IFERROR(VLOOKUP(B19*1,PEDIDOS!D:L,9,0),"" ""))"),13762.0) -> 13762 | F19: =IFERROR(__xludf.DUMMYFUNCTION("IF(B19="""","""",IFERROR(VLOOKUP(TO_TEXT(B19),PEDIDOS!D:I,6,0),IFERROR(VLOOKUP(B19*1,PEDIDOS!D:I,6,0),"" "")))"),"ENTREGUE") -> ENTREGUE
A20: =IFERROR(__xludf.DUMMYFUNCTION("""COMPUTED_VALUE"""),"FT100L35T") -> FT100L35T | B20: =IFERROR(__xludf.DUMMYFUNCTION("""COMPUTED_VALUE"""),"10050") -> 10050 | C20: =IFERROR(__xludf.DUMMYFUNCTION("""COMPUTED_VALUE"""),"EXT") -> EXT | D20: =IF(OR(F20<>" ",G20<>"")=TRUE,1,0) -> 0 | E20: =IFERROR(__xludf.DUMMYFUNCTION("IFERROR(VLOOKUP(TO_TEXT(B20),PEDIDOS!D:L,9,0),IFERROR(VLOOKUP(B20*1,PEDIDOS!D:L,9,0),"" ""))")," ") | F20: =IFERROR(__xludf.DUMMYFUNCTION("IF(B20="""","""",IFERROR(VLOOKUP(TO_TEXT(B20),PEDIDOS!D:I,6,0),IFERROR(VLOOKUP(B20*1,PEDIDOS!D:I,6,0),"" "")))")," ")
A21: =IFERROR(__xludf.DUMMYFUNCTION("""COMPUTED_VALUE"""),"FT60F35T") -> FT60F35T | B21: =IFERROR(__xludf.DUMMYFUNCTION("""COMPUTED_VALUE"""),"10617") -> 10617 | C21: =IFERROR(__xludf.DUMMYFUNCTION("""COMPUTED_VALUE"""),"NORMAL") -> NORMAL | D21: =IF(OR(F21<>" ",G21<>"")=TRUE,1,0) -> 0 | E21: =IFERROR(__xludf.DUMMYFUNCTION("IFERROR(VLOOKUP(TO_TEXT(B21),PEDIDOS!D:L,9,0),IFERROR(VLOOKUP(B21*1,PEDIDOS!D:L,9,0),"" ""))")," ") | F21: =IFERROR(__xludf.DUMMYFUNCTION("IF(B21="""","""",IFERROR(VLOOKUP(TO_TEXT(B21),PEDIDOS!D:I,6,0),IFERROR(VLOOKUP(B21*1,PEDIDOS!D:I,6,0),"" "")))")," ")
A22: =IFERROR(__xludf.DUMMYFUNCTION("""COMPUTED_VALUE"""),"FT80H35T") -> FT80H35T | B22: =IFERROR(__xludf.DUMMYFUNCTION("""COMPUTED_VALUE"""),"11441") -> 11441 | C22: =IFERROR(__xludf.DUMMYFUNCTION("""COMPUTED_VALUE"""),"EXT") -> EXT | D22: =IF(OR(F22<>" ",G22<>"")=TRUE,1,0) -> 0 | E22: =IFERROR(__xludf.DUMMYFUNCTION("IFERROR(VLOOKUP(TO_TEXT(B22),PEDIDOS!D:L,9,0),IFERROR(VLOOKUP(B22*1,PEDIDOS!D:L,9,0),"" ""))")," ") | F22: =IFERROR(__xludf.DUMMYFUNCTION("IF(B22="""","""",IFERROR(VLOOKUP(TO_TEXT(B22),PEDIDOS!D:I,6,0),IFERROR(VLOOKUP(B22*1,PEDIDOS!D:I,6,0),"" "")))")," ")
A23: =IFERROR(__xludf.DUMMYFUNCTION("""COMPUTED_VALUE"""),"FT80H35T") -> FT80H35T | B23: =IFERROR(__xludf.DUMMYFUNCTION("""COMPUTED_VALUE"""),"11443") -> 11443 | C23: =IFERROR(__xludf.DUMMYFUNCTION("""COMPUTED_VALUE"""),"EXT") -> EXT | D23: =IF(OR(F23<>" ",G23<>"")=TRUE,1,0) -> 0 | E23: =IFERROR(__xludf.DUMMYFUNCTION("IFERROR(VLOOKUP(TO_TEXT(B23),PEDIDOS!D:L,9,0),IFERROR(VLOOKUP(B23*1,PEDIDOS!D:L,9,0),"" ""))")," ") | F23: =IFERROR(__xludf.DUMMYFUNCTION("IF(B23="""","""",IFERROR(VLOOKUP(TO_TEXT(B23),PEDIDOS!D:I,6,0),IFERROR(VLOOKUP(B23*1,PEDIDOS!D:I,6,0),"" "")))")," ")
A24: =IFERROR(__xludf.DUMMYFUNCTION("""COMPUTED_VALUE"""),"FT80H35T") -> FT80H35T | B24: =IFERROR(__xludf.DUMMYFUNCTION("""COMPUTED_VALUE"""),"11651") -> 11651 | C24: =IFERROR(__xludf.DUMMYFUNCTION("""COMPUTED_VALUE"""),"EXT") -> EXT | D24: =IF(OR(F24<>" ",G24<>"")=TRUE,1,0) -> 0 | E24: =IFERROR(__xludf.DUMMYFUNCTION("IFERROR(VLOOKUP(TO_TEXT(B24),PEDIDOS!D:L,9,0),IFERROR(VLOOKUP(B24*1,PEDIDOS!D:L,9,0),"" ""))")," ") | F24: =IFERROR(__xludf.DUMMYFUNCTION("IF(B24="""","""",IFERROR(VLOOKUP(TO_TEXT(B24),PEDIDOS!D:I,6,0),IFERROR(VLOOKUP(B24*1,PEDIDOS!D:I,6,0),"" "")))")," ")
A25: =IFERROR(__xludf.DUMMYFUNCTION("""COMPUTED_VALUE"""),"FT120B35") -> FT120B35 | B25: =IFERROR(__xludf.DUMMYFUNCTION("""COMPUTED_VALUE"""),"20219") -> 20219 | C25: =IFERROR(__xludf.DUMMYFUNCTION("""COMPUTED_VALUE"""),"PDX") -> PDX | D25: =IF(OR(F25<>" ",G25<>"")=TRUE,1,0) -> 1 | E25: =IFERROR(__xludf.DUMMYFUNCTION("IFERROR(VLOOKUP(TO_TEXT(B25),PEDIDOS!D:L,9,0),IFERROR(VLOOKUP(B25*1,PEDIDOS!D:L,9,0),"" ""))"),13537.0) -> 13537 | F25: =IFERROR(__xludf.DUMMYFUNCTION("IF(B25="""","""",IFERROR(VLOOKUP(TO_TEXT(B25),PEDIDOS!D:I,6,0),IFERROR(VLOOKUP(B25*1,PEDIDOS!D:I,6,0),"" "")))"),"ENTREGUE") -> ENTREGUE
A26: =IFERROR(__xludf.DUMMYFUNCTION("""COMPUTED_VALUE"""),"FT70B35T") -> FT70B35T | B26: =IFERROR(__xludf.DUMMYFUNCTION("""COMPUTED_VALUE"""),"12188") -> 12188 | C26: =IFERROR(__xludf.DUMMYFUNCTION("""COMPUTED_VALUE"""),"NORMAL") -> NORMAL | D26: =IF(OR(F26<>" ",G26<>"")=TRUE,1,0) -> 0 | E26: =IFERROR(__xludf.DUMMYFUNCTION("IFERROR(VLOOKUP(TO_TEXT(B26),PEDIDOS!D:L,9,0),IFERROR(VLOOKUP(B26*1,PEDIDOS!D:L,9,0),"" ""))")," ") | F26: =IFERROR(__xludf.DUMMYFUNCTION("IF(B26="""","""",IFERROR(VLOOKUP(TO_TEXT(B26),PEDIDOS!D:I,6,0),IFERROR(VLOOKUP(B26*1,PEDIDOS!D:I,6,0),"" "")))")," ")
A27: =IFERROR(__xludf.DUMMYFUNCTION("""COMPUTED_VALUE"""),"FT120B35T") -> FT120B35T | B27: =IFERROR(__xludf.DUMMYFUNCTION("""COMPUTED_VALUE"""),"13113") -> 13113 | C27: =IFERROR(__xludf.DUMMYFUNCTION("""COMPUTED_VALUE"""),"NORMAL") -> NORMAL | D27: =IF(OR(F27<>" ",G27<>"")=TRUE,1,0) -> 1 | E27: =IFERROR(__xludf.DUMMYFUNCTION("IFERROR(VLOOKUP(TO_TEXT(B27),PEDIDOS!D:L,9,0),IFERROR(VLOOKUP(B27*1,PEDIDOS!D:L,9,0),"" ""))")," ") | F27: =IFERROR(__xludf.DUMMYFUNCTION("IF(B27="""","""",IFERROR(VLOOKUP(TO_TEXT(B27),PEDIDOS!D:I,6,0),IFERROR(VLOOKUP(B27*1,PEDIDOS!D:I,6,0),"" "")))")," ") | G27: =IFERROR(__xludf.DUMMYFUNCTION("IF(B27="""","""",IFERROR(VLOOKUP(TO_TEXT(B27),PEDIDOS!D:L,7,0),IFERROR(VLOOKUP(B27*1,PEDIDOS!D:L,7,0),"" "")))")," ")
A28: =IFERROR(__xludf.DUMMYFUNCTION("""COMPUTED_VALUE"""),"FT60F35") -> FT60F35 | B28: =IFERROR(__xludf.DUMMYFUNCTION("""COMPUTED_VALUE"""),"13190") -> 13190 | C28: =IFERROR(__xludf.DUMMYFUNCTION("""COMPUTED_VALUE"""),"PDX") -> PDX | D28: =IF(OR(F28<>" ",G28<>"")=TRUE,1,0) -> 0 | E28: =IFERROR(__xludf.DUMMYFUNCTION("IFERROR(VLOOKUP(TO_TEXT(B28),PEDIDOS!D:L,9,0),IFERROR(VLOOKUP(B28*1,PEDIDOS!D:L,9,0),"" ""))")," ") | F28: =IFERROR(__xludf.DUMMYFUNCTION("IF(B28="""","""",IFERROR(VLOOKUP(TO_TEXT(B28),PEDIDOS!D:I,6,0),IFERROR(VLOOKUP(B28*1,PEDIDOS!D:I,6,0),"" "")))")," ")
A29: =IFERROR(__xludf.DUMMYFUNCTION("""COMPUTED_VALUE"""),"FT60J35T") -> FT60J35T | B29: =IFERROR(__xludf.DUMMYFUNCTION("""COMPUTED_VALUE"""),"13313") -> 13313 | C29: =IFERROR(__xludf.DUMMYFUNCTION("""COMPUTED_VALUE"""),"NORMAL") -> NORMAL | D29: =IF(OR(F29<>" ",G29<>"")=TRUE,1,0) -> 0 | E29: =IFERROR(__xludf.DUMMYFUNCTION("IFERROR(VLOOKUP(TO_TEXT(B29),PEDIDOS!D:L,9,0),IFERROR(VLOOKUP(B29*1,PEDIDOS!D:L,9,0),"" ""))")," ") | F29: =IFERROR(__xludf.DUMMYFUNCTION("IF(B29="""","""",IFERROR(VLOOKUP(TO_TEXT(B29),PEDIDOS!D:I,6,0),IFERROR(VLOOKUP(B29*1,PEDIDOS!D:I,6,0),"" "")))")," ")
A30: =IFERROR(__xludf.DUMMYFUNCTION("""COMPUTED_VALUE"""),"FT120L35T") -> FT120L35T | B30: =IFERROR(__xludf.DUMMYFUNCTION("""COMPUTED_VALUE"""),"13327") -> 13327 | C30: =IFERROR(__xludf.DUMMYFUNCTION("""COMPUTED_VALUE"""),"NORMAL") -> NORMAL | D30: =IF(OR(F30<>" ",G30<>"")=TRUE,1,0) -> 1 | E30: =IFERROR(__xludf.DUMMYFUNCTION("IFERROR(VLOOKUP(TO_TEXT(B30),PEDIDOS!D:L,9,0),IFERROR(VLOOKUP(B30*1,PEDIDOS!D:L,9,0),"" ""))")," ") | F30: =IFERROR(__xludf.DUMMYFUNCTION("IF(B30="""","""",IFERROR(VLOOKUP(TO_TEXT(B30),PEDIDOS!D:I,6,0),IFERROR(VLOOKUP(B30*1,PEDIDOS!D:I,6,0),"" "")))")," ") | G30: =IFERROR(__xludf.DUMMYFUNCTION("IF(B30="""","""",IFERROR(VLOOKUP(TO_TEXT(B30),PEDIDOS!D:L,7,0),IFERROR(VLOOKUP(B30*1,PEDIDOS!D:L,7,0),"" "")))")," ")
A31: =IFERROR(__xludf.DUMMYFUNCTION("""COMPUTED_VALUE"""),"FT240J35") -> FT240J35 | B31: =IFERROR(__xludf.DUMMYFUNCTION("""COMPUTED_VALUE"""),"13353") -> 13353 | C31: =IFERROR(__xludf.DUMMYFUNCTION("""COMPUTED_VALUE"""),"PDX") -> PDX | D31: =IF(OR(F31<>" ",G31<>"")=TRUE,1,0) -> 0 | E31: =IFERROR(__xludf.DUMMYFUNCTION("IFERROR(VLOOKUP(TO_TEXT(B31),PEDIDOS!D:L,9,0),IFERROR(VLOOKUP(B31*1,PEDIDOS!D:L,9,0),"" ""))")," ") | F31: =IFERROR(__xludf.DUMMYFUNCTION("IF(B31="""","""",IFERROR(VLOOKUP(TO_TEXT(B31),PEDIDOS!D:I,6,0),IFERROR(VLOOKUP(B31*1,PEDIDOS!D:I,6,0),"" "")))")," ")
A32: =IFERROR(__xludf.DUMMYFUNCTION("""COMPUTED_VALUE"""),"FT120J35") -> FT120J35 | B32: =IFERROR(__xludf.DUMMYFUNCTION("""COMPUTED_VALUE"""),"13718") -> 13718 | C32: =IFERROR(__xludf.DUMMYFUNCTION("""COMPUTED_VALUE"""),"PDX") -> PDX | D32: =IF(OR(F32<>" ",G32<>"")=TRUE,1,0) -> 0 | E32: =IFERROR(__xludf.DUMMYFUNCTION("IFERROR(VLOOKUP(TO_TEXT(B32),PEDIDOS!D:L,9,0),IFERROR(VLOOKUP(B32*1,PEDIDOS!D:L,9,0),"" ""))")," ") | F32: =IFERROR(__xludf.DUMMYFUNCTION("IF(B32="""","""",IFERROR(VLOOKUP(TO_TEXT(B32),PEDIDOS!D:I,6,0),IFERROR(VLOOKUP(B32*1,PEDIDOS!D:I,6,0),"" "")))")," ")
A33: =IFERROR(__xludf.DUMMYFUNCTION("""COMPUTED_VALUE"""),"FT160F35") -> FT160F35 | B33: =IFERROR(__xludf.DUMMYFUNCTION("""COMPUTED_VALUE"""),"13751") -> 13751 | C33: =IFERROR(__xludf.DUMMYFUNCTION("""COMPUTED_VALUE"""),"PDX") -> PDX | D33: =IF(OR(F33<>" ",G33<>"")=TRUE,1,0) -> 1 | E33: =IFERROR(__xludf.DUMMYFUNCTION("IFERROR(VLOOKUP(TO_TEXT(B33),PEDIDOS!D:L,9,0),IFERROR(VLOOKUP(B33*1,PEDIDOS!D:L,9,0),"" ""))"),14121.0) -> 14121 | F33: =IFERROR(__xludf.DUMMYFUNCTION("IF(B33="""","""",IFERROR(VLOOKUP(TO_TEXT(B33),PEDIDOS!D:I,6,0),IFERROR(VLOOKUP(B33*1,PEDIDOS!D:I,6,0),"" "")))"),"ENTREGUE") -> ENTREGUE
A34: =IFERROR(__xludf.DUMMYFUNCTION("""COMPUTED_VALUE"""),"FTI75DPTBR") -> FTI75DPTBR | B34: =IFERROR(__xludf.DUMMYFUNCTION("""COMPUTED_VALUE"""),"13932") -> 13932 | C34: =IFERROR(__xludf.DUMMYFUNCTION("""COMPUTED_VALUE"""),"WI-FI") -> WI-FI | D34: =IF(OR(F34<>" ",G34<>"")=TRUE,1,0) -> 0 | E34: =IFERROR(__xludf.DUMMYFUNCTION("IFERROR(VLOOKUP(TO_TEXT(B34),PEDIDOS!D:L,9,0),IFERROR(VLOOKUP(B34*1,PEDIDOS!D:L,9,0),"" ""))")," ") | F34: =IFERROR(__xludf.DUMMYFUNCTION("IF(B34="""","""",IFERROR(VLOOKUP(TO_TEXT(B34),PEDIDOS!D:I,6,0),IFERROR(VLOOKUP(B34*1,PEDIDOS!D:I,6,0),"" "")))")," ")
A35: =IFERROR(__xludf.DUMMYFUNCTION("""COMPUTED_VALUE"""),"FT160F35") -> FT160F35 | B35: =IFERROR(__xludf.DUMMYFUNCTION("""COMPUTED_VALUE"""),"13972") -> 13972 | C35: =IFERROR(__xludf.DUMMYFUNCTION("""COMPUTED_VALUE"""),"PDX") -> PDX | D35: =IF(OR(F35<>" ",G35<>"")=TRUE,1,0) -> 0 | E35: =IFERROR(__xludf.DUMMYFUNCTION("IFERROR(VLOOKUP(TO_TEXT(B35),PEDIDOS!D:L,9,0),IFERROR(VLOOKUP(B35*1,PEDIDOS!D:L,9,0),"" ""))")," ") | F35: =IFERROR(__xludf.DUMMYFUNCTION("IF(B35="""","""",IFERROR(VLOOKUP(TO_TEXT(B35),PEDIDOS!D:I,6,0),IFERROR(VLOOKUP(B35*1,PEDIDOS!D:I,6,0),"" "")))")," ")
A36: =IFERROR(__xludf.DUMMYFUNCTION("""COMPUTED_VALUE"""),"FT60B35W") -> FT60B35W | B36: =IFERROR(__xludf.DUMMYFUNCTION("""COMPUTED_VALUE"""),"14023") -> 14023 | C36: =IFERROR(__xludf.DUMMYFUNCTION("""COMPUTED_VALUE"""),"WI-FI") -> WI-FI | D36: =IF(OR(F36<>" ",G36<>"")=TRUE,1,0) -> 0 | E36: =IFERROR(__xludf.DUMMYFUNCTION("IFERROR(VLOOKUP(TO_TEXT(B36),PEDIDOS!D:L,9,0),IFERROR(VLOOKUP(B36*1,PEDIDOS!D:L,9,0),"" ""))")," ") | F36: =IFERROR(__xludf.DUMMYFUNCTION("IF(B36="""","""",IFERROR(VLOOKUP(TO_TEXT(B36),PEDIDOS!D:I,6,0),IFERROR(VLOOKUP(B36*1,PEDIDOS!D:I,6,0),"" "")))")," ")
A37: =IFERROR(__xludf.DUMMYFUNCTION("""COMPUTED_VALUE"""),"FT240J35T") -> FT240J35T | B37: =IFERROR(__xludf.DUMMYFUNCTION("""COMPUTED_VALUE"""),"14050") -> 14050 | C37: =IFERROR(__xludf.DUMMYFUNCTION("""COMPUTED_VALUE"""),"NORMAL") -> NORMAL | D37: =IF(OR(F37<>" ",G37<>"")=TRUE,1,0) -> 0 | E37: =IFERROR(__xludf.DUMMYFUNCTION("IFERROR(VLOOKUP(TO_TEXT(B37),PEDIDOS!D:L,9,0),IFERROR(VLOOKUP(B37*1,PEDIDOS!D:L,9,0),"" ""))")," ") | F37: =IFERROR(__xludf.DUMMYFUNCTION("IF(B37="""","""",IFERROR(VLOOKUP(TO_TEXT(B37),PEDIDOS!D:I,6,0),IFERROR(VLOOKUP(B37*1,PEDIDOS!D:I,6,0),"" "")))")," ")
A38: =IFERROR(__xludf.DUMMYFUNCTION("""COMPUTED_VALUE"""),"FT160J35T") -> FT160J35T | B38: =IFERROR(__xludf.DUMMYFUNCTION("""COMPUTED_VALUE"""),"14089") -> 14089 | C38: =IFERROR(__xludf.DUMMYFUNCTION("""COMPUTED_VALUE"""),"SOBREPOR") -> SOBREPOR | D38: =IF(OR(F38<>" ",G38<>"")=TRUE,1,0) -> 0 | E38: =IFERROR(__xludf.DUMMYFUNCTION("IFERROR(VLOOKUP(TO_TEXT(B38),PEDIDOS!D:L,9,0),IFERROR(VLOOKUP(B38*1,PEDIDOS!D:L,9,0),"" ""))")," ") | F38: =IFERROR(__xludf.DUMMYFUNCTION("IF(B38="""","""",IFERROR(VLOOKUP(TO_TEXT(B38),PEDIDOS!D:I,6,0),IFERROR(VLOOKUP(B38*1,PEDIDOS!D:I,6,0),"" "")))")," ")
A39: =IFERROR(__xludf.DUMMYFUNCTION("""COMPUTED_VALUE"""),"FH160L60T") -> FH160L60T | B39: =IFERROR(__xludf.DUMMYFUNCTION("""COMPUTED_VALUE"""),"20005") -> 20005 | C39: =IFERROR(__xludf.DUMMYFUNCTION("""COMPUTED_VALUE"""),"NORMAL") -> NORMAL | D39: =IF(OR(F39<>" ",G39<>"")=TRUE,1,0) -> 0 | E39: =IFERROR(__xludf.DUMMYFUNCTION("IFERROR(VLOOKUP(TO_TEXT(B39),PEDIDOS!D:L,9,0),IFERROR(VLOOKUP(B39*1,PEDIDOS!D:L,9,0),"" ""))")," ") | F39: =IFERROR(__xludf.DUMMYFUNCTION("IF(B39="""","""",IFERROR(VLOOKUP(TO_TEXT(B39),PEDIDOS!D:I,6,0),IFERROR(VLOOKUP(B39*1,PEDIDOS!D:I,6,0),"" "")))")," ")
A40: =IFERROR(__xludf.DUMMYFUNCTION("""COMPUTED_VALUE"""),"FT60J35T") -> FT60J35T | B40: =IFERROR(__xludf.DUMMYFUNCTION("""COMPUTED_VALUE"""),"20008") -> 20008 | C40: =IFERROR(__xludf.DUMMYFUNCTION("""COMPUTED_VALUE"""),"NORMAL") -> NORMAL | D40: =IF(OR(F40<>" ",G40<>"")=TRUE,1,0) -> 0 | E40: =IFERROR(__xludf.DUMMYFUNCTION("IFERROR(VLOOKUP(TO_TEXT(B40),PEDIDOS!D:L,9,0),IFERROR(VLOOKUP(B40*1,PEDIDOS!D:L,9,0),"" ""))")," ") | F40: =IFERROR(__xludf.DUMMYFUNCTION("IF(B40="""","""",IFERROR(VLOOKUP(TO_TEXT(B40),PEDIDOS!D:I,6,0),IFERROR(VLOOKUP(B40*1,PEDIDOS!D:I,6,0),"" "")))")," ")
A41: =IFERROR(__xludf.DUMMYFUNCTION("""COMPUTED_VALUE"""),"FT60J35T") -> FT60J35T | B41: =IFERROR(__xludf.DUMMYFUNCTION("""COMPUTED_VALUE"""),"20009") -> 20009 | C41: =IFERROR(__xludf.DUMMYFUNCTION("""COMPUTED_VALUE"""),"NORMAL") -> NORMAL | D41: =IF(OR(F41<>" ",G41<>"")=TRUE,1,0) -> 0 | E41: =IFERROR(__xludf.DUMMYFUNCTION("IFERROR(VLOOKUP(TO_TEXT(B41),PEDIDOS!D:L,9,0),IFERROR(VLOOKUP(B41*1,PEDIDOS!D:L,9,0),"" ""))")," ") | F41: =IFERROR(__xludf.DUMMYFUNCTION("IF(B41="""","""",IFERROR(VLOOKUP(TO_TEXT(B41),PEDIDOS!D:I,6,0),IFERROR(VLOOKUP(B41*1,PEDIDOS!D:I,6,0),"" "")))")," ")
A42: =IFERROR(__xludf.DUMMYFUNCTION("""COMPUTED_VALUE"""),"FT60J35T") -> FT60J35T | B42: =IFERROR(__xludf.DUMMYFUNCTION("""COMPUTED_VALUE"""),"20010") -> 20010 | C42: =IFERROR(__xludf.DUMMYFUNCTION("""COMPUTED_VALUE"""),"NORMAL") -> NORMAL | D42: =IF(OR(F42<>" ",G42<>"")=TRUE,1,0) -> 0 | E42: =IFERROR(__xludf.DUMMYFUNCTION("IFERROR(VLOOKUP(TO_TEXT(B42),PEDIDOS!D:L,9,0),IFERROR(VLOOKUP(B42*1,PEDIDOS!D:L,9,0),"" ""))")," ") | F42: =IFERROR(__xludf.DUMMYFUNCTION("IF(B42="""","""",IFERROR(VLOOKUP(TO_TEXT(B42),PEDIDOS!D:I,6,0),IFERROR(VLOOKUP(B42*1,PEDIDOS!D:I,6,0),"" "")))")," ")
A43: =IFERROR(__xludf.DUMMYFUNCTION("""COMPUTED_VALUE"""),"FT180F35") -> FT180F35 | B43: =IFERROR(__xludf.DUMMYFUNCTION("""COMPUTED_VALUE"""),"20037") -> 20037 | C43: =IFERROR(__xludf.DUMMYFUNCTION("""COMPUTED_VALUE"""),"PDX") -> PDX | D43: =IF(OR(F43<>" ",G43<>"")=TRUE,1,0) -> 0 | E43: =IFERROR(__xludf.DUMMYFUNCTION("IFERROR(VLOOKUP(TO_TEXT(B43),PEDIDOS!D:L,9,0),IFERROR(VLOOKUP(B43*1,PEDIDOS!D:L,9,0),"" ""))")," ") | F43: =IFERROR(__xludf.DUMMYFUNCTION("IF(B43="""","""",IFERROR(VLOOKUP(TO_TEXT(B43),PEDIDOS!D:I,6,0),IFERROR(VLOOKUP(B43*1,PEDIDOS!D:I,6,0),"" "")))")," ")
A44: =IFERROR(__xludf.DUMMYFUNCTION("""COMPUTED_VALUE"""),"FT180J35") -> FT180J35 | B44: =IFERROR(__xludf.DUMMYFUNCTION("""COMPUTED_VALUE"""),"20038") -> 20038 | C44: =IFERROR(__xludf.DUMMYFUNCTION("""COMPUTED_VALUE"""),"PDX") -> PDX | D44: =IF(OR(F44<>" ",G44<>"")=TRUE,1,0) -> 0 | E44: =IFERROR(__xludf.DUMMYFUNCTION("IFERROR(VLOOKUP(TO_TEXT(B44),PEDIDOS!D:L,9,0),IFERROR(VLOOKUP(B44*1,PEDIDOS!D:L,9,0),"" ""))")," ") | F44: =IFERROR(__xludf.DUMMYFUNCTION("IF(B44="""","""",IFERROR(VLOOKUP(TO_TEXT(B44),PEDIDOS!D:I,6,0),IFERROR(VLOOKUP(B44*1,PEDIDOS!D:I,6,0),"" "")))")," ")
A45: =IFERROR(__xludf.DUMMYFUNCTION("""COMPUTED_VALUE"""),"FT160H35T") -> FT160H35T | B45: =IFERROR(__xludf.DUMMYFUNCTION("""COMPUTED_VALUE"""),"20042") -> 20042 | C45: =IFERROR(__xludf.DUMMYFUNCTION("""COMPUTED_VALUE"""),"NORMAL") -> NORMAL | D45: =IF(OR(F45<>" ",G45<>"")=TRUE,1,0) -> 0 | E45: =IFERROR(__xludf.DUMMYFUNCTION("IFERROR(VLOOKUP(TO_TEXT(B45),PEDIDOS!D:L,9,0),IFERROR(VLOOKUP(B45*1,PEDIDOS!D:L,9,0),"" ""))")," ") | F45: =IFERROR(__xludf.DUMMYFUNCTION("IF(B45="""","""",IFERROR(VLOOKUP(TO_TEXT(B45),PEDIDOS!D:I,6,0),IFERROR(VLOOKUP(B45*1,PEDIDOS!D:I,6,0),"" "")))")," ")
A46: =IFERROR(__xludf.DUMMYFUNCTION("""COMPUTED_VALUE"""),"FT160H35T") -> FT160H35T | B46: =IFERROR(__xludf.DUMMYFUNCTION("""COMPUTED_VALUE"""),"20043") -> 20043 | C46: =IFERROR(__xludf.DUMMYFUNCTION("""COMPUTED_VALUE"""),"NORMAL") -> NORMAL | D46: =IF(OR(F46<>" ",G46<>"")=TRUE,1,0) -> 0 | E46: =IFERROR(__xludf.DUMMYFUNCTION("IFERROR(VLOOKUP(TO_TEXT(B46),PEDIDOS!D:L,9,0),IFERROR(VLOOKUP(B46*1,PEDIDOS!D:L,9,0),"" ""))")," ") | F46: =IFERROR(__xludf.DUMMYFUNCTION("IF(B46="""","""",IFERROR(VLOOKUP(TO_TEXT(B46),PEDIDOS!D:I,6,0),IFERROR(VLOOKUP(B46*1,PEDIDOS!D:I,6,0),"" "")))")," ")
A47: =IFERROR(__xludf.DUMMYFUNCTION("""COMPUTED_VALUE"""),"FH100L60T") -> FH100L60T | B47: =IFERROR(__xludf.DUMMYFUNCTION("""COMPUTED_VALUE"""),"20137") -> 20137 | C47: =IFERROR(__xludf.DUMMYFUNCTION("""COMPUTED_VALUE"""),"NORMAL") -> NORMAL | D47: =IF(OR(F47<>" ",G47<>"")=TRUE,1,0) -> 0 | E47: =IFERROR(__xludf.DUMMYFUNCTION("IFERROR(VLOOKUP(TO_TEXT(B47),PEDIDOS!D:L,9,0),IFERROR(VLOOKUP(B47*1,PEDIDOS!D:L,9,0),"" ""))")," ") | F47: =IFERROR(__xludf.DUMMYFUNCTION("IF(B47="""","""",IFERROR(VLOOKUP(TO_TEXT(B47),PEDIDOS!D:I,6,0),IFERROR(VLOOKUP(B47*1,PEDIDOS!D:I,6,0),"" "")))")," ")
A48: =IFERROR(__xludf.DUMMYFUNCTION("""COMPUTED_VALUE"""),"BDC25A75PT - BANDEJA") -> BDC25A75PT - BANDEJA | B48: =IFERROR(__xludf.DUMMYFUNCTION("""COMPUTED_VALUE"""),"20088") -> 20088 | C48: =IFERROR(__xludf.DUMMYFUNCTION("""COMPUTED_VALUE"""),"BANDEJA") -> BANDEJA | D48: =IF(OR(F48<>" ",G48<>"")=TRUE,1,0) -> 0 | E48: =IFERROR(__xludf.DUMMYFUNCTION("IFERROR(VLOOKUP(TO_TEXT(B48),PEDIDOS!D:L,9,0),IFERROR(VLOOKUP(B48*1,PEDIDOS!D:L,9,0),"" ""))")," ") | F48: =IFERROR(__xludf.DUMMYFUNCTION("IF(B48="""","""",IFERROR(VLOOKUP(TO_TEXT(B48),PEDIDOS!D:I,6,0),IFERROR(VLOOKUP(B48*1,PEDIDOS!D:I,6,0),"" "")))")," ")
A49: =IFERROR(__xludf.DUMMYFUNCTION("""COMPUTED_VALUE"""),"BDC105A125PT - BANDEJA") -> BDC105A125PT - BANDEJA | B49: =IFERROR(__xludf.DUMMYFUNCTION("""COMPUTED_VALUE"""),"20087") -> 20087 | C49: =IFERROR(__xludf.DUMMYFUNCTION("""COMPUTED_VALUE"""),"BANDEJA") -> BANDEJA | D49: =IF(OR(F49<>" ",G49<>"")=TRUE,1,0) -> 0 | E49: =IFERROR(__xludf.DUMMYFUNCTION("IFERROR(VLOOKUP(TO_TEXT(B49),PEDIDOS!D:L,9,0),IFERROR(VLOOKUP(B49*1,PEDIDOS!D:L,9,0),"" ""))")," ") | F49: =IFERROR(__xludf.DUMMYFUNCTION("IF(B49="""","""",IFERROR(VLOOKUP(TO_TEXT(B49),PEDIDOS!D:I,6,0),IFERROR(VLOOKUP(B49*1,PEDIDOS!D:I,6,0),"" "")))")," ")
A50: =IFERROR(__xludf.DUMMYFUNCTION("""COMPUTED_VALUE"""),"FT160J35T") -> FT160J35T | B50: =IFERROR(__xludf.DUMMYFUNCTION("""COMPUTED_VALUE"""),"20103") -> 20103 | C50: =IFERROR(__xludf.DUMMYFUNCTION("""COMPUTED_VALUE"""),"NORMAL") -> NORMAL | D50: =IF(OR(F50<>" ",G50<>"")=TRUE,1,0) -> 0 | E50: =IFERROR(__xludf.DUMMYFUNCTION("IFERROR(VLOOKUP(TO_TEXT(B50),PEDIDOS!D:L,9,0),IFERROR(VLOOKUP(B50*1,PEDIDOS!D:L,9,0),"" ""))")," ") | F50: =IFERROR(__xludf.DUMMYFUNCTION("IF(B50="""","""",IFERROR(VLOOKUP(TO_TEXT(B50),PEDIDOS!D:I,6,0),IFERROR(VLOOKUP(B50*1,PEDIDOS!D:I,6,0),"" "")))")," ")
A51: =IFERROR(__xludf.DUMMYFUNCTION("""COMPUTED_VALUE"""),"FT180J35T") -> FT180J35T | B51: =IFERROR(__xludf.DUMMYFUNCTION("""COMPUTED_VALUE"""),"20123") -> 20123 | C51: =IFERROR(__xludf.DUMMYFUNCTION("""COMPUTED_VALUE"""),"NORMAL") -> NORMAL | D51: =IF(OR(F51<>" ",G51<>"")=TRUE,1,0) -> 0 | E51: =IFERROR(__xludf.DUMMYFUNCTION("IFERROR(VLOOKUP(TO_TEXT(B51),PEDIDOS!D:L,9,0),IFERROR(VLOOKUP(B51*1,PEDIDOS!D:L,9,0),"" ""))")," ") | F51: =IFERROR(__xludf.DUMMYFUNCTION("IF(B51="""","""",IFERROR(VLOOKUP(TO_TEXT(B51),PEDIDOS!D:I,6,0),IFERROR(VLOOKUP(B51*1,PEDIDOS!D:I,6,0),"" "")))")," ")
A52: =IFERROR(__xludf.DUMMYFUNCTION("""COMPUTED_VALUE"""),"FT160F35") -> FT160F35 | B52: =IFERROR(__xludf.DUMMYFUNCTION("""COMPUTED_VALUE"""),"20156") -> 20156 | C52: =IFERROR(__xludf.DUMMYFUNCTION("""COMPUTED_VALUE"""),"PDX") -> PDX | D52: =IF(OR(F52<>" ",G52<>"")=TRUE,1,0) -> 0 | E52: =IFERROR(__xludf.DUMMYFUNCTION("IFERROR(VLOOKUP(TO_TEXT(B52),PEDIDOS!D:L,9,0),IFERROR(VLOOKUP(B52*1,PEDIDOS!D:L,9,0),"" ""))")," ") | F52: =IFERROR(__xludf.DUMMYFUNCTION("IF(B52="""","""",IFERROR(VLOOKUP(TO_TEXT(B52),PEDIDOS!D:I,6,0),IFERROR(VLOOKUP(B52*1,PEDIDOS!D:I,6,0),"" "")))")," ")
A53: =IFERROR(__xludf.DUMMYFUNCTION("""COMPUTED_VALUE"""),"FT180F35T") -> FT180F35T | B53: =IFERROR(__xludf.DUMMYFUNCTION("""COMPUTED_VALUE"""),"20222") -> 20222 | C53: =IFERROR(__xludf.DUMMYFUNCTION("""COMPUTED_VALUE"""),"NORMAL") -> NORMAL | D53: =IF(OR(F53<>" ",G53<>"")=TRUE,1,0) -> 0 | E53: =IFERROR(__xludf.DUMMYFUNCTION("IFERROR(VLOOKUP(TO_TEXT(B53),PEDIDOS!D:L,9,0),IFERROR(VLOOKUP(B53*1,PEDIDOS!D:L,9,0),"" ""))")," ") | F53: =IFERROR(__xludf.DUMMYFUNCTION("IF(B53="""","""",IFERROR(VLOOKUP(TO_TEXT(B53),PEDIDOS!D:I,6,0),IFERROR(VLOOKUP(B53*1,PEDIDOS!D:I,6,0),"" "")))")," ")
A54: =IFERROR(__xludf.DUMMYFUNCTION("""COMPUTED_VALUE"""),"FT180F35T") -> FT180F35T | B54: =IFERROR(__xludf.DUMMYFUNCTION("""COMPUTED_VALUE"""),"20221") -> 20221 | C54: =IFERROR(__xludf.DUMMYFUNCTION("""COMPUTED_VALUE"""),"NORMAL") -> NORMAL | D54: =IF(OR(F54<>" ",G54<>"")=TRUE,1,0) -> 0 | E54: =IFERROR(__xludf.DUMMYFUNCTION("IFERROR(VLOOKUP(TO_TEXT(B54),PEDIDOS!D:L,9,0),IFERROR(VLOOKUP(B54*1,PEDIDOS!D:L,9,0),"" ""))")," ") | F54: =IFERROR(__xludf.DUMMYFUNCTION("IF(B54="""","""",IFERROR(VLOOKUP(TO_TEXT(B54),PEDIDOS!D:I,6,0),IFERROR(VLOOKUP(B54*1,PEDIDOS!D:I,6,0),"" "")))")," ")
A55: =IFERROR(__xludf.DUMMYFUNCTION("""COMPUTED_VALUE"""),"FT180L35T") -> FT180L35T | B55: =IFERROR(__xludf.DUMMYFUNCTION("""COMPUTED_VALUE"""),"20228") -> 20228 | C55: =IFERROR(__xludf.DUMMYFUNCTION("""COMPUTED_VALUE"""),"NORMAL") -> NORMAL | D55: =IF(OR(F55<>" ",G55<>"")=TRUE,1,0) -> 0 | E55: =IFERROR(__xludf.DUMMYFUNCTION("IFERROR(VLOOKUP(TO_TEXT(B55),PEDIDOS!D:L,9,0),IFERROR(VLOOKUP(B55*1,PEDIDOS!D:L,9,0),"" ""))")," ") | F55: =IFERROR(__xludf.DUMMYFUNCTION("IF(B55="""","""",IFERROR(VLOOKUP(TO_TEXT(B55),PEDIDOS!D:I,6,0),IFERROR(VLOOKUP(B55*1,PEDIDOS!D:I,6,0),"" "")))")," ")
A56: =IFERROR(__xludf.DUMMYFUNCTION("""COMPUTED_VALUE"""),"FT180L35T") -> FT180L35T | B56: =IFERROR(__xludf.DUMMYFUNCTION("""COMPUTED_VALUE"""),"20227") -> 20227 | C56: =IFERROR(__xludf.DUMMYFUNCTION("""COMPUTED_VALUE"""),"NORMAL") -> NORMAL | D56: =IF(OR(F56<>" ",G56<>"")=TRUE,1,0) -> 0 | E56: =IFERROR(__xludf.DUMMYFUNCTION("IFERROR(VLOOKUP(TO_TEXT(B56),PEDIDOS!D:L,9,0),IFERROR(VLOOKUP(B56*1,PEDIDOS!D:L,9,0),"" ""))")," ") | F56: =IFERROR(__xludf.DUMMYFUNCTION("IF(B56="""","""",IFERROR(VLOOKUP(TO_TEXT(B56),PEDIDOS!D:I,6,0),IFERROR(VLOOKUP(B56*1,PEDIDOS!D:I,6,0),"" "")))")," ")
A57: =IFERROR(__xludf.DUMMYFUNCTION("""COMPUTED_VALUE"""),"FT120F35T") -> FT120F35T | B57: =IFERROR(__xludf.DUMMYFUNCTION("""COMPUTED_VALUE"""),"20229") -> 20229 | C57: =IFERROR(__xludf.DUMMYFUNCTION("""COMPUTED_VALUE"""),"NORMAL") -> NORMAL | D57: =IF(OR(F57<>" ",G57<>"")=TRUE,1,0) -> 0 | E57: =IFERROR(__xludf.DUMMYFUNCTION("IFERROR(VLOOKUP(TO_TEXT(B57),PEDIDOS!D:L,9,0),IFERROR(VLOOKUP(B57*1,PEDIDOS!D:L,9,0),"" ""))")," ") | F57: =IFERROR(__xludf.DUMMYFUNCTION("IF(B57="""","""",IFERROR(VLOOKUP(TO_TEXT(B57),PEDIDOS!D:I,6,0),IFERROR(VLOOKUP(B57*1,PEDIDOS!D:I,6,0),"" "")))")," ")
A58: =IFERROR(__xludf.DUMMYFUNCTION("""COMPUTED_VALUE"""),"BDC25A75PT - BANDEJA") -> BDC25A75PT - BANDEJA | B58: =IFERROR(__xludf.DUMMYFUNCTION("""COMPUTED_VALUE"""),"20276") -> 20276 | C58: =IFERROR(__xludf.DUMMYFUNCTION("""COMPUTED_VALUE"""),"BANDEJA") -> BANDEJA | D58: =IF(OR(F58<>" ",G58<>"")=TRUE,1,0) -> 0 | E58: =IFERROR(__xludf.DUMMYFUNCTION("IFERROR(VLOOKUP(TO_TEXT(B58),PEDIDOS!D:L,9,0),IFERROR(VLOOKUP(B58*1,PEDIDOS!D:L,9,0),"" ""))")," ") | F58: =IFERROR(__xludf.DUMMYFUNCTION("IF(B58="""","""",IFERROR(VLOOKUP(TO_TEXT(B58),PEDIDOS!D:I,6,0),IFERROR(VLOOKUP(B58*1,PEDIDOS!D:I,6,0),"" "")))")," ")
A59: =IFERROR(__xludf.DUMMYFUNCTION("""COMPUTED_VALUE"""),"FT180F35T") -> FT180F35T | B59: =IFERROR(__xludf.DUMMYFUNCTION("""COMPUTED_VALUE"""),"20314") -> 20314 | C59: =IFERROR(__xludf.DUMMYFUNCTION("""COMPUTED_VALUE"""),"EXT") -> EXT | D59: =IF(OR(F59<>" ",G59<>"")=TRUE,1,0) -> 0 | E59: =IFERROR(__xludf.DUMMYFUNCTION("IFERROR(VLOOKUP(TO_TEXT(B59),PEDIDOS!D:L,9,0),IFERROR(VLOOKUP(B59*1,PEDIDOS!D:L,9,0),"" ""))")," ") | F59: =IFERROR(__xludf.DUMMYFUNCTION("IF(B59="""","""",IFERROR(VLOOKUP(TO_TEXT(B59),PEDIDOS!D:I,6,0),IFERROR(VLOOKUP(B59*1,PEDIDOS!D:I,6,0),"" "")))")," ")
A60: =IFERROR(__xludf.DUMMYFUNCTION("""COMPUTED_VALUE"""),"FT180F35T") -> FT180F35T | B60: =IFERROR(__xludf.DUMMYFUNCTION("""COMPUTED_VALUE"""),"20315") -> 20315 | C60: =IFERROR(__xludf.DUMMYFUNCTION("""COMPUTED_VALUE"""),"EXT") -> EXT | D60: =IF(OR(F60<>" ",G60<>"")=TRUE,1,0) -> 0 | E60: =IFERROR(__xludf.DUMMYFUNCTION("IFERROR(VLOOKUP(TO_TEXT(B60),PEDIDOS!D:L,9,0),IFERROR(VLOOKUP(B60*1,PEDIDOS!D:L,9,0),"" ""))")," ") | F60: =IFERROR(__xludf.DUMMYFUNCTION("IF(B60="""","""",IFERROR(VLOOKUP(TO_TEXT(B60),PEDIDOS!D:I,6,0),IFERROR(VLOOKUP(B60*1,PEDIDOS!D:I,6,0),"" "")))")," ")
A61: =IFERROR(__xludf.DUMMYFUNCTION("""COMPUTED_VALUE"""),"FT180F35T") -> FT180F35T | B61: =IFERROR(__xludf.DUMMYFUNCTION("""COMPUTED_VALUE"""),"20316") -> 20316 | C61: =IFERROR(__xludf.DUMMYFUNCTION("""COMPUTED_VALUE"""),"EXT") -> EXT | D61: =IF(OR(F61<>" ",G61<>"")=TRUE,1,0) -> 0 | E61: =IFERROR(__xludf.DUMMYFUNCTION("IFERROR(VLOOKUP(TO_TEXT(B61),PEDIDOS!D:L,9,0),IFERROR(VLOOKUP(B61*1,PEDIDOS!D:L,9,0),"" ""))")," ") | F61: =IFERROR(__xludf.DUMMYFUNCTION("IF(B61="""","""",IFERROR(VLOOKUP(TO_TEXT(B61),PEDIDOS!D:I,6,0),IFERROR(VLOOKUP(B61*1,PEDIDOS!D:I,6,0),"" "")))")," ")
A62: =IFERROR(__xludf.DUMMYFUNCTION("""COMPUTED_VALUE"""),"FT180F35T") -> FT180F35T | B62: =IFERROR(__xludf.DUMMYFUNCTION("""COMPUTED_VALUE"""),"20317") -> 20317 | C62: =IFERROR(__xludf.DUMMYFUNCTION("""COMPUTED_VALUE"""),"EXT") -> EXT | D62: =IF(OR(F62<>" ",G62<>"")=TRUE,1,0) -> 0 | E62: =IFERROR(__xludf.DUMMYFUNCTION("IFERROR(VLOOKUP(TO_TEXT(B62),PEDIDOS!D:L,9,0),IFERROR(VLOOKUP(B62*1,PEDIDOS!D:L,9,0),"" ""))")," ") | F62: =IFERROR(__xludf.DUMMYFUNCTION("IF(B62="""","""",IFERROR(VLOOKUP(TO_TEXT(B62),PEDIDOS!D:I,6,0),IFERROR(VLOOKUP(B62*1,PEDIDOS!D:I,6,0),"" "")))")," ")
A63: =IFERROR(__xludf.DUMMYFUNCTION("""COMPUTED_VALUE"""),"FT160L35T") -> FT160L35T | B63: =IFERROR(__xludf.DUMMYFUNCTION("""COMPUTED_VALUE"""),"20324") -> 20324 | C63: =IFERROR(__xludf.DUMMYFUNCTION("""COMPUTED_VALUE"""),"NORMAL") -> NORMAL | D63: =IF(OR(F63<>" ",G63<>"")=TRUE,1,0) -> 0 | E63: =IFERROR(__xludf.DUMMYFUNCTION("IFERROR(VLOOKUP(TO_TEXT(B63),PEDIDOS!D:L,9,0),IFERROR(VLOOKUP(B63*1,PEDIDOS!D:L,9,0),"" ""))")," ") | F63: =IFERROR(__xludf.DUMMYFUNCTION("IF(B63="""","""",IFERROR(VLOOKUP(TO_TEXT(B63),PEDIDOS!D:I,6,0),IFERROR(VLOOKUP(B63*1,PEDIDOS!D:I,6,0),"" "")))")," ")
A64: =IFERROR(__xludf.DUMMYFUNCTION("""COMPUTED_VALUE"""),"FT160L35T") -> FT160L35T | B64: =IFERROR(__xludf.DUMMYFUNCTION("""COMPUTED_VALUE"""),"20325") -> 20325 | C64: =IFERROR(__xludf.DUMMYFUNCTION("""COMPUTED_VALUE"""),"NORMAL") -> NORMAL | D64: =IF(OR(F64<>" ",G64<>"")=TRUE,1,0) -> 0 | E64: =IFERROR(__xludf.DUMMYFUNCTION("IFERROR(VLOOKUP(TO_TEXT(B64),PEDIDOS!D:L,9,0),IFERROR(VLOOKUP(B64*1,PEDIDOS!D:L,9,0),"" ""))")," ") | F64: =IFERROR(__xludf.DUMMYFUNCTION("IF(B64="""","""",IFERROR(VLOOKUP(TO_TEXT(B64),PEDIDOS!D:I,6,0),IFERROR(VLOOKUP(B64*1,PEDIDOS!D:I,6,0),"" "")))")," ")
A65: =IFERROR(__xludf.DUMMYFUNCTION("""COMPUTED_VALUE"""),"FTI145DPTBR") -> FTI145DPTBR | B65: =IFERROR(__xludf.DUMMYFUNCTION("""COMPUTED_VALUE"""),"20374") -> 20374 | C65: =IFERROR(__xludf.DUMMYFUNCTION("""COMPUTED_VALUE"""),"INVERTER") -> INVERTER | D65: =IF(OR(F65<>" ",G65<>"")=TRUE,1,0) -> 1 | F65: =IFERROR(__xludf.DUMMYFUNCTION("IF(B65="""","""",IFERROR(VLOOKUP(TO_TEXT(B65),PEDIDOS!D:I,6,0),IFERROR(VLOOKUP(B65*1,PEDIDOS!D:I,6,0),"" "")))"),"EM ABERTO") -> EM ABERTO
A66: =IFERROR(__xludf.DUMMYFUNCTION("""COMPUTED_VALUE"""),"FT80B35W") -> FT80B35W | B66: =IFERROR(__xludf.DUMMYFUNCTION("""COMPUTED_VALUE"""),"20377") -> 20377 | C66: =IFERROR(__xludf.DUMMYFUNCTION("""COMPUTED_VALUE"""),"WI-FI") -> WI-FI | D66: =IF(OR(F66<>" ",G66<>"")=TRUE,1,0) -> 1 | F66: =IFERROR(__xludf.DUMMYFUNCTION("IF(B66="""","""",IFERROR(VLOOKUP(TO_TEXT(B66),PEDIDOS!D:I,6,0),IFERROR(VLOOKUP(B66*1,PEDIDOS!D:I,6,0),"" "")))"),"TESTAR") -> TESTAR
A67: =IFERROR(__xludf.DUMMYFUNCTION("""COMPUTED_VALUE"""),"FT160F35T") -> FT160F35T | B67: =IFERROR(__xludf.DUMMYFUNCTION("""COMPUTED_VALUE"""),20397.0) -> 20397 | C67: =IFERROR(__xludf.DUMMYFUNCTION("""COMPUTED_VALUE"""),"SOBREPOR") -> SOBREPOR | D67: =IF(OR(F67<>" ",G67<>"")=TRUE,1,0) -> 1 | F67: =IFERROR(__xludf.DUMMYFUNCTION("IF(B67="""","""",IFERROR(VLOOKUP(TO_TEXT(B67),PEDIDOS!D:I,6,0),IFERROR(VLOOKUP(B67*1,PEDIDOS!D:I,6,0),"" "")))"),"FINALIZADO") -> FINALIZADO
D68: =IF(OR(F68<>" ",G68<>"")=TRUE,1,0) -> 1 | F68: =IFERROR(__xludf.DUMMYFUNCTION("IF(B68="""","""",IFERROR(VLOOKUP(TO_TEXT(B68),PEDIDOS!D:I,6,0),IFERROR(VLOOKUP(B68*1,PEDIDOS!D:I,6,0),"" "")))"),"")
D69: =IF(OR(F69<>" ",G69<>"")=TRUE,1,0) -> 1 | F69: =IFERROR(__xludf.DUMMYFUNCTION("IF(B69="""","""",IFERROR(VLOOKUP(TO_TEXT(B69),PEDIDOS!D:I,6,0),IFERROR(VLOOKUP(B69*1,PEDIDOS!D:I,6,0),"" "")))"),"")
D70: =IF(OR(F70<>" ",G70<>"")=TRUE,1,0) -> 1 | F70: =IFERROR(__xludf.DUMMYFUNCTION("IF(B70="""","""",IFERROR(VLOOKUP(TO_TEXT(B70),PEDIDOS!D:I,6,0),IFERROR(VLOOKUP(B70*1,PEDIDOS!D:I,6,0),"" "")))"),"")
D71: =IF(OR(F71<>" ",G71<>"")=TRUE,1,0) -> 1 | F71: =IFERROR(__xludf.DUMMYFUNCTION("IF(B71="""","""",IFERROR(VLOOKUP(TO_TEXT(B71),PEDIDOS!D:I,6,0),IFERROR(VLOOKUP(B71*1,PEDIDOS!D:I,6,0),"" "")))"),"")
D72: =IF(OR(F72<>" ",G72<>"")=TRUE,1,0) -> 1 | F72: =IFERROR(__xludf.DUMMYFUNCTION("IF(B72="""","""",IFERROR(VLOOKUP(TO_TEXT(B72),PEDIDOS!D:I,6,0),IFERROR(VLOOKUP(B72*1,PEDIDOS!D:I,6,0),"" "")))"),"")
D73: =IF(OR(F73<>" ",G73<>"")=TRUE,1,0) -> 1 | F73: =IFERROR(__xludf.DUMMYFUNCTION("IF(B73="""","""",IFERROR(VLOOKUP(TO_TEXT(B73),PEDIDOS!D:I,6,0),IFERROR(VLOOKUP(B73*1,PEDIDOS!D:I,6,0),"" "")))"),"") | G73: =IFERROR(__xludf.DUMMYFUNCTION("IF(B73="""","""",IFERROR(VLOOKUP(TO_TEXT(B73),PEDIDOS!D:L,7,0),IFERROR(VLOOKUP(B73*1,PEDIDOS!D:L,7,0),"" "")))"),"")
D74: =IF(OR(F74<>" ",G74<>"")=TRUE,1,0) -> 1 | F74: =IFERROR(__xludf.DUMMYFUNCTION("IF(B74="""","""",IFERROR(VLOOKUP(TO_TEXT(B74),PEDIDOS!D:I,6,0),IFERROR(VLOOKUP(B74*1,PEDIDOS!D:I,6,0),"" "")))"),"")
D75: =IF(OR(F75<>" ",G75<>"")=TRUE,1,0) -> 1 | F75: =IFERROR(__xludf.DUMMYFUNCTION("IF(B75="""","""",IFERROR(VLOOKUP(TO_TEXT(B75),PEDIDOS!D:I,6,0),IFERROR(VLOOKUP(B75*1,PEDIDOS!D:I,6,0),"" "")))"),"")
D76: =IF(OR(F76<>" ",G76<>"")=TRUE,1,0) -> 1 | F76: =IFERROR(__xludf.DUMMYFUNCTION("IF(B76="""","""",IFERROR(VLOOKUP(TO_TEXT(B76),PEDIDOS!D:I,6,0),IFERROR(VLOOKUP(B76*1,PEDIDOS!D:I,6,0),"" "")))"),"")
D77: =IF(OR(F77<>" ",G77<>"")=TRUE,1,0) -> 1 | F77: =IFERROR(__xludf.DUMMYFUNCTION("IF(B77="""","""",IFERROR(VLOOKUP(TO_TEXT(B77),PEDIDOS!D:I,6,0),IFERROR(VLOOKUP(B77*1,PEDIDOS!D:I,6,0),"" "")))"),"")
D78: =IF(OR(F78<>" ",G78<>"")=TRUE,1,0) -> 1 | F78: =IFERROR(__xludf.DUMMYFUNCTION("IF(B78="""","""",IFERROR(VLOOKUP(TO_TEXT(B78),PEDIDOS!D:I,6,0),IFERROR(VLOOKUP(B78*1,PEDIDOS!D:I,6,0),"" "")))"),"")
D79: =IF(OR(F79<>" ",G79<>"")=TRUE,1,0) -> 1 | F79: =IFERROR(__xludf.DUMMYFUNCTION("IF(B79="""","""",IFERROR(VLOOKUP(TO_TEXT(B79),PEDIDOS!D:I,6,0),IFERROR(VLOOKUP(B79*1,PEDIDOS!D:I,6,0),"" "")))"),"")
D80: =IF(OR(F80<>" ",G80<>"")=TRUE,1,0) -> 1 | F80: =IFERROR(__xludf.DUMMYFUNCTION("IF(B80="""","""",IFERROR(VLOOKUP(TO_TEXT(B80),PEDIDOS!D:I,6,0),IFERROR(VLOOKUP(B80*1,PEDIDOS!D:I,6,0),"" "")))"),"")
D81: =IF(OR(F81<>" ",G81<>"")=TRUE,1,0) -> 1 | F81: =IFERROR(__xludf.DUMMYFUNCTION("IF(B81="""","""",IFERROR(VLOOKUP(TO_TEXT(B81),PEDIDOS!D:I,6,0),IFERROR(VLOOKUP(B81*1,PEDIDOS!D:I,6,0),"" "")))"),"")
D82: =IF(OR(F82<>" ",G82<>"")=TRUE,1,0) -> 1 | F82: =IFERROR(__xludf.DUMMYFUNCTION("IF(B82="""","""",IFERROR(VLOOKUP(TO_TEXT(B82),PEDIDOS!D:I,6,0),IFERROR(VLOOKUP(B82*1,PEDIDOS!D:I,6,0),"" "")))"),"")
D83: =IF(OR(F83<>" ",G83<>"")=TRUE,1,0) -> 1 | F83: =IFERROR(__xludf.DUMMYFUNCTION("IF(B83="""","""",IFERROR(VLOOKUP(TO_TEXT(B83),PEDIDOS!D:I,6,0),IFERROR(VLOOKUP(B83*1,PEDIDOS!D:I,6,0),"" "")))"),"")
D84: =IF(OR(F84<>" ",G84<>"")=TRUE,1,0) -> 1 | F84: =IFERROR(__xludf.DUMMYFUNCTION("IF(B84="""","""",IFERROR(VLOOKUP(TO_TEXT(B84),PEDIDOS!D:I,6,0),IFERROR(VLOOKUP(B84*1,PEDIDOS!D:I,6,0),"" "")))"),"")
D85: =IF(OR(F85<>" ",G85<>"")=TRUE,1,0) -> 1 | F85: =IFERROR(__xludf.DUMMYFUNCTION("IF(B85="""","""",IFERROR(VLOOKUP(TO_TEXT(B85),PEDIDOS!D:I,6,0),IFERROR(VLOOKUP(B85*1,PEDIDOS!D:I,6,0),"" "")))"),"")
D86: =IF(OR(F86<>" ",G86<>"")=TRUE,1,0) -> 1 | F86: =IFERROR(__xludf.DUMMYFUNCTION("IF(B86="""","""",IFERROR(VLOOKUP(TO_TEXT(B86),PEDIDOS!D:I,6,0),IFERROR(VLOOKUP(B86*1,PEDIDOS!D:I,6,0),"" "")))"),"")
D87: =IF(OR(F87<>" ",G87<>"")=TRUE,1,0) -> 1 | F87: =IFERROR(__xludf.DUMMYFUNCTION("IF(B87="""","""",IFERROR(VLOOKUP(TO_TEXT(B87),PEDIDOS!D:I,6,0),IFERROR(VLOOKUP(B87*1,PEDIDOS!D:I,6,0),"" "")))"),"")
D88: =IF(OR(F88<>" ",G88<>"")=TRUE,1,0) -> 1 | F88: =IFERROR(__xludf.DUMMYFUNCTION("IF(B88="""","""",IFERROR(VLOOKUP(TO_TEXT(B88),PEDIDOS!D:I,6,0),IFERROR(VLOOKUP(B88*1,PEDIDOS!D:I,6,0),"" "")))"),"")
D89: =IF(OR(F89<>" ",G89<>"")=TRUE,1,0) -> 1 | F89: =IFERROR(__xludf.DUMMYFUNCTION("IF(B89="""","""",IFERROR(VLOOKUP(TO_TEXT(B89),PEDIDOS!D:I,6,0),IFERROR(VLOOKUP(B89*1,PEDIDOS!D:I,6,0),"" "")))"),"")
D90: =IF(OR(F90<>" ",G90<>"")=TRUE,1,0) -> 1 | F90: =IFERROR(__xludf.DUMMYFUNCTION("IF(B90="""","""",IFERROR(VLOOKUP(TO_TEXT(B90),PEDIDOS!D:I,6,0),IFERROR(VLOOKUP(B90*1,PEDIDOS!D:I,6,0),"" "")))"),"")
D91: =IF(OR(F91<>" ",G91<>"")=TRUE,1,0) -> 1 | F91: =IFERROR(__xludf.DUMMYFUNCTION("IF(B91="""","""",IFERROR(VLOOKUP(TO_TEXT(B91),PEDIDOS!D:I,6,0),IFERROR(VLOOKUP(B91*1,PEDIDOS!D:I,6,0),"" "")))"),"")
D92: =IF(OR(F92<>" ",G92<>"")=TRUE,1,0) -> 1 | F92: =IFERROR(__xludf.DUMMYFUNCTION("IF(B92="""","""",IFERROR(VLOOKUP(TO_TEXT(B92),PEDIDOS!D:I,6,0),IFERROR(VLOOKUP(B92*1,PEDIDOS!D:I,6,0),"" "")))"),"")
D93: =IF(OR(F93<>" ",G93<>"")=TRUE,1,0) -> 1 | F93: =IFERROR(__xludf.DUMMYFUNCTION("IF(B93="""","""",IFERROR(VLOOKUP(TO_TEXT(B93),PEDIDOS!D:I,6,0),IFERROR(VLOOKUP(B93*1,PEDIDOS!D:I,6,0),"" "")))"),"")
D94: =IF(OR(F94<>" ",G94<>"")=TRUE,1,0) -> 1 | F94: =IFERROR(__xludf.DUMMYFUNCTION("IF(B94="""","""",IFERROR(VLOOKUP(TO_TEXT(B94),PEDIDOS!D:I,6,0),IFERROR(VLOOKUP(B94*1,PEDIDOS!D:I,6,0),"" "")))"),"")
D95: =IF(OR(F95<>" ",G95<>"")=TRUE,1,0) -> 1 | F95: =IFERROR(__xludf.DUMMYFUNCTION("IF(B95="""","""",IFERROR(VLOOKUP(TO_TEXT(B95),PEDIDOS!D:I,6,0),IFERROR(VLOOKUP(B95*1,PEDIDOS!D:I,6,0),"" "")))"),"")
D96: =IF(OR(F96<>" ",G96<>"")=TRUE,1,0) -> 1 | F96: =IFERROR(__xludf.DUMMYFUNCTION("IF(B96="""","""",IFERROR(VLOOKUP(TO_TEXT(B96),PEDIDOS!D:I,6,0),IFERROR(VLOOKUP(B96*1,PEDIDOS!D:I,6,0),"" "")))"),"")
D97: =IF(OR(F97<>" ",G97<>"")=TRUE,1,0) -> 1 | F97: =IFERROR(__xludf.DUMMYFUNCTION("IF(B97="""","""",IFERROR(VLOOKUP(TO_TEXT(B97),PEDIDOS!D:I,6,0),IFERROR(VLOOKUP(B97*1,PEDIDOS!D:I,6,0),"" "")))"),"")
D98: =IF(OR(F98<>" ",G98<>"")=TRUE,1,0) -> 1 | F98: =IFERROR(__xludf.DUMMYFUNCTION("IF(B98="""","""",IFERROR(VLOOKUP(TO_TEXT(B98),PEDIDOS!D:I,6,0),IFERROR(VLOOKUP(B98*1,PEDIDOS!D:I,6,0),"" "")))"),"")
D99: =IF(OR(F99<>" ",G99<>"")=TRUE,1,0) -> 1 | F99: =IFERROR(__xludf.DUMMYFUNCTION("IF(B99="""","""",IFERROR(VLOOKUP(TO_TEXT(B99),PEDIDOS!D:I,6,0),IFERROR(VLOOKUP(B99*1,PEDIDOS!D:I,6,0),"" "")))"),"")
D100: =IF(OR(F100<>" ",G100<>"")=TRUE,1,0) -> 1 | F100: =IFERROR(__xludf.DUMMYFUNCTION("IF(B100="""","""",IFERROR(VLOOKUP(TO_TEXT(B100),PEDIDOS!D:I,6,0),IFERROR(VLOOKUP(B100*1,PEDIDOS!D:I,6,0),"" "")))"),"")
...

Sheet AGUARDAR CONTAINER
A1: PEDIDO | B1: CLIENTE/NOME FANTASIA | C1: QTY EM ESTOQUE | D1: ORDEM DE PROD INFOR. DE PROD. | E1: MODELO | F1: CONTROL | G1: TIPO DE QUADRO | H1: ESQ ESF | I1: SITUAÇÃO | J1: TRANSPORTADORA | K1: REDESPACHO | L1: NUMERO DA NOTA FISCAL | M1: EXPEDIDO POR | N1: VEICULO | O1: DATA DE ENTREGA | P1: OBSERVAÇÃO | Q1: INSERIDO POR | R1: APROVADO POR | S1: FINALIZADO POR | T1: INTEGRAÇÃO DO PEDIDO | U1: APROVAÇÃO PEDIDO | V1: FINALIZAÇÃO DA IDENTIFICAÇÃO | W1: 🔒 Row ID | X1: FORMA PGTO | Y1: DATA_PAGTO | Z1: VALOR | AA1: UF | AB1: REP | AC1: OBS GERAIS
A2: =IFERROR(__xludf.DUMMYFUNCTION("SORT(FILTER(PEDIDOS!A1:P1000,(PEDIDOS!I1:I1000=""AGUARDAR CONTAINER"")),5,TRUE )"),"18038-4") -> 18038-4 | B2: =IFERROR(__xludf.DUMMYFUNCTION("""COMPUTED_VALUE"""),"GLOBAL TECH BRASIL COMERCIO ELETRONICO LTDA") -> GLOBAL TECH BRASIL COMERCIO ELETRONICO LTDA | C2: =IFERROR(__xludf.DUMMYFUNCTION("""COMPUTED_VALUE"""),1.0) -> 1 | E2: =IFERROR(__xludf.DUMMYFUNCTION("""COMPUTED_VALUE"""),"FTI25D40PT") -> FTI25D40PT | F2: =IFERROR(__xludf.DUMMYFUNCTION("""COMPUTED_VALUE"""),"WI-FI") -> WI-FI | G2: =IFERROR(__xludf.DUMMYFUNCTION("""COMPUTED_VALUE"""),"NAO") -> NAO | H2: =IFERROR(__xludf.DUMMYFUNCTION("""COMPUTED_VALUE"""),"NAO") -> NAO | I2: =IFERROR(__xludf.DUMMYFUNCTION("""COMPUTED_VALUE"""),"AGUARDAR CONTAINER") -> AGUARDAR CONTAINER | J2: =IFERROR(__xludf.DUMMYFUNCTION("""COMPUTED_VALUE"""),"FITLOG") -> FITLOG | K2: =IFERROR(__xludf.DUMMYFUNCTION("""COMPUTED_VALUE"""),"SEM REDESPACHO") -> SEM REDESPACHO | L2: =IFERROR(__xludf.DUMMYFUNCTION("""COMPUTED_VALUE"""),-13519.0) -> -13519 | P2: =IFERROR(__xludf.DUMMYFUNCTION("""COMPUTED_VALUE"""),"FITLOG TRANSPORTES E LOGISTICA LTDA / (048) 996277956Informação Adicional: ENTRADA 30%+30/60/90/120 DS BOLETO . / E-mail para nota fiscal: , E-mail de cobrança: , Telefone para contat") -> FITLOG TRANSPORTES E LOGISTICA LTDA / (048) 996277956Informação Adicional: ENTRADA 30%+30/60/90/120 DS BOLETO . / E-mail para nota fiscal: , E-mail de cobrança: , Telefone para contat
A3: =IFERROR(__xludf.DUMMYFUNCTION("""COMPUTED_VALUE"""),"18038-5") -> 18038-5 | B3: =IFERROR(__xludf.DUMMYFUNCTION("""COMPUTED_VALUE"""),"GLOBAL TECH BRASIL COMERCIO ELETRONICO LTDA") -> GLOBAL TECH BRASIL COMERCIO ELETRONICO LTDA | C3: =IFERROR(__xludf.DUMMYFUNCTION("""COMPUTED_VALUE"""),1.0) -> 1 | E3: =IFERROR(__xludf.DUMMYFUNCTION("""COMPUTED_VALUE"""),"FTI25D40PT") -> FTI25D40PT | F3: =IFERROR(__xludf.DUMMYFUNCTION("""COMPUTED_VALUE"""),"WI-FI") -> WI-FI | G3: =IFERROR(__xludf.DUMMYFUNCTION("""COMPUTED_VALUE"""),"NAO") -> NAO | H3: =IFERROR(__xludf.DUMMYFUNCTION("""COMPUTED_VALUE"""),"NAO") -> NAO | I3: =IFERROR(__xludf.DUMMYFUNCTION("""COMPUTED_VALUE"""),"AGUARDAR CONTAINER") -> AGUARDAR CONTAINER | J3: =IFERROR(__xludf.DUMMYFUNCTION("""COMPUTED_VALUE"""),"FITLOG") -> FITLOG | K3: =IFERROR(__xludf.DUMMYFUNCTION("""COMPUTED_VALUE"""),"SEM REDESPACHO") -> SEM REDESPACHO | L3: =IFERROR(__xludf.DUMMYFUNCTION("""COMPUTED_VALUE"""),-13519.0) -> -13519 | P3: =IFERROR(__xludf.DUMMYFUNCTION("""COMPUTED_VALUE"""),"FITLOG TRANSPORTES E LOGISTICA LTDA / (048) 996277956Informação Adicional: ENTRADA 30%+30/60/90/120 DS BOLETO . / E-mail para nota fiscal: , E-mail de cobrança: , Telefone para contat") -> FITLOG TRANSPORTES E LOGISTICA LTDA / (048) 996277956Informação Adicional: ENTRADA 30%+30/60/90/120 DS BOLETO . / E-mail para nota fiscal: , E-mail de cobrança: , Telefone para contat
A4: =IFERROR(__xludf.DUMMYFUNCTION("""COMPUTED_VALUE"""),"18263-B") -> 18263-B | B4: =IFERROR(__xludf.DUMMYFUNCTION("""COMPUTED_VALUE"""),"AGUA E LAZER") -> AGUA E LAZER | C4: =IFERROR(__xludf.DUMMYFUNCTION("""COMPUTED_VALUE"""),1.0) -> 1 | E4: =IFERROR(__xludf.DUMMYFUNCTION("""COMPUTED_VALUE"""),"FTI25D40PT") -> FTI25D40PT | F4: =IFERROR(__xludf.DUMMYFUNCTION("""COMPUTED_VALUE"""),"WI-FI") -> WI-FI | G4: =IFERROR(__xludf.DUMMYFUNCTION("""COMPUTED_VALUE"""),"NAO") -> NAO | H4: =IFERROR(__xludf.DUMMYFUNCTION("""COMPUTED_VALUE"""),"NAO") -> NAO | I4: =IFERROR(__xludf.DUMMYFUNCTION("""COMPUTED_VALUE"""),"AGUARDAR CONTAINER") -> AGUARDAR CONTAINER | J4: =IFERROR(__xludf.DUMMYFUNCTION("""COMPUTED_VALUE"""),"FITLOG") -> FITLOG | K4: =IFERROR(__xludf.DUMMYFUNCTION("""COMPUTED_VALUE"""),"SETE LAGOAS") -> SETE LAGOAS | P4: =IFERROR(__xludf.DUMMYFUNCTION("""COMPUTED_VALUE"""),"FITLOG TRANSPORTES E LOGISTICA LTDA / (048) 996277956Informação Adicional: FRETE FOB COM REDESPACHO PELA SETE LAGOS CNPJ : 03.098.929/0005-17 - End. SP: RUA PEDRO DE TOLEDO, 407 - JARDIM SANTA LIDIA - GUARULHOS - SP - CEP 07140-000 - VALOR TOTAL DO PEDIDO"&": R$ 9.690,84 / Obs.Interna: ENTREGA FUTURA DIA 10/10/25 . / E-mail para nota fiscal: , E-mail de cobrança: , Telefone para contato <br>") -> FITLOG TRANSPORTES E LOGISTICA LTDA / (048) 996277956Informação Adicional: FRETE FOB COM REDESPACHO PELA SETE LAGOS CNPJ : 03.098.929/0005-17 - End. SP: RUA PEDRO DE TOLEDO, 407 - JARDIM SANTA LIDIA - GUARULHOS - SP - CEP 07140-000 - VALOR TOTAL DO PEDIDO: R$ 9.690,84 / Obs.Interna: ENTREGA FUTURA DIA 10/10/25 . / E-mail para nota fiscal: , E-mail de cobrança: , Telefone para contato <br>
A5: =IFERROR(__xludf.DUMMYFUNCTION("""COMPUTED_VALUE"""),"18422-D") -> 18422-D | B5: =IFERROR(__xludf.DUMMYFUNCTION("""COMPUTED_VALUE"""),"POOL ARARAS") -> POOL ARARAS | C5: =IFERROR(__xludf.DUMMYFUNCTION("""COMPUTED_VALUE"""),1.0) -> 1 | E5: =IFERROR(__xludf.DUMMYFUNCTION("""COMPUTED_VALUE"""),"FTI25D40PT") -> FTI25D40PT | F5: =IFERROR(__xludf.DUMMYFUNCTION("""COMPUTED_VALUE"""),"WI-FI") -> WI-FI | G5: =IFERROR(__xludf.DUMMYFUNCTION("""COMPUTED_VALUE"""),"NAO") -> NAO | H5: =IFERROR(__xludf.DUMMYFUNCTION("""COMPUTED_VALUE"""),"NAO") -> NAO | I5: =IFERROR(__xludf.DUMMYFUNCTION("""COMPUTED_VALUE"""),"AGUARDAR CONTAINER") -> AGUARDAR CONTAINER | J5: =IFERROR(__xludf.DUMMYFUNCTION("""COMPUTED_VALUE"""),"FITLOG") -> FITLOG | K5: =IFERROR(__xludf.DUMMYFUNCTION("""COMPUTED_VALUE"""),"TRANSRUAS ") -> TRANSRUAS | P5: =IFERROR(__xludf.DUMMYFUNCTION("""COMPUTED_VALUE"""),"FITLOG TRANSPORTES E LOGISTICA LTDA / (048) 996277956Obs.Interna: Entrega futura dia 10/10/2025 . / E-mail para nota fiscal: , E-mail de cobrança: , Telefone para contato") -> FITLOG TRANSPORTES E LOGISTICA LTDA / (048) 996277956Obs.Interna: Entrega futura dia 10/10/2025 . / E-mail para nota fiscal: , E-mail de cobrança: , Telefone para contato
A6: =IFERROR(__xludf.DUMMYFUNCTION("""COMPUTED_VALUE"""),"18422-E") -> 18422-E | B6: =IFERROR(__xludf.DUMMYFUNCTION("""COMPUTED_VALUE"""),"POOL ARARAS") -> POOL ARARAS | C6: =IFERROR(__xludf.DUMMYFUNCTION("""COMPUTED_VALUE"""),1.0) -> 1 | E6: =IFERROR(__xludf.DUMMYFUNCTION("""COMPUTED_VALUE"""),"FTI25D40PT") -> FTI25D40PT | F6: =IFERROR(__xludf.DUMMYFUNCTION("""COMPUTED_VALUE"""),"WI-FI") -> WI-FI | G6: =IFERROR(__xludf.DUMMYFUNCTION("""COMPUTED_VALUE"""),"NAO") -> NAO | H6: =IFERROR(__xludf.DUMMYFUNCTION("""COMPUTED_VALUE"""),"NAO") -> NAO | I6: =IFERROR(__xludf.DUMMYFUNCTION("""COMPUTED_VALUE"""),"AGUARDAR CONTAINER") -> AGUARDAR CONTAINER | J6: =IFERROR(__xludf.DUMMYFUNCTION("""COMPUTED_VALUE"""),"FITLOG") -> FITLOG | K6: =IFERROR(__xludf.DUMMYFUNCTION("""COMPUTED_VALUE"""),"TRANSRUAS ") -> TRANSRUAS | P6: =IFERROR(__xludf.DUMMYFUNCTION("""COMPUTED_VALUE"""),"FITLOG TRANSPORTES E LOGISTICA LTDA / (048) 996277956Obs.Interna: Entrega futura dia 10/10/2025 . / E-mail para nota fiscal: , E-mail de cobrança: , Telefone para contato") -> FITLOG TRANSPORTES E LOGISTICA LTDA / (048) 996277956Obs.Interna: Entrega futura dia 10/10/2025 . / E-mail para nota fiscal: , E-mail de cobrança: , Telefone para contato
A7: =IFERROR(__xludf.DUMMYFUNCTION("""COMPUTED_VALUE"""),"18422-F") -> 18422-F | B7: =IFERROR(__xludf.DUMMYFUNCTION("""COMPUTED_VALUE"""),"POOL ARARAS") -> POOL ARARAS | C7: =IFERROR(__xludf.DUMMYFUNCTION("""COMPUTED_VALUE"""),1.0) -> 1 | E7: =IFERROR(__xludf.DUMMYFUNCTION("""COMPUTED_VALUE"""),"FTI25D40PT") -> FTI25D40PT | F7: =IFERROR(__xludf.DUMMYFUNCTION("""COMPUTED_VALUE"""),"WI-FI") -> WI-FI | G7: =IFERROR(__xludf.DUMMYFUNCTION("""COMPUTED_VALUE"""),"NAO") -> NAO | H7: =IFERROR(__xludf.DUMMYFUNCTION("""COMPUTED_VALUE"""),"NAO") -> NAO | I7: =IFERROR(__xludf.DUMMYFUNCTION("""COMPUTED_VALUE"""),"AGUARDAR CONTAINER") -> AGUARDAR CONTAINER | J7: =IFERROR(__xludf.DUMMYFUNCTION("""COMPUTED_VALUE"""),"FITLOG") -> FITLOG | K7: =IFERROR(__xludf.DUMMYFUNCTION("""COMPUTED_VALUE"""),"TRANSRUAS ") -> TRANSRUAS | P7: =IFERROR(__xludf.DUMMYFUNCTION("""COMPUTED_VALUE"""),"FITLOG TRANSPORTES E LOGISTICA LTDA / (048) 996277956Obs.Interna: Entrega futura dia 10/10/2025 . / E-mail para nota fiscal: , E-mail de cobrança: , Telefone para contato") -> FITLOG TRANSPORTES E LOGISTICA LTDA / (048) 996277956Obs.Interna: Entrega futura dia 10/10/2025 . / E-mail para nota fiscal: , E-mail de cobrança: , Telefone para contato
A8: =IFERROR(__xludf.DUMMYFUNCTION("""COMPUTED_VALUE"""),"18422-G") -> 18422-G | B8: =IFERROR(__xludf.DUMMYFUNCTION("""COMPUTED_VALUE"""),"POOL ARARAS") -> POOL ARARAS | C8: =IFERROR(__xludf.DUMMYFUNCTION("""COMPUTED_VALUE"""),1.0) -> 1 | E8: =IFERROR(__xludf.DUMMYFUNCTION("""COMPUTED_VALUE"""),"FTI25D40PT") -> FTI25D40PT | F8: =IFERROR(__xludf.DUMMYFUNCTION("""COMPUTED_VALUE"""),"WI-FI") -> WI-FI | G8: =IFERROR(__xludf.DUMMYFUNCTION("""COMPUTED_VALUE"""),"NAO") -> NAO | H8: =IFERROR(__xludf.DUMMYFUNCTION("""COMPUTED_VALUE"""),"NAO") -> NAO | I8: =IFERROR(__xludf.DUMMYFUNCTION("""COMPUTED_VALUE"""),"AGUARDAR CONTAINER") -> AGUARDAR CONTAINER | J8: =IFERROR(__xludf.DUMMYFUNCTION("""COMPUTED_VALUE"""),"FITLOG") -> FITLOG | K8: =IFERROR(__xludf.DUMMYFUNCTION("""COMPUTED_VALUE"""),"TRANSRUAS ") -> TRANSRUAS | P8: =IFERROR(__xludf.DUMMYFUNCTION("""COMPUTED_VALUE"""),"FITLOG TRANSPORTES E LOGISTICA LTDA / (048) 996277956Obs.Interna: Entrega futura dia 10/10/2025 . / E-mail para nota fiscal: , E-mail de cobrança: , Telefone para contato") -> FITLOG TRANSPORTES E LOGISTICA LTDA / (048) 996277956Obs.Interna: Entrega futura dia 10/10/2025 . / E-mail para nota fiscal: , E-mail de cobrança: , Telefone para contato
A9: =IFERROR(__xludf.DUMMYFUNCTION("""COMPUTED_VALUE"""),"18432-F") -> 18432-F | B9: =IFERROR(__xludf.DUMMYFUNCTION("""COMPUTED_VALUE"""),"W E COMERCIO DE PISCINAS LTDA") -> W E COMERCIO DE PISCINAS LTDA | C9: =IFERROR(__xludf.DUMMYFUNCTION("""COMPUTED_VALUE"""),1.0) -> 1 | E9: =IFERROR(__xludf.DUMMYFUNCTION("""COMPUTED_VALUE"""),"FTI25D40PT") -> FTI25D40PT | F9: =IFERROR(__xludf.DUMMYFUNCTION("""COMPUTED_VALUE"""),"WI-FI") -> WI-FI | G9: =IFERROR(__xludf.DUMMYFUNCTION("""COMPUTED_VALUE"""),"NAO") -> NAO | H9: =IFERROR(__xludf.DUMMYFUNCTION("""COMPUTED_VALUE"""),"NAO") -> NAO | I9: =IFERROR(__xludf.DUMMYFUNCTION("""COMPUTED_VALUE"""),"AGUARDAR CONTAINER") -> AGUARDAR CONTAINER | J9: =IFERROR(__xludf.DUMMYFUNCTION("""COMPUTED_VALUE"""),"TRANSMIG TRANSPORTES RODOVIARIOS LTDA") -> TRANSMIG TRANSPORTES RODOVIARIOS LTDA | K9: =IFERROR(__xludf.DUMMYFUNCTION("""COMPUTED_VALUE"""),"SEM REDESPACHO") -> SEM REDESPACHO | L9: =IFERROR(__xludf.DUMMYFUNCTION("""COMPUTED_VALUE"""),-14235.0) -> -14235 | P9: =IFERROR(__xludf.DUMMYFUNCTION("""COMPUTED_VALUE"""),"CLIENTE RETIRA / (0) Obs.Interna: VALOR DA MAQUINA R$ 4.845,00 CLIENTE RETIRA NA FABRICA PREVISAO 10/10 QUANDO CHEGAR AS MAQUINAS INFORMAR TRANSPORTADORA - TRANSMIG TRANSPORTES RODOVIARIOS LTDA CNPJ: 11.693.111/0001-47 / E-mail para nota fiscal: , E-ma"&"il de cobrança: , Telefone para contato") -> CLIENTE RETIRA / (0) Obs.Interna: VALOR DA MAQUINA R$ 4.845,00 CLIENTE RETIRA NA FABRICA PREVISAO 10/10 QUANDO CHEGAR AS MAQUINAS INFORMAR TRANSPORTADORA - TRANSMIG TRANSPORTES RODOVIARIOS LTDA CNPJ: 11.693.111/0001-47 / E-mail para nota fiscal: , E-mail de cobrança: , Telefone para contato
A10: =IFERROR(__xludf.DUMMYFUNCTION("""COMPUTED_VALUE"""),"18432-G") -> 18432-G | B10: =IFERROR(__xludf.DUMMYFUNCTION("""COMPUTED_VALUE"""),"W E COMERCIO DE PISCINAS LTDA") -> W E COMERCIO DE PISCINAS LTDA | C10: =IFERROR(__xludf.DUMMYFUNCTION("""COMPUTED_VALUE"""),1.0) -> 1 | E10: =IFERROR(__xludf.DUMMYFUNCTION("""COMPUTED_VALUE"""),"FTI25D40PT") -> FTI25D40PT | F10: =IFERROR(__xludf.DUMMYFUNCTION("""COMPUTED_VALUE"""),"WI-FI") -> WI-FI | G10: =IFERROR(__xludf.DUMMYFUNCTION("""COMPUTED_VALUE"""),"NAO") -> NAO | H10: =IFERROR(__xludf.DUMMYFUNCTION("""COMPUTED_VALUE"""),"NAO") -> NAO | I10: =IFERROR(__xludf.DUMMYFUNCTION("""COMPUTED_VALUE"""),"AGUARDAR CONTAINER") -> AGUARDAR CONTAINER | J10: =IFERROR(__xludf.DUMMYFUNCTION("""COMPUTED_VALUE"""),"TRANSMIG TRANSPORTES RODOVIARIOS LTDA") -> TRANSMIG TRANSPORTES RODOVIARIOS LTDA | K10: =IFERROR(__xludf.DUMMYFUNCTION("""COMPUTED_VALUE"""),"SEM REDESPACHO") -> SEM REDESPACHO | L10: =IFERROR(__xludf.DUMMYFUNCTION("""COMPUTED_VALUE"""),-14235.0) -> -14235 | P10: =IFERROR(__xludf.DUMMYFUNCTION("""COMPUTED_VALUE"""),"CLIENTE RETIRA / (0) Obs.Interna: VALOR DA MAQUINA R$ 4.845,00 CLIENTE RETIRA NA FABRICA PREVISAO 10/10 QUANDO CHEGAR AS MAQUINAS INFORMAR TRANSPORTADORA - TRANSMIG TRANSPORTES RODOVIARIOS LTDA CNPJ: 11.693.111/0001-47 / E-mail para nota fiscal: , E-ma"&"il de cobrança: , Telefone para contato") -> CLIENTE RETIRA / (0) Obs.Interna: VALOR DA MAQUINA R$ 4.845,00 CLIENTE RETIRA NA FABRICA PREVISAO 10/10 QUANDO CHEGAR AS MAQUINAS INFORMAR TRANSPORTADORA - TRANSMIG TRANSPORTES RODOVIARIOS LTDA CNPJ: 11.693.111/0001-47 / E-mail para nota fiscal: , E-mail de cobrança: , Telefone para contato
A11: =IFERROR(__xludf.DUMMYFUNCTION("""COMPUTED_VALUE"""),"18432-H") -> 18432-H | B11: =IFERROR(__xludf.DUMMYFUNCTION("""COMPUTED_VALUE"""),"W E COMERCIO DE PISCINAS LTDA") -> W E COMERCIO DE PISCINAS LTDA | C11: =IFERROR(__xludf.DUMMYFUNCTION("""COMPUTED_VALUE"""),1.0) -> 1 | E11: =IFERROR(__xludf.DUMMYFUNCTION("""COMPUTED_VALUE"""),"FTI25D40PT") -> FTI25D40PT | F11: =IFERROR(__xludf.DUMMYFUNCTION("""COMPUTED_VALUE"""),"WI-FI") -> WI-FI | G11: =IFERROR(__xludf.DUMMYFUNCTION("""COMPUTED_VALUE"""),"NAO") -> NAO | H11: =IFERROR(__xludf.DUMMYFUNCTION("""COMPUTED_VALUE"""),"NAO") -> NAO | I11: =IFERROR(__xludf.DUMMYFUNCTION("""COMPUTED_VALUE"""),"AGUARDAR CONTAINER") -> AGUARDAR CONTAINER | J11: =IFERROR(__xludf.DUMMYFUNCTION("""COMPUTED_VALUE"""),"TRANSMIG TRANSPORTES RODOVIARIOS LTDA") -> TRANSMIG TRANSPORTES RODOVIARIOS LTDA | K11: =IFERROR(__xludf.DUMMYFUNCTION("""COMPUTED_VALUE"""),"SEM REDESPACHO") -> SEM REDESPACHO | L11: =IFERROR(__xludf.DUMMYFUNCTION("""COMPUTED_VALUE"""),-14235.0) -> -14235 | P11: =IFERROR(__xludf.DUMMYFUNCTION("""COMPUTED_VALUE"""),"CLIENTE RETIRA / (0) Obs.Interna: VALOR DA MAQUINA R$ 4.845,00 CLIENTE RETIRA NA FABRICA PREVISAO 10/10 QUANDO CHEGAR AS MAQUINAS INFORMAR TRANSPORTADORA - TRANSMIG TRANSPORTES RODOVIARIOS LTDA CNPJ: 11.693.111/0001-47 / E-mail para nota fiscal: , E-ma"&"il de cobrança: , Telefone para contato") -> CLIENTE RETIRA / (0) Obs.Interna: VALOR DA MAQUINA R$ 4.845,00 CLIENTE RETIRA NA FABRICA PREVISAO 10/10 QUANDO CHEGAR AS MAQUINAS INFORMAR TRANSPORTADORA - TRANSMIG TRANSPORTES RODOVIARIOS LTDA CNPJ: 11.693.111/0001-47 / E-mail para nota fiscal: , E-mail de cobrança: , Telefone para contato
A12: =IFERROR(__xludf.DUMMYFUNCTION("""COMPUTED_VALUE"""),"18432-I") -> 18432-I | B12: =IFERROR(__xludf.DUMMYFUNCTION("""COMPUTED_VALUE"""),"W E COMERCIO DE PISCINAS LTDA") -> W E COMERCIO DE PISCINAS LTDA | C12: =IFERROR(__xludf.DUMMYFUNCTION("""COMPUTED_VALUE"""),1.0) -> 1 | E12: =IFERROR(__xludf.DUMMYFUNCTION("""COMPUTED_VALUE"""),"FTI25D40PT") -> FTI25D40PT | F12: =IFERROR(__xludf.DUMMYFUNCTION("""COMPUTED_VALUE"""),"WI-FI") -> WI-FI | G12: =IFERROR(__xludf.DUMMYFUNCTION("""COMPUTED_VALUE"""),"NAO") -> NAO | H12: =IFERROR(__xludf.DUMMYFUNCTION("""COMPUTED_VALUE"""),"NAO") -> NAO | I12: =IFERROR(__xludf.DUMMYFUNCTION("""COMPUTED_VALUE"""),"AGUARDAR CONTAINER") -> AGUARDAR CONTAINER | J12: =IFERROR(__xludf.DUMMYFUNCTION("""COMPUTED_VALUE"""),"TRANSMIG TRANSPORTES RODOVIARIOS LTDA") -> TRANSMIG TRANSPORTES RODOVIARIOS LTDA | K12: =IFERROR(__xludf.DUMMYFUNCTION("""COMPUTED_VALUE"""),"SEM REDESPACHO") -> SEM REDESPACHO | L12: =IFERROR(__xludf.DUMMYFUNCTION("""COMPUTED_VALUE"""),-14235.0) -> -14235 | P12: =IFERROR(__xludf.DUMMYFUNCTION("""COMPUTED_VALUE"""),"CLIENTE RETIRA / (0) Obs.Interna: VALOR DA MAQUINA R$ 4.845,00 CLIENTE RETIRA NA FABRICA PREVISAO 10/10 QUANDO CHEGAR AS MAQUINAS INFORMAR TRANSPORTADORA - TRANSMIG TRANSPORTES RODOVIARIOS LTDA CNPJ: 11.693.111/0001-47 / E-mail para nota fiscal: , E-ma"&"il de cobrança: , Telefone para contato") -> CLIENTE RETIRA / (0) Obs.Interna: VALOR DA MAQUINA R$ 4.845,00 CLIENTE RETIRA NA FABRICA PREVISAO 10/10 QUANDO CHEGAR AS MAQUINAS INFORMAR TRANSPORTADORA - TRANSMIG TRANSPORTES RODOVIARIOS LTDA CNPJ: 11.693.111/0001-47 / E-mail para nota fiscal: , E-mail de cobrança: , Telefone para contato
A13: =IFERROR(__xludf.DUMMYFUNCTION("""COMPUTED_VALUE"""),"18432-J") -> 18432-J | B13: =IFERROR(__xludf.DUMMYFUNCTION("""COMPUTED_VALUE"""),"W E COMERCIO DE PISCINAS LTDA") -> W E COMERCIO DE PISCINAS LTDA | C13: =IFERROR(__xludf.DUMMYFUNCTION("""COMPUTED_VALUE"""),1.0) -> 1 | E13: =IFERROR(__xludf.DUMMYFUNCTION("""COMPUTED_VALUE"""),"FTI25D40PT") -> FTI25D40PT | F13: =IFERROR(__xludf.DUMMYFUNCTION("""COMPUTED_VALUE"""),"WI-FI") -> WI-FI | G13: =IFERROR(__xludf.DUMMYFUNCTION("""COMPUTED_VALUE"""),"NAO") -> NAO | H13: =IFERROR(__xludf.DUMMYFUNCTION("""COMPUTED_VALUE"""),"NAO") -> NAO | I13: =IFERROR(__xludf.DUMMYFUNCTION("""COMPUTED_VALUE"""),"AGUARDAR CONTAINER") -> AGUARDAR CONTAINER | J13: =IFERROR(__xludf.DUMMYFUNCTION("""COMPUTED_VALUE"""),"TRANSMIG TRANSPORTES RODOVIARIOS LTDA") -> TRANSMIG TRANSPORTES RODOVIARIOS LTDA | K13: =IFERROR(__xludf.DUMMYFUNCTION("""COMPUTED_VALUE"""),"SEM REDESPACHO") -> SEM REDESPACHO | L13: =IFERROR(__xludf.DUMMYFUNCTION("""COMPUTED_VALUE"""),-14235.0) -> -14235 | P13: =IFERROR(__xludf.DUMMYFUNCTION("""COMPUTED_VALUE"""),"CLIENTE RETIRA / (0) Obs.Interna: VALOR DA MAQUINA R$ 4.845,00 CLIENTE RETIRA NA FABRICA PREVISAO 10/10 QUANDO CHEGAR AS MAQUINAS INFORMAR TRANSPORTADORA - TRANSMIG TRANSPORTES RODOVIARIOS LTDA CNPJ: 11.693.111/0001-47 / E-mail para nota fiscal: , E-ma"&"il de cobrança: , Telefone para contato") -> CLIENTE RETIRA / (0) Obs.Interna: VALOR DA MAQUINA R$ 4.845,00 CLIENTE RETIRA NA FABRICA PREVISAO 10/10 QUANDO CHEGAR AS MAQUINAS INFORMAR TRANSPORTADORA - TRANSMIG TRANSPORTES RODOVIARIOS LTDA CNPJ: 11.693.111/0001-47 / E-mail para nota fiscal: , E-mail de cobrança: , Telefone para contato
A14: =IFERROR(__xludf.DUMMYFUNCTION("""COMPUTED_VALUE"""),"18518") -> 18518 | B14: =IFERROR(__xludf.DUMMYFUNCTION("""COMPUTED_VALUE"""),"KYP COMERCIO DE EQUIPAMENTOS PARA PISCINAS LTDA") -> KYP COMERCIO DE EQUIPAMENTOS PARA PISCINAS LTDA | C14: =IFERROR(__xludf.DUMMYFUNCTION("""COMPUTED_VALUE"""),1.0) -> 1 | E14: =IFERROR(__xludf.DUMMYFUNCTION("""COMPUTED_VALUE"""),"FTI25D40PT") -> FTI25D40PT | F14: =IFERROR(__xludf.DUMMYFUNCTION("""COMPUTED_VALUE"""),"WI-FI") -> WI-FI | G14: =IFERROR(__xludf.DUMMYFUNCTION("""COMPUTED_VALUE"""),"NAO") -> NAO | H14: =IFERROR(__xludf.DUMMYFUNCTION("""COMPUTED_VALUE"""),"NAO") -> NAO | I14: =IFERROR(__xludf.DUMMYFUNCTION("""COMPUTED_VALUE"""),"AGUARDAR CONTAINER") -> AGUARDAR CONTAINER | J14: =IFERROR(__xludf.DUMMYFUNCTION("""COMPUTED_VALUE"""),"FITLOG") -> FITLOG | K14: =IFERROR(__xludf.DUMMYFUNCTION("""COMPUTED_VALUE"""),"SEM REDESPACHO") -> SEM REDESPACHO | P14: =IFERROR(__xludf.DUMMYFUNCTION("""COMPUTED_VALUE"""),"FITLOG TRANSPORTES E LOGISTICA LTDA / (048) 996277956Informação Adicional: Cliente: Paulo Cesar / Obs.Interna: entrega futura em 10/10 / E-mail para nota fiscal: , E-mail de cobrança: , Telefone para contato") -> FITLOG TRANSPORTES E LOGISTICA LTDA / (048) 996277956Informação Adicional: Cliente: Paulo Cesar / Obs.Interna: entrega futura em 10/10 / E-mail para nota fiscal: , E-mail de cobrança: , Telefone para contato
A15: =IFERROR(__xludf.DUMMYFUNCTION("""COMPUTED_VALUE"""),"18661-A") -> 18661-A | B15: =IFERROR(__xludf.DUMMYFUNCTION("""COMPUTED_VALUE"""),"GLOBAL TECH BRASIL COMERCIO ELETRONICO LTDA") -> GLOBAL TECH BRASIL COMERCIO ELETRONICO LTDA | C15: =IFERROR(__xludf.DUMMYFUNCTION("""COMPUTED_VALUE"""),1.0) -> 1 | E15: =IFERROR(__xludf.DUMMYFUNCTION("""COMPUTED_VALUE"""),"FTI25D40PT") -> FTI25D40PT | F15: =IFERROR(__xludf.DUMMYFUNCTION("""COMPUTED_VALUE"""),"WI-FI") -> WI-FI | G15: =IFERROR(__xludf.DUMMYFUNCTION("""COMPUTED_VALUE"""),"NAO") -> NAO | H15: =IFERROR(__xludf.DUMMYFUNCTION("""COMPUTED_VALUE"""),"NAO") -> NAO | I15: =IFERROR(__xludf.DUMMYFUNCTION("""COMPUTED_VALUE"""),"AGUARDAR CONTAINER") -> AGUARDAR CONTAINER | J15: =IFERROR(__xludf.DUMMYFUNCTION("""COMPUTED_VALUE"""),"FITLOG") -> FITLOG | K15: =IFERROR(__xludf.DUMMYFUNCTION("""COMPUTED_VALUE"""),"SEM REDESPACHO") -> SEM REDESPACHO | P15: =IFERROR(__xludf.DUMMYFUNCTION("""COMPUTED_VALUE"""),"FITLOG TRANSPORTES E LOGISTICA LTDA / (048) 996277956Informação Adicional: Pedido de Compra Nº 7990 / E-mail para nota fiscal: , E-mail de cobrança: , Telefone para contato") -> FITLOG TRANSPORTES E LOGISTICA LTDA / (048) 996277956Informação Adicional: Pedido de Compra Nº 7990 / E-mail para nota fiscal: , E-mail de cobrança: , Telefone para contato
A16: =IFERROR(__xludf.DUMMYFUNCTION("""COMPUTED_VALUE"""),"18661-B") -> 18661-B | B16: =IFERROR(__xludf.DUMMYFUNCTION("""COMPUTED_VALUE"""),"GLOBAL TECH BRASIL COMERCIO ELETRONICO LTDA") -> GLOBAL TECH BRASIL COMERCIO ELETRONICO LTDA | C16: =IFERROR(__xludf.DUMMYFUNCTION("""COMPUTED_VALUE"""),1.0) -> 1 | E16: =IFERROR(__xludf.DUMMYFUNCTION("""COMPUTED_VALUE"""),"FTI25D40PT") -> FTI25D40PT | F16: =IFERROR(__xludf.DUMMYFUNCTION("""COMPUTED_VALUE"""),"WI-FI") -> WI-FI | G16: =IFERROR(__xludf.DUMMYFUNCTION("""COMPUTED_VALUE"""),"NAO") -> NAO | H16: =IFERROR(__xludf.DUMMYFUNCTION("""COMPUTED_VALUE"""),"NAO") -> NAO | I16: =IFERROR(__xludf.DUMMYFUNCTION("""COMPUTED_VALUE"""),"AGUARDAR CONTAINER") -> AGUARDAR CONTAINER | J16: =IFERROR(__xludf.DUMMYFUNCTION("""COMPUTED_VALUE"""),"FITLOG") -> FITLOG | K16: =IFERROR(__xludf.DUMMYFUNCTION("""COMPUTED_VALUE"""),"SEM REDESPACHO") -> SEM REDESPACHO | P16: =IFERROR(__xludf.DUMMYFUNCTION("""COMPUTED_VALUE"""),"FITLOG TRANSPORTES E LOGISTICA LTDA / (048) 996277956Informação Adicional: Pedido de Compra Nº 7990 / E-mail para nota fiscal: , E-mail de cobrança: , Telefone para contato") -> FITLOG TRANSPORTES E LOGISTICA LTDA / (048) 996277956Informação Adicional: Pedido de Compra Nº 7990 / E-mail para nota fiscal: , E-mail de cobrança: , Telefone para contato
A17: =IFERROR(__xludf.DUMMYFUNCTION("""COMPUTED_VALUE"""),"18665-A") -> 18665-A | B17: =IFERROR(__xludf.DUMMYFUNCTION("""COMPUTED_VALUE"""),"AQUAFIX EQUIPAMENTOS PARA PISCINAS") -> AQUAFIX EQUIPAMENTOS PARA PISCINAS | C17: =IFERROR(__xludf.DUMMYFUNCTION("""COMPUTED_VALUE"""),1.0) -> 1 | E17: =IFERROR(__xludf.DUMMYFUNCTION("""COMPUTED_VALUE"""),"FTI25D40PT") -> FTI25D40PT | F17: =IFERROR(__xludf.DUMMYFUNCTION("""COMPUTED_VALUE"""),"WI-FI") -> WI-FI | G17: =IFERROR(__xludf.DUMMYFUNCTION("""COMPUTED_VALUE"""),"NAO") -> NAO | H17: =IFERROR(__xludf.DUMMYFUNCTION("""COMPUTED_VALUE"""),"NAO") -> NAO | I17: =IFERROR(__xludf.DUMMYFUNCTION("""COMPUTED_VALUE"""),"AGUARDAR CONTAINER") -> AGUARDAR CONTAINER | J17: =IFERROR(__xludf.DUMMYFUNCTION("""COMPUTED_VALUE"""),"EXPRESSO SAO MIGUEL") -> EXPRESSO SAO MIGUEL | K17: =IFERROR(__xludf.DUMMYFUNCTION("""COMPUTED_VALUE"""),"SEM REDESPACHO") -> SEM REDESPACHO | P17: =IFERROR(__xludf.DUMMYFUNCTION("""COMPUTED_VALUE"""),"EXPRESSO SAO MIGUEL S/A / (049) 3361-6627Informação Adicional: VALOR DE CADA MAQUINA 4845,00 ENTRADA DE 50% + 50% 30/60/90 / E-mail para nota fiscal: , E-mail de cobrança: , Telefone para contato") -> EXPRESSO SAO MIGUEL S/A / (049) 3361-6627Informação Adicional: VALOR DE CADA MAQUINA 4845,00 ENTRADA DE 50% + 50% 30/60/90 / E-mail para nota fiscal: , E-mail de cobrança: , Telefone para contato
A18: =IFERROR(__xludf.DUMMYFUNCTION("""COMPUTED_VALUE"""),"18665-B") -> 18665-B | B18: =IFERROR(__xludf.DUMMYFUNCTION("""COMPUTED_VALUE"""),"AQUAFIX EQUIPAMENTOS PARA PISCINAS") -> AQUAFIX EQUIPAMENTOS PARA PISCINAS | C18: =IFERROR(__xludf.DUMMYFUNCTION("""COMPUTED_VALUE"""),1.0) -> 1 | E18: =IFERROR(__xludf.DUMMYFUNCTION("""COMPUTED_VALUE"""),"FTI25D40PT") -> FTI25D40PT | F18: =IFERROR(__xludf.DUMMYFUNCTION("""COMPUTED_VALUE"""),"WI-FI") -> WI-FI | G18: =IFERROR(__xludf.DUMMYFUNCTION("""COMPUTED_VALUE"""),"NAO") -> NAO | H18: =IFERROR(__xludf.DUMMYFUNCTION("""COMPUTED_VALUE"""),"NAO") -> NAO | I18: =IFERROR(__xludf.DUMMYFUNCTION("""COMPUTED_VALUE"""),"AGUARDAR CONTAINER") -> AGUARDAR CONTAINER | J18: =IFERROR(__xludf.DUMMYFUNCTION("""COMPUTED_VALUE"""),"EXPRESSO SAO MIGUEL") -> EXPRESSO SAO MIGUEL | K18: =IFERROR(__xludf.DUMMYFUNCTION("""COMPUTED_VALUE"""),"SEM REDESPACHO") -> SEM REDESPACHO | P18: =IFERROR(__xludf.DUMMYFUNCTION("""COMPUTED_VALUE"""),"EXPRESSO SAO MIGUEL S/A / (049) 3361-6627Informação Adicional: VALOR DE CADA MAQUINA 4845,00 ENTRADA DE 50% + 50% 30/60/90 / E-mail para nota fiscal: , E-mail de cobrança: , Telefone para contato") -> EXPRESSO SAO MIGUEL S/A / (049) 3361-6627Informação Adicional: VALOR DE CADA MAQUINA 4845,00 ENTRADA DE 50% + 50% 30/60/90 / E-mail para nota fiscal: , E-mail de cobrança: , Telefone para contato
A19: =IFERROR(__xludf.DUMMYFUNCTION("""COMPUTED_VALUE"""),"18699") -> 18699 | B19: =IFERROR(__xludf.DUMMYFUNCTION("""COMPUTED_VALUE"""),"ROYAL BLUE COMERCIO DE PISCINAS") -> ROYAL BLUE COMERCIO DE PISCINAS | C19: =IFERROR(__xludf.DUMMYFUNCTION("""COMPUTED_VALUE"""),1.0) -> 1 | E19: =IFERROR(__xludf.DUMMYFUNCTION("""COMPUTED_VALUE"""),"FTI25D40PT") -> FTI25D40PT | F19: =IFERROR(__xludf.DUMMYFUNCTION("""COMPUTED_VALUE"""),"WI-FI") -> WI-FI | G19: =IFERROR(__xludf.DUMMYFUNCTION("""COMPUTED_VALUE"""),"NAO") -> NAO | H19: =IFERROR(__xludf.DUMMYFUNCTION("""COMPUTED_VALUE"""),"NAO") -> NAO | I19: =IFERROR(__xludf.DUMMYFUNCTION("""COMPUTED_VALUE"""),"AGUARDAR CONTAINER") -> AGUARDAR CONTAINER | J19: =IFERROR(__xludf.DUMMYFUNCTION("""COMPUTED_VALUE"""),"EXPRESSO SAO MIGUEL") -> EXPRESSO SAO MIGUEL | K19: =IFERROR(__xludf.DUMMYFUNCTION("""COMPUTED_VALUE"""),"SEM REDESPACHO") -> SEM REDESPACHO | P19: =IFERROR(__xludf.DUMMYFUNCTION("""COMPUTED_VALUE"""),"EXPRESSO SAO MIGUEL S/A / (049) 3361-6627Informação Adicional: valor da maquina R$ 4845,42 / E-mail para nota fiscal: , E-mail de cobrança: , Telefone para contato") -> EXPRESSO SAO MIGUEL S/A / (049) 3361-6627Informação Adicional: valor da maquina R$ 4845,42 / E-mail para nota fiscal: , E-mail de cobrança: , Telefone para contato
A20: =IFERROR(__xludf.DUMMYFUNCTION("""COMPUTED_VALUE"""),"18774") -> 18774 | B20: =IFERROR(__xludf.DUMMYFUNCTION("""COMPUTED_VALUE"""),"CESAR HASS") -> CESAR HASS | C20: =IFERROR(__xludf.DUMMYFUNCTION("""COMPUTED_VALUE"""),1.0) -> 1 | E20: =IFERROR(__xludf.DUMMYFUNCTION("""COMPUTED_VALUE"""),"FTI25D40PT") -> FTI25D40PT | F20: =IFERROR(__xludf.DUMMYFUNCTION("""COMPUTED_VALUE"""),"WI-FI") -> WI-FI | G20: =IFERROR(__xludf.DUMMYFUNCTION("""COMPUTED_VALUE"""),"NAO") -> NAO | H20: =IFERROR(__xludf.DUMMYFUNCTION("""COMPUTED_VALUE"""),"NAO") -> NAO | I20: =IFERROR(__xludf.DUMMYFUNCTION("""COMPUTED_VALUE"""),"AGUARDAR CONTAINER") -> AGUARDAR CONTAINER | J20: =IFERROR(__xludf.DUMMYFUNCTION("""COMPUTED_VALUE"""),"TRANSP BAUER EXPRESS") -> TRANSP BAUER EXPRESS | K20: =IFERROR(__xludf.DUMMYFUNCTION("""COMPUTED_VALUE"""),"SEM REDESPACHO") -> SEM REDESPACHO | P20: =IFERROR(__xludf.DUMMYFUNCTION("""COMPUTED_VALUE"""),"NOVEMBRO Transportadora Bauer / (048) 9943-3665Informação Adicional: ENTREGA EM NOVEMBRO . / E-mail para nota fiscal: , E-mail de cobrança: , Telefone para contato") -> NOVEMBRO Transportadora Bauer / (048) 9943-3665Informação Adicional: ENTREGA EM NOVEMBRO . / E-mail para nota fiscal: , E-mail de cobrança: , Telefone para contato
A21: =IFERROR(__xludf.DUMMYFUNCTION("""COMPUTED_VALUE"""),"18808-A") -> 18808-A | B21: =IFERROR(__xludf.DUMMYFUNCTION("""COMPUTED_VALUE""")," ECO SOLAR E PISCINA") -> ECO SOLAR E PISCINA | C21: =IFERROR(__xludf.DUMMYFUNCTION("""COMPUTED_VALUE"""),1.0) -> 1 | E21: =IFERROR(__xludf.DUMMYFUNCTION("""COMPUTED_VALUE"""),"FTI25D40PT") -> FTI25D40PT | F21: =IFERROR(__xludf.DUMMYFUNCTION("""COMPUTED_VALUE"""),"WI-FI") -> WI-FI | G21: =IFERROR(__xludf.DUMMYFUNCTION("""COMPUTED_VALUE"""),"NAO") -> NAO | H21: =IFERROR(__xludf.DUMMYFUNCTION("""COMPUTED_VALUE"""),"NAO") -> NAO | I21: =IFERROR(__xludf.DUMMYFUNCTION("""COMPUTED_VALUE"""),"AGUARDAR CONTAINER") -> AGUARDAR CONTAINER | J21: =IFERROR(__xludf.DUMMYFUNCTION("""COMPUTED_VALUE"""),"FITLOG") -> FITLOG | K21: =IFERROR(__xludf.DUMMYFUNCTION("""COMPUTED_VALUE"""),"INOVAR TRANSPORTES") -> INOVAR TRANSPORTES | P21: =IFERROR(__xludf.DUMMYFUNCTION("""COMPUTED_VALUE"""),"FITLOG TRANSPORTES E LOGISTICA LTDA / (048) 996277956Informação Adicional: REDESPACHO: INOVAR TRANSPORTES E LOGISTICA LTDA-CNPJ: 04.989.756/0007-51 -Rua Carlópolis , 181, Parque São Luiz, Guarulhos- SP CEP 07170-540 - (11) 2467 5631 / Obs.Interna: entre"&"ga para inicio de novembro / E-mail para nota fiscal: , E-mail de cobrança: , Telefone para contato") -> FITLOG TRANSPORTES E LOGISTICA LTDA / (048) 996277956Informação Adicional: REDESPACHO: INOVAR TRANSPORTES E LOGISTICA LTDA-CNPJ: 04.989.756/0007-51 -Rua Carlópolis , 181, Parque São Luiz, Guarulhos- SP CEP 07170-540 - (11) 2467 5631 / Obs.Interna: entrega para inicio de novembro / E-mail para nota fiscal: , E-mail de cobrança: , Telefone para contato
A22: =IFERROR(__xludf.DUMMYFUNCTION("""COMPUTED_VALUE"""),"18808-B") -> 18808-B | B22: =IFERROR(__xludf.DUMMYFUNCTION("""COMPUTED_VALUE""")," ECO SOLAR E PISCINA") -> ECO SOLAR E PISCINA | C22: =IFERROR(__xludf.DUMMYFUNCTION("""COMPUTED_VALUE"""),1.0) -> 1 | E22: =IFERROR(__xludf.DUMMYFUNCTION("""COMPUTED_VALUE"""),"FTI25D40PT") -> FTI25D40PT | F22: =IFERROR(__xludf.DUMMYFUNCTION("""COMPUTED_VALUE"""),"WI-FI") -> WI-FI | G22: =IFERROR(__xludf.DUMMYFUNCTION("""COMPUTED_VALUE"""),"NAO") -> NAO | H22: =IFERROR(__xludf.DUMMYFUNCTION("""COMPUTED_VALUE"""),"NAO") -> NAO | I22: =IFERROR(__xludf.DUMMYFUNCTION("""COMPUTED_VALUE"""),"AGUARDAR CONTAINER") -> AGUARDAR CONTAINER | J22: =IFERROR(__xludf.DUMMYFUNCTION("""COMPUTED_VALUE"""),"FITLOG") -> FITLOG | K22: =IFERROR(__xludf.DUMMYFUNCTION("""COMPUTED_VALUE"""),"INOVAR TRANSPORTES") -> INOVAR TRANSPORTES | P22: =IFERROR(__xludf.DUMMYFUNCTION("""COMPUTED_VALUE"""),"FITLOG TRANSPORTES E LOGISTICA LTDA / (048) 996277956Informação Adicional: REDESPACHO: INOVAR TRANSPORTES E LOGISTICA LTDA-CNPJ: 04.989.756/0007-51 -Rua Carlópolis , 181, Parque São Luiz, Guarulhos- SP CEP 07170-540 - (11) 2467 5631 / Obs.Interna: entre"&"ga para inicio de novembro / E-mail para nota fiscal: , E-mail de cobrança: , Telefone para contato") -> FITLOG TRANSPORTES E LOGISTICA LTDA / (048) 996277956Informação Adicional: REDESPACHO: INOVAR TRANSPORTES E LOGISTICA LTDA-CNPJ: 04.989.756/0007-51 -Rua Carlópolis , 181, Parque São Luiz, Guarulhos- SP CEP 07170-540 - (11) 2467 5631 / Obs.Interna: entrega para inicio de novembro / E-mail para nota fiscal: , E-mail de cobrança: , Telefone para contato
A23: =IFERROR(__xludf.DUMMYFUNCTION("""COMPUTED_VALUE"""),"18808-C") -> 18808-C | B23: =IFERROR(__xludf.DUMMYFUNCTION("""COMPUTED_VALUE""")," ECO SOLAR E PISCINA") -> ECO SOLAR E PISCINA | C23: =IFERROR(__xludf.DUMMYFUNCTION("""COMPUTED_VALUE"""),1.0) -> 1 | E23: =IFERROR(__xludf.DUMMYFUNCTION("""COMPUTED_VALUE"""),"FTI25D40PT") -> FTI25D40PT | F23: =IFERROR(__xludf.DUMMYFUNCTION("""COMPUTED_VALUE"""),"WI-FI") -> WI-FI | G23: =IFERROR(__xludf.DUMMYFUNCTION("""COMPUTED_VALUE"""),"NAO") -> NAO | H23: =IFERROR(__xludf.DUMMYFUNCTION("""COMPUTED_VALUE"""),"NAO") -> NAO | I23: =IFERROR(__xludf.DUMMYFUNCTION("""COMPUTED_VALUE"""),"AGUARDAR CONTAINER") -> AGUARDAR CONTAINER | J23: =IFERROR(__xludf.DUMMYFUNCTION("""COMPUTED_VALUE"""),"FITLOG") -> FITLOG | K23: =IFERROR(__xludf.DUMMYFUNCTION("""COMPUTED_VALUE"""),"INOVAR TRANSPORTES") -> INOVAR TRANSPORTES | P23: =IFERROR(__xludf.DUMMYFUNCTION("""COMPUTED_VALUE"""),"FITLOG TRANSPORTES E LOGISTICA LTDA / (048) 996277956Informação Adicional: REDESPACHO: INOVAR TRANSPORTES E LOGISTICA LTDA-CNPJ: 04.989.756/0007-51 -Rua Carlópolis , 181, Parque São Luiz, Guarulhos- SP CEP 07170-540 - (11) 2467 5631 / Obs.Interna: entre"&"ga para inicio de novembro / E-mail para nota fiscal: , E-mail de cobrança: , Telefone para contato") -> FITLOG TRANSPORTES E LOGISTICA LTDA / (048) 996277956Informação Adicional: REDESPACHO: INOVAR TRANSPORTES E LOGISTICA LTDA-CNPJ: 04.989.756/0007-51 -Rua Carlópolis , 181, Parque São Luiz, Guarulhos- SP CEP 07170-540 - (11) 2467 5631 / Obs.Interna: entrega para inicio de novembro / E-mail para nota fiscal: , E-mail de cobrança: , Telefone para contato
A24: =IFERROR(__xludf.DUMMYFUNCTION("""COMPUTED_VALUE"""),"18814-A") -> 18814-A | B24: =IFERROR(__xludf.DUMMYFUNCTION("""COMPUTED_VALUE"""),"W E COMERCIO DE PISCINAS LTDA") -> W E COMERCIO DE PISCINAS LTDA | C24: =IFERROR(__xludf.DUMMYFUNCTION("""COMPUTED_VALUE"""),1.0) -> 1 | E24: =IFERROR(__xludf.DUMMYFUNCTION("""COMPUTED_VALUE"""),"FTI25D40PT") -> FTI25D40PT | F24: =IFERROR(__xludf.DUMMYFUNCTION("""COMPUTED_VALUE"""),"WI-FI") -> WI-FI | G24: =IFERROR(__xludf.DUMMYFUNCTION("""COMPUTED_VALUE"""),"NAO") -> NAO | H24: =IFERROR(__xludf.DUMMYFUNCTION("""COMPUTED_VALUE"""),"NAO") -> NAO | I24: =IFERROR(__xludf.DUMMYFUNCTION("""COMPUTED_VALUE"""),"AGUARDAR CONTAINER") -> AGUARDAR CONTAINER | J24: =IFERROR(__xludf.DUMMYFUNCTION("""COMPUTED_VALUE"""),"RETIRA") -> RETIRA | K24: =IFERROR(__xludf.DUMMYFUNCTION("""COMPUTED_VALUE"""),"SEM REDESPACHO") -> SEM REDESPACHO | P24: =IFERROR(__xludf.DUMMYFUNCTION("""COMPUTED_VALUE"""),"CLIENTE RETIRA / (0) Obs.Interna: valor da maquina R$ 4.845,42 CLIENTE RETIRA - Entrega em DEZEMBRO PAGAMENTO EM 16/10/25 . / E-mail para nota fiscal: , E-mail de cobrança: , Telefone para contato") -> CLIENTE RETIRA / (0) Obs.Interna: valor da maquina R$ 4.845,42 CLIENTE RETIRA - Entrega em DEZEMBRO PAGAMENTO EM 16/10/25 . / E-mail para nota fiscal: , E-mail de cobrança: , Telefone para contato
A25: =IFERROR(__xludf.DUMMYFUNCTION("""COMPUTED_VALUE"""),"18814-A1") -> 18814-A1 | B25: =IFERROR(__xludf.DUMMYFUNCTION("""COMPUTED_VALUE"""),"W E COMERCIO DE PISCINAS LTDA") -> W E COMERCIO DE PISCINAS LTDA | C25: =IFERROR(__xludf.DUMMYFUNCTION("""COMPUTED_VALUE"""),1.0) -> 1 | E25: =IFERROR(__xludf.DUMMYFUNCTION("""COMPUTED_VALUE"""),"FTI25D40PT") -> FTI25D40PT | F25: =IFERROR(__xludf.DUMMYFUNCTION("""COMPUTED_VALUE"""),"WI-FI") -> WI-FI | G25: =IFERROR(__xludf.DUMMYFUNCTION("""COMPUTED_VALUE"""),"NAO") -> NAO | H25: =IFERROR(__xludf.DUMMYFUNCTION("""COMPUTED_VALUE"""),"NAO") -> NAO | I25: =IFERROR(__xludf.DUMMYFUNCTION("""COMPUTED_VALUE"""),"AGUARDAR CONTAINER") -> AGUARDAR CONTAINER | J25: =IFERROR(__xludf.DUMMYFUNCTION("""COMPUTED_VALUE"""),"RETIRA") -> RETIRA | K25: =IFERROR(__xludf.DUMMYFUNCTION("""COMPUTED_VALUE"""),"SEM REDESPACHO") -> SEM REDESPACHO | P25: =IFERROR(__xludf.DUMMYFUNCTION("""COMPUTED_VALUE"""),"CLIENTE RETIRA / (0) Obs.Interna: valor da maquina R$ 4.845,42 CLIENTE RETIRA - Entrega em DEZEMBRO PAGAMENTO EM 16/10/25 . / E-mail para nota fiscal: , E-mail de cobrança: , Telefone para contato") -> CLIENTE RETIRA / (0) Obs.Interna: valor da maquina R$ 4.845,42 CLIENTE RETIRA - Entrega em DEZEMBRO PAGAMENTO EM 16/10/25 . / E-mail para nota fiscal: , E-mail de cobrança: , Telefone para contato
A26: =IFERROR(__xludf.DUMMYFUNCTION("""COMPUTED_VALUE"""),"18814-A10") -> 18814-A10 | B26: =IFERROR(__xludf.DUMMYFUNCTION("""COMPUTED_VALUE"""),"W E COMERCIO DE PISCINAS LTDA") -> W E COMERCIO DE PISCINAS LTDA | C26: =IFERROR(__xludf.DUMMYFUNCTION("""COMPUTED_VALUE"""),1.0) -> 1 | E26: =IFERROR(__xludf.DUMMYFUNCTION("""COMPUTED_VALUE"""),"FTI25D40PT") -> FTI25D40PT | F26: =IFERROR(__xludf.DUMMYFUNCTION("""COMPUTED_VALUE"""),"WI-FI") -> WI-FI | G26: =IFERROR(__xludf.DUMMYFUNCTION("""COMPUTED_VALUE"""),"NAO") -> NAO | H26: =IFERROR(__xludf.DUMMYFUNCTION("""COMPUTED_VALUE"""),"NAO") -> NAO | I26: =IFERROR(__xludf.DUMMYFUNCTION("""COMPUTED_VALUE"""),"AGUARDAR CONTAINER") -> AGUARDAR CONTAINER | J26: =IFERROR(__xludf.DUMMYFUNCTION("""COMPUTED_VALUE"""),"RETIRA") -> RETIRA | K26: =IFERROR(__xludf.DUMMYFUNCTION("""COMPUTED_VALUE"""),"SEM REDESPACHO") -> SEM REDESPACHO | P26: =IFERROR(__xludf.DUMMYFUNCTION("""COMPUTED_VALUE"""),"CLIENTE RETIRA / (0) Obs.Interna: valor da maquina R$ 4.845,42 CLIENTE RETIRA - Entrega em DEZEMBRO PAGAMENTO EM 16/10/25 . / E-mail para nota fiscal: , E-mail de cobrança: , Telefone para contato") -> CLIENTE RETIRA / (0) Obs.Interna: valor da maquina R$ 4.845,42 CLIENTE RETIRA - Entrega em DEZEMBRO PAGAMENTO EM 16/10/25 . / E-mail para nota fiscal: , E-mail de cobrança: , Telefone para contato
A27: =IFERROR(__xludf.DUMMYFUNCTION("""COMPUTED_VALUE"""),"18814-A11") -> 18814-A11 | B27: =IFERROR(__xludf.DUMMYFUNCTION("""COMPUTED_VALUE"""),"W E COMERCIO DE PISCINAS LTDA") -> W E COMERCIO DE PISCINAS LTDA | C27: =IFERROR(__xludf.DUMMYFUNCTION("""COMPUTED_VALUE"""),1.0) -> 1 | E27: =IFERROR(__xludf.DUMMYFUNCTION("""COMPUTED_VALUE"""),"FTI25D40PT") -> FTI25D40PT | F27: =IFERROR(__xludf.DUMMYFUNCTION("""COMPUTED_VALUE"""),"WI-FI") -> WI-FI | G27: =IFERROR(__xludf.DUMMYFUNCTION("""COMPUTED_VALUE"""),"NAO") -> NAO | H27: =IFERROR(__xludf.DUMMYFUNCTION("""COMPUTED_VALUE"""),"NAO") -> NAO | I27: =IFERROR(__xludf.DUMMYFUNCTION("""COMPUTED_VALUE"""),"AGUARDAR CONTAINER") -> AGUARDAR CONTAINER | J27: =IFERROR(__xludf.DUMMYFUNCTION("""COMPUTED_VALUE"""),"RETIRA") -> RETIRA | K27: =IFERROR(__xludf.DUMMYFUNCTION("""COMPUTED_VALUE"""),"SEM REDESPACHO") -> SEM REDESPACHO | P27: =IFERROR(__xludf.DUMMYFUNCTION("""COMPUTED_VALUE"""),"CLIENTE RETIRA / (0) Obs.Interna: valor da maquina R$ 4.845,42 CLIENTE RETIRA - Entrega em DEZEMBRO PAGAMENTO EM 16/10/25 . / E-mail para nota fiscal: , E-mail de cobrança: , Telefone para contato") -> CLIENTE RETIRA / (0) Obs.Interna: valor da maquina R$ 4.845,42 CLIENTE RETIRA - Entrega em DEZEMBRO PAGAMENTO EM 16/10/25 . / E-mail para nota fiscal: , E-mail de cobrança: , Telefone para contato
A28: =IFERROR(__xludf.DUMMYFUNCTION("""COMPUTED_VALUE"""),"18814-A12") -> 18814-A12 | B28: =IFERROR(__xludf.DUMMYFUNCTION("""COMPUTED_VALUE"""),"W E COMERCIO DE PISCINAS LTDA") -> W E COMERCIO DE PISCINAS LTDA | C28: =IFERROR(__xludf.DUMMYFUNCTION("""COMPUTED_VALUE"""),1.0) -> 1 | E28: =IFERROR(__xludf.DUMMYFUNCTION("""COMPUTED_VALUE"""),"FTI25D40PT") -> FTI25D40PT | F28: =IFERROR(__xludf.DUMMYFUNCTION("""COMPUTED_VALUE"""),"WI-FI") -> WI-FI | G28: =IFERROR(__xludf.DUMMYFUNCTION("""COMPUTED_VALUE"""),"NAO") -> NAO | H28: =IFERROR(__xludf.DUMMYFUNCTION("""COMPUTED_VALUE"""),"NAO") -> NAO | I28: =IFERROR(__xludf.DUMMYFUNCTION("""COMPUTED_VALUE"""),"AGUARDAR CONTAINER") -> AGUARDAR CONTAINER | J28: =IFERROR(__xludf.DUMMYFUNCTION("""COMPUTED_VALUE"""),"RETIRA") -> RETIRA | K28: =IFERROR(__xludf.DUMMYFUNCTION("""COMPUTED_VALUE"""),"SEM REDESPACHO") -> SEM REDESPACHO | P28: =IFERROR(__xludf.DUMMYFUNCTION("""COMPUTED_VALUE"""),"CLIENTE RETIRA / (0) Obs.Interna: valor da maquina R$ 4.845,42 CLIENTE RETIRA - Entrega em DEZEMBRO PAGAMENTO EM 16/10/25 . / E-mail para nota fiscal: , E-mail de cobrança: , Telefone para contato") -> CLIENTE RETIRA / (0) Obs.Interna: valor da maquina R$ 4.845,42 CLIENTE RETIRA - Entrega em DEZEMBRO PAGAMENTO EM 16/10/25 . / E-mail para nota fiscal: , E-mail de cobrança: , Telefone para contato
A29: =IFERROR(__xludf.DUMMYFUNCTION("""COMPUTED_VALUE"""),"18814-A13") -> 18814-A13 | B29: =IFERROR(__xludf.DUMMYFUNCTION("""COMPUTED_VALUE"""),"W E COMERCIO DE PISCINAS LTDA") -> W E COMERCIO DE PISCINAS LTDA | C29: =IFERROR(__xludf.DUMMYFUNCTION("""COMPUTED_VALUE"""),1.0) -> 1 | E29: =IFERROR(__xludf.DUMMYFUNCTION("""COMPUTED_VALUE"""),"FTI25D40PT") -> FTI25D40PT | F29: =IFERROR(__xludf.DUMMYFUNCTION("""COMPUTED_VALUE"""),"WI-FI") -> WI-FI | G29: =IFERROR(__xludf.DUMMYFUNCTION("""COMPUTED_VALUE"""),"NAO") -> NAO | H29: =IFERROR(__xludf.DUMMYFUNCTION("""COMPUTED_VALUE"""),"NAO") -> NAO | I29: =IFERROR(__xludf.DUMMYFUNCTION("""COMPUTED_VALUE"""),"AGUARDAR CONTAINER") -> AGUARDAR CONTAINER | J29: =IFERROR(__xludf.DUMMYFUNCTION("""COMPUTED_VALUE"""),"RETIRA") -> RETIRA | K29: =IFERROR(__xludf.DUMMYFUNCTION("""COMPUTED_VALUE"""),"SEM REDESPACHO") -> SEM REDESPACHO | P29: =IFERROR(__xludf.DUMMYFUNCTION("""COMPUTED_VALUE"""),"CLIENTE RETIRA / (0) Obs.Interna: valor da maquina R$ 4.845,42 CLIENTE RETIRA - Entrega em DEZEMBRO PAGAMENTO EM 16/10/25 . / E-mail para nota fiscal: , E-mail de cobrança: , Telefone para contato") -> CLIENTE RETIRA / (0) Obs.Interna: valor da maquina R$ 4.845,42 CLIENTE RETIRA - Entrega em DEZEMBRO PAGAMENTO EM 16/10/25 . / E-mail para nota fiscal: , E-mail de cobrança: , Telefone para contato
A30: =IFERROR(__xludf.DUMMYFUNCTION("""COMPUTED_VALUE"""),"18814-A14") -> 18814-A14 | B30: =IFERROR(__xludf.DUMMYFUNCTION("""COMPUTED_VALUE"""),"W E COMERCIO DE PISCINAS LTDA") -> W E COMERCIO DE PISCINAS LTDA | C30: =IFERROR(__xludf.DUMMYFUNCTION("""COMPUTED_VALUE"""),1.0) -> 1 | E30: =IFERROR(__xludf.DUMMYFUNCTION("""COMPUTED_VALUE"""),"FTI25D40PT") -> FTI25D40PT | F30: =IFERROR(__xludf.DUMMYFUNCTION("""COMPUTED_VALUE"""),"WI-FI") -> WI-FI | G30: =IFERROR(__xludf.DUMMYFUNCTION("""COMPUTED_VALUE"""),"NAO") -> NAO | H30: =IFERROR(__xludf.DUMMYFUNCTION("""COMPUTED_VALUE"""),"NAO") -> NAO | I30: =IFERROR(__xludf.DUMMYFUNCTION("""COMPUTED_VALUE"""),"AGUARDAR CONTAINER") -> AGUARDAR CONTAINER | J30: =IFERROR(__xludf.DUMMYFUNCTION("""COMPUTED_VALUE"""),"RETIRA") -> RETIRA | K30: =IFERROR(__xludf.DUMMYFUNCTION("""COMPUTED_VALUE"""),"SEM REDESPACHO") -> SEM REDESPACHO | P30: =IFERROR(__xludf.DUMMYFUNCTION("""COMPUTED_VALUE"""),"CLIENTE RETIRA / (0) Obs.Interna: valor da maquina R$ 4.845,42 CLIENTE RETIRA - Entrega em DEZEMBRO PAGAMENTO EM 16/10/25 . / E-mail para nota fiscal: , E-mail de cobrança: , Telefone para contato") -> CLIENTE RETIRA / (0) Obs.Interna: valor da maquina R$ 4.845,42 CLIENTE RETIRA - Entrega em DEZEMBRO PAGAMENTO EM 16/10/25 . / E-mail para nota fiscal: , E-mail de cobrança: , Telefone para contato
A31: =IFERROR(__xludf.DUMMYFUNCTION("""COMPUTED_VALUE"""),"18814-A15") -> 18814-A15 | B31: =IFERROR(__xludf.DUMMYFUNCTION("""COMPUTED_VALUE"""),"W E COMERCIO DE PISCINAS LTDA") -> W E COMERCIO DE PISCINAS LTDA | C31: =IFERROR(__xludf.DUMMYFUNCTION("""COMPUTED_VALUE"""),1.0) -> 1 | E31: =IFERROR(__xludf.DUMMYFUNCTION("""COMPUTED_VALUE"""),"FTI25D40PT") -> FTI25D40PT | F31: =IFERROR(__xludf.DUMMYFUNCTION("""COMPUTED_VALUE"""),"WI-FI") -> WI-FI | G31: =IFERROR(__xludf.DUMMYFUNCTION("""COMPUTED_VALUE"""),"NAO") -> NAO | H31: =IFERROR(__xludf.DUMMYFUNCTION("""COMPUTED_VALUE"""),"NAO") -> NAO | I31: =IFERROR(__xludf.DUMMYFUNCTION("""COMPUTED_VALUE"""),"AGUARDAR CONTAINER") -> AGUARDAR CONTAINER | J31: =IFERROR(__xludf.DUMMYFUNCTION("""COMPUTED_VALUE"""),"RETIRA") -> RETIRA | K31: =IFERROR(__xludf.DUMMYFUNCTION("""COMPUTED_VALUE"""),"SEM REDESPACHO") -> SEM REDESPACHO | P31: =IFERROR(__xludf.DUMMYFUNCTION("""COMPUTED_VALUE"""),"CLIENTE RETIRA / (0) Obs.Interna: valor da maquina R$ 4.845,42 CLIENTE RETIRA - Entrega em DEZEMBRO PAGAMENTO EM 16/10/25 . / E-mail para nota fiscal: , E-mail de cobrança: , Telefone para contato") -> CLIENTE RETIRA / (0) Obs.Interna: valor da maquina R$ 4.845,42 CLIENTE RETIRA - Entrega em DEZEMBRO PAGAMENTO EM 16/10/25 . / E-mail para nota fiscal: , E-mail de cobrança: , Telefone para contato
A32: =IFERROR(__xludf.DUMMYFUNCTION("""COMPUTED_VALUE"""),"18814-A16") -> 18814-A16 | B32: =IFERROR(__xludf.DUMMYFUNCTION("""COMPUTED_VALUE"""),"W E COMERCIO DE PISCINAS LTDA") -> W E COMERCIO DE PISCINAS LTDA | C32: =IFERROR(__xludf.DUMMYFUNCTION("""COMPUTED_VALUE"""),1.0) -> 1 | E32: =IFERROR(__xludf.DUMMYFUNCTION("""COMPUTED_VALUE"""),"FTI25D40PT") -> FTI25D40PT | F32: =IFERROR(__xludf.DUMMYFUNCTION("""COMPUTED_VALUE"""),"WI-FI") -> WI-FI | G32: =IFERROR(__xludf.DUMMYFUNCTION("""COMPUTED_VALUE"""),"NAO") -> NAO | H32: =IFERROR(__xludf.DUMMYFUNCTION("""COMPUTED_VALUE"""),"NAO") -> NAO | I32: =IFERROR(__xludf.DUMMYFUNCTION("""COMPUTED_VALUE"""),"AGUARDAR CONTAINER") -> AGUARDAR CONTAINER | J32: =IFERROR(__xludf.DUMMYFUNCTION("""COMPUTED_VALUE"""),"RETIRA") -> RETIRA | K32: =IFERROR(__xludf.DUMMYFUNCTION("""COMPUTED_VALUE"""),"SEM REDESPACHO") -> SEM REDESPACHO | P32: =IFERROR(__xludf.DUMMYFUNCTION("""COMPUTED_VALUE"""),"CLIENTE RETIRA / (0) Obs.Interna: valor da maquina R$ 4.845,42 CLIENTE RETIRA - Entrega em DEZEMBRO PAGAMENTO EM 16/10/25 . / E-mail para nota fiscal: , E-mail de cobrança: , Telefone para contato") -> CLIENTE RETIRA / (0) Obs.Interna: valor da maquina R$ 4.845,42 CLIENTE RETIRA - Entrega em DEZEMBRO PAGAMENTO EM 16/10/25 . / E-mail para nota fiscal: , E-mail de cobrança: , Telefone para contato
A33: =IFERROR(__xludf.DUMMYFUNCTION("""COMPUTED_VALUE"""),"18814-A2") -> 18814-A2 | B33: =IFERROR(__xludf.DUMMYFUNCTION("""COMPUTED_VALUE"""),"W E COMERCIO DE PISCINAS LTDA") -> W E COMERCIO DE PISCINAS LTDA | C33: =IFERROR(__xludf.DUMMYFUNCTION("""COMPUTED_VALUE"""),1.0) -> 1 | E33: =IFERROR(__xludf.DUMMYFUNCTION("""COMPUTED_VALUE"""),"FTI25D40PT") -> FTI25D40PT | F33: =IFERROR(__xludf.DUMMYFUNCTION("""COMPUTED_VALUE"""),"WI-FI") -> WI-FI | G33: =IFERROR(__xludf.DUMMYFUNCTION("""COMPUTED_VALUE"""),"NAO") -> NAO | H33: =IFERROR(__xludf.DUMMYFUNCTION("""COMPUTED_VALUE"""),"NAO") -> NAO | I33: =IFERROR(__xludf.DUMMYFUNCTION("""COMPUTED_VALUE"""),"AGUARDAR CONTAINER") -> AGUARDAR CONTAINER | J33: =IFERROR(__xludf.DUMMYFUNCTION("""COMPUTED_VALUE"""),"RETIRA") -> RETIRA | K33: =IFERROR(__xludf.DUMMYFUNCTION("""COMPUTED_VALUE"""),"SEM REDESPACHO") -> SEM REDESPACHO | P33: =IFERROR(__xludf.DUMMYFUNCTION("""COMPUTED_VALUE"""),"CLIENTE RETIRA / (0) Obs.Interna: valor da maquina R$ 4.845,42 CLIENTE RETIRA - Entrega em DEZEMBRO PAGAMENTO EM 16/10/25 . / E-mail para nota fiscal: , E-mail de cobrança: , Telefone para contato") -> CLIENTE RETIRA / (0) Obs.Interna: valor da maquina R$ 4.845,42 CLIENTE RETIRA - Entrega em DEZEMBRO PAGAMENTO EM 16/10/25 . / E-mail para nota fiscal: , E-mail de cobrança: , Telefone para contato
A34: =IFERROR(__xludf.DUMMYFUNCTION("""COMPUTED_VALUE"""),"18814-A3") -> 18814-A3 | B34: =IFERROR(__xludf.DUMMYFUNCTION("""COMPUTED_VALUE"""),"W E COMERCIO DE PISCINAS LTDA") -> W E COMERCIO DE PISCINAS LTDA | C34: =IFERROR(__xludf.DUMMYFUNCTION("""COMPUTED_VALUE"""),1.0) -> 1 | E34: =IFERROR(__xludf.DUMMYFUNCTION("""COMPUTED_VALUE"""),"FTI25D40PT") -> FTI25D40PT | F34: =IFERROR(__xludf.DUMMYFUNCTION("""COMPUTED_VALUE"""),"WI-FI") -> WI-FI | G34: =IFERROR(__xludf.DUMMYFUNCTION("""COMPUTED_VALUE"""),"NAO") -> NAO | H34: =IFERROR(__xludf.DUMMYFUNCTION("""COMPUTED_VALUE"""),"NAO") -> NAO | I34: =IFERROR(__xludf.DUMMYFUNCTION("""COMPUTED_VALUE"""),"AGUARDAR CONTAINER") -> AGUARDAR CONTAINER | J34: =IFERROR(__xludf.DUMMYFUNCTION("""COMPUTED_VALUE"""),"RETIRA") -> RETIRA | K34: =IFERROR(__xludf.DUMMYFUNCTION("""COMPUTED_VALUE"""),"SEM REDESPACHO") -> SEM REDESPACHO | P34: =IFERROR(__xludf.DUMMYFUNCTION("""COMPUTED_VALUE"""),"CLIENTE RETIRA / (0) Obs.Interna: valor da maquina R$ 4.845,42 CLIENTE RETIRA - Entrega em DEZEMBRO PAGAMENTO EM 16/10/25 . / E-mail para nota fiscal: , E-mail de cobrança: , Telefone para contato") -> CLIENTE RETIRA / (0) Obs.Interna: valor da maquina R$ 4.845,42 CLIENTE RETIRA - Entrega em DEZEMBRO PAGAMENTO EM 16/10/25 . / E-mail para nota fiscal: , E-mail de cobrança: , Telefone para contato
A35: =IFERROR(__xludf.DUMMYFUNCTION("""COMPUTED_VALUE"""),"18814-A4") -> 18814-A4 | B35: =IFERROR(__xludf.DUMMYFUNCTION("""COMPUTED_VALUE"""),"W E COMERCIO DE PISCINAS LTDA") -> W E COMERCIO DE PISCINAS LTDA | C35: =IFERROR(__xludf.DUMMYFUNCTION("""COMPUTED_VALUE"""),1.0) -> 1 | E35: =IFERROR(__xludf.DUMMYFUNCTION("""COMPUTED_VALUE"""),"FTI25D40PT") -> FTI25D40PT | F35: =IFERROR(__xludf.DUMMYFUNCTION("""COMPUTED_VALUE"""),"WI-FI") -> WI-FI | G35: =IFERROR(__xludf.DUMMYFUNCTION("""COMPUTED_VALUE"""),"NAO") -> NAO | H35: =IFERROR(__xludf.DUMMYFUNCTION("""COMPUTED_VALUE"""),"NAO") -> NAO | I35: =IFERROR(__xludf.DUMMYFUNCTION("""COMPUTED_VALUE"""),"AGUARDAR CONTAINER") -> AGUARDAR CONTAINER | J35: =IFERROR(__xludf.DUMMYFUNCTION("""COMPUTED_VALUE"""),"RETIRA") -> RETIRA | K35: =IFERROR(__xludf.DUMMYFUNCTION("""COMPUTED_VALUE"""),"SEM REDESPACHO") -> SEM REDESPACHO | P35: =IFERROR(__xludf.DUMMYFUNCTION("""COMPUTED_VALUE"""),"CLIENTE RETIRA / (0) Obs.Interna: valor da maquina R$ 4.845,42 CLIENTE RETIRA - Entrega em DEZEMBRO PAGAMENTO EM 16/10/25 . / E-mail para nota fiscal: , E-mail de cobrança: , Telefone para contato") -> CLIENTE RETIRA / (0) Obs.Interna: valor da maquina R$ 4.845,42 CLIENTE RETIRA - Entrega em DEZEMBRO PAGAMENTO EM 16/10/25 . / E-mail para nota fiscal: , E-mail de cobrança: , Telefone para contato
A36: =IFERROR(__xludf.DUMMYFUNCTION("""COMPUTED_VALUE"""),"18814-A5") -> 18814-A5 | B36: =IFERROR(__xludf.DUMMYFUNCTION("""COMPUTED_VALUE"""),"W E COMERCIO DE PISCINAS LTDA") -> W E COMERCIO DE PISCINAS LTDA | C36: =IFERROR(__xludf.DUMMYFUNCTION("""COMPUTED_VALUE"""),1.0) -> 1 | E36: =IFERROR(__xludf.DUMMYFUNCTION("""COMPUTED_VALUE"""),"FTI25D40PT") -> FTI25D40PT | F36: =IFERROR(__xludf.DUMMYFUNCTION("""COMPUTED_VALUE"""),"WI-FI") -> WI-FI | G36: =IFERROR(__xludf.DUMMYFUNCTION("""COMPUTED_VALUE"""),"NAO") -> NAO | H36: =IFERROR(__xludf.DUMMYFUNCTION("""COMPUTED_VALUE"""),"NAO") -> NAO | I36: =IFERROR(__xludf.DUMMYFUNCTION("""COMPUTED_VALUE"""),"AGUARDAR CONTAINER") -> AGUARDAR CONTAINER | J36: =IFERROR(__xludf.DUMMYFUNCTION("""COMPUTED_VALUE"""),"RETIRA") -> RETIRA | K36: =IFERROR(__xludf.DUMMYFUNCTION("""COMPUTED_VALUE"""),"SEM REDESPACHO") -> SEM REDESPACHO | P36: =IFERROR(__xludf.DUMMYFUNCTION("""COMPUTED_VALUE"""),"CLIENTE RETIRA / (0) Obs.Interna: valor da maquina R$ 4.845,42 CLIENTE RETIRA - Entrega em DEZEMBRO PAGAMENTO EM 16/10/25 . / E-mail para nota fiscal: , E-mail de cobrança: , Telefone para contato") -> CLIENTE RETIRA / (0) Obs.Interna: valor da maquina R$ 4.845,42 CLIENTE RETIRA - Entrega em DEZEMBRO PAGAMENTO EM 16/10/25 . / E-mail para nota fiscal: , E-mail de cobrança: , Telefone para contato
A37: =IFERROR(__xludf.DUMMYFUNCTION("""COMPUTED_VALUE"""),"18814-A6") -> 18814-A6 | B37: =IFERROR(__xludf.DUMMYFUNCTION("""COMPUTED_VALUE"""),"W E COMERCIO DE PISCINAS LTDA") -> W E COMERCIO DE PISCINAS LTDA | C37: =IFERROR(__xludf.DUMMYFUNCTION("""COMPUTED_VALUE"""),1.0) -> 1 | E37: =IFERROR(__xludf.DUMMYFUNCTION("""COMPUTED_VALUE"""),"FTI25D40PT") -> FTI25D40PT | F37: =IFERROR(__xludf.DUMMYFUNCTION("""COMPUTED_VALUE"""),"WI-FI") -> WI-FI | G37: =IFERROR(__xludf.DUMMYFUNCTION("""COMPUTED_VALUE"""),"NAO") -> NAO | H37: =IFERROR(__xludf.DUMMYFUNCTION("""COMPUTED_VALUE"""),"NAO") -> NAO | I37: =IFERROR(__xludf.DUMMYFUNCTION("""COMPUTED_VALUE"""),"AGUARDAR CONTAINER") -> AGUARDAR CONTAINER | J37: =IFERROR(__xludf.DUMMYFUNCTION("""COMPUTED_VALUE"""),"RETIRA") -> RETIRA | K37: =IFERROR(__xludf.DUMMYFUNCTION("""COMPUTED_VALUE"""),"SEM REDESPACHO") -> SEM REDESPACHO | P37: =IFERROR(__xludf.DUMMYFUNCTION("""COMPUTED_VALUE"""),"CLIENTE RETIRA / (0) Obs.Interna: valor da maquina R$ 4.845,42 CLIENTE RETIRA - Entrega em DEZEMBRO PAGAMENTO EM 16/10/25 . / E-mail para nota fiscal: , E-mail de cobrança: , Telefone para contato") -> CLIENTE RETIRA / (0) Obs.Interna: valor da maquina R$ 4.845,42 CLIENTE RETIRA - Entrega em DEZEMBRO PAGAMENTO EM 16/10/25 . / E-mail para nota fiscal: , E-mail de cobrança: , Telefone para contato
A38: =IFERROR(__xludf.DUMMYFUNCTION("""COMPUTED_VALUE"""),"18814-A7") -> 18814-A7 | B38: =IFERROR(__xludf.DUMMYFUNCTION("""COMPUTED_VALUE"""),"W E COMERCIO DE PISCINAS LTDA") -> W E COMERCIO DE PISCINAS LTDA | C38: =IFERROR(__xludf.DUMMYFUNCTION("""COMPUTED_VALUE"""),1.0) -> 1 | E38: =IFERROR(__xludf.DUMMYFUNCTION("""COMPUTED_VALUE"""),"FTI25D40PT") -> FTI25D40PT | F38: =IFERROR(__xludf.DUMMYFUNCTION("""COMPUTED_VALUE"""),"WI-FI") -> WI-FI | G38: =IFERROR(__xludf.DUMMYFUNCTION("""COMPUTED_VALUE"""),"NAO") -> NAO | H38: =IFERROR(__xludf.DUMMYFUNCTION("""COMPUTED_VALUE"""),"NAO") -> NAO | I38: =IFERROR(__xludf.DUMMYFUNCTION("""COMPUTED_VALUE"""),"AGUARDAR CONTAINER") -> AGUARDAR CONTAINER | J38: =IFERROR(__xludf.DUMMYFUNCTION("""COMPUTED_VALUE"""),"RETIRA") -> RETIRA | K38: =IFERROR(__xludf.DUMMYFUNCTION("""COMPUTED_VALUE"""),"SEM REDESPACHO") -> SEM REDESPACHO | P38: =IFERROR(__xludf.DUMMYFUNCTION("""COMPUTED_VALUE"""),"CLIENTE RETIRA / (0) Obs.Interna: valor da maquina R$ 4.845,42 CLIENTE RETIRA - Entrega em DEZEMBRO PAGAMENTO EM 16/10/25 . / E-mail para nota fiscal: , E-mail de cobrança: , Telefone para contato") -> CLIENTE RETIRA / (0) Obs.Interna: valor da maquina R$ 4.845,42 CLIENTE RETIRA - Entrega em DEZEMBRO PAGAMENTO EM 16/10/25 . / E-mail para nota fiscal: , E-mail de cobrança: , Telefone para contato
A39: =IFERROR(__xludf.DUMMYFUNCTION("""COMPUTED_VALUE"""),"18814-A8") -> 18814-A8 | B39: =IFERROR(__xludf.DUMMYFUNCTION("""COMPUTED_VALUE"""),"W E COMERCIO DE PISCINAS LTDA") -> W E COMERCIO DE PISCINAS LTDA | C39: =IFERROR(__xludf.DUMMYFUNCTION("""COMPUTED_VALUE"""),1.0) -> 1 | E39: =IFERROR(__xludf.DUMMYFUNCTION("""COMPUTED_VALUE"""),"FTI25D40PT") -> FTI25D40PT | F39: =IFERROR(__xludf.DUMMYFUNCTION("""COMPUTED_VALUE"""),"WI-FI") -> WI-FI | G39: =IFERROR(__xludf.DUMMYFUNCTION("""COMPUTED_VALUE"""),"NAO") -> NAO | H39: =IFERROR(__xludf.DUMMYFUNCTION("""COMPUTED_VALUE"""),"NAO") -> NAO | I39: =IFERROR(__xludf.DUMMYFUNCTION("""COMPUTED_VALUE"""),"AGUARDAR CONTAINER") -> AGUARDAR CONTAINER | J39: =IFERROR(__xludf.DUMMYFUNCTION("""COMPUTED_VALUE"""),"RETIRA") -> RETIRA | K39: =IFERROR(__xludf.DUMMYFUNCTION("""COMPUTED_VALUE"""),"SEM REDESPACHO") -> SEM REDESPACHO | P39: =IFERROR(__xludf.DUMMYFUNCTION("""COMPUTED_VALUE"""),"CLIENTE RETIRA / (0) Obs.Interna: valor da maquina R$ 4.845,42 CLIENTE RETIRA - Entrega em DEZEMBRO PAGAMENTO EM 16/10/25 . / E-mail para nota fiscal: , E-mail de cobrança: , Telefone para contato") -> CLIENTE RETIRA / (0) Obs.Interna: valor da maquina R$ 4.845,42 CLIENTE RETIRA - Entrega em DEZEMBRO PAGAMENTO EM 16/10/25 . / E-mail para nota fiscal: , E-mail de cobrança: , Telefone para contato
A40: =IFERROR(__xludf.DUMMYFUNCTION("""COMPUTED_VALUE"""),"18814-A9") -> 18814-A9 | B40: =IFERROR(__xludf.DUMMYFUNCTION("""COMPUTED_VALUE"""),"W E COMERCIO DE PISCINAS LTDA") -> W E COMERCIO DE PISCINAS LTDA | C40: =IFERROR(__xludf.DUMMYFUNCTION("""COMPUTED_VALUE"""),1.0) -> 1 | E40: =IFERROR(__xludf.DUMMYFUNCTION("""COMPUTED_VALUE"""),"FTI25D40PT") -> FTI25D40PT | F40: =IFERROR(__xludf.DUMMYFUNCTION("""COMPUTED_VALUE"""),"WI-FI") -> WI-FI | G40: =IFERROR(__xludf.DUMMYFUNCTION("""COMPUTED_VALUE"""),"NAO") -> NAO | H40: =IFERROR(__xludf.DUMMYFUNCTION("""COMPUTED_VALUE"""),"NAO") -> NAO | I40: =IFERROR(__xludf.DUMMYFUNCTION("""COMPUTED_VALUE"""),"AGUARDAR CONTAINER") -> AGUARDAR CONTAINER | J40: =IFERROR(__xludf.DUMMYFUNCTION("""COMPUTED_VALUE"""),"RETIRA") -> RETIRA | K40: =IFERROR(__xludf.DUMMYFUNCTION("""COMPUTED_VALUE"""),"SEM REDESPACHO") -> SEM REDESPACHO | P40: =IFERROR(__xludf.DUMMYFUNCTION("""COMPUTED_VALUE"""),"CLIENTE RETIRA / (0) Obs.Interna: valor da maquina R$ 4.845,42 CLIENTE RETIRA - Entrega em DEZEMBRO PAGAMENTO EM 16/10/25 . / E-mail para nota fiscal: , E-mail de cobrança: , Telefone para contato") -> CLIENTE RETIRA / (0) Obs.Interna: valor da maquina R$ 4.845,42 CLIENTE RETIRA - Entrega em DEZEMBRO PAGAMENTO EM 16/10/25 . / E-mail para nota fiscal: , E-mail de cobrança: , Telefone para contato
A41: =IFERROR(__xludf.DUMMYFUNCTION("""COMPUTED_VALUE"""),"18814-B") -> 18814-B | B41: =IFERROR(__xludf.DUMMYFUNCTION("""COMPUTED_VALUE"""),"W E COMERCIO DE PISCINAS LTDA") -> W E COMERCIO DE PISCINAS LTDA | C41: =IFERROR(__xludf.DUMMYFUNCTION("""COMPUTED_VALUE"""),1.0) -> 1 | E41: =IFERROR(__xludf.DUMMYFUNCTION("""COMPUTED_VALUE"""),"FTI25D40PT") -> FTI25D40PT | F41: =IFERROR(__xludf.DUMMYFUNCTION("""COMPUTED_VALUE"""),"WI-FI") -> WI-FI | G41: =IFERROR(__xludf.DUMMYFUNCTION("""COMPUTED_VALUE"""),"NAO") -> NAO | H41: =IFERROR(__xludf.DUMMYFUNCTION("""COMPUTED_VALUE"""),"NAO") -> NAO | I41: =IFERROR(__xludf.DUMMYFUNCTION("""COMPUTED_VALUE"""),"AGUARDAR CONTAINER") -> AGUARDAR CONTAINER | J41: =IFERROR(__xludf.DUMMYFUNCTION("""COMPUTED_VALUE"""),"RETIRA") -> RETIRA | K41: =IFERROR(__xludf.DUMMYFUNCTION("""COMPUTED_VALUE"""),"SEM REDESPACHO") -> SEM REDESPACHO | P41: =IFERROR(__xludf.DUMMYFUNCTION("""COMPUTED_VALUE"""),"CLIENTE RETIRA / (0) Obs.Interna: valor da maquina R$ 4.845,42 CLIENTE RETIRA - Entrega em DEZEMBRO PAGAMENTO EM 16/10/25 . / E-mail para nota fiscal: , E-mail de cobrança: , Telefone para contato") -> CLIENTE RETIRA / (0) Obs.Interna: valor da maquina R$ 4.845,42 CLIENTE RETIRA - Entrega em DEZEMBRO PAGAMENTO EM 16/10/25 . / E-mail para nota fiscal: , E-mail de cobrança: , Telefone para contato
A42: =IFERROR(__xludf.DUMMYFUNCTION("""COMPUTED_VALUE"""),"18814-C") -> 18814-C | B42: =IFERROR(__xludf.DUMMYFUNCTION("""COMPUTED_VALUE"""),"W E COMERCIO DE PISCINAS LTDA") -> W E COMERCIO DE PISCINAS LTDA | C42: =IFERROR(__xludf.DUMMYFUNCTION("""COMPUTED_VALUE"""),1.0) -> 1 | E42: =IFERROR(__xludf.DUMMYFUNCTION("""COMPUTED_VALUE"""),"FTI25D40PT") -> FTI25D40PT | F42: =IFERROR(__xludf.DUMMYFUNCTION("""COMPUTED_VALUE"""),"WI-FI") -> WI-FI | G42: =IFERROR(__xludf.DUMMYFUNCTION("""COMPUTED_VALUE"""),"NAO") -> NAO | H42: =IFERROR(__xludf.DUMMYFUNCTION("""COMPUTED_VALUE"""),"NAO") -> NAO | I42: =IFERROR(__xludf.DUMMYFUNCTION("""COMPUTED_VALUE"""),"AGUARDAR CONTAINER") -> AGUARDAR CONTAINER | J42: =IFERROR(__xludf.DUMMYFUNCTION("""COMPUTED_VALUE"""),"RETIRA") -> RETIRA | K42: =IFERROR(__xludf.DUMMYFUNCTION("""COMPUTED_VALUE"""),"SEM REDESPACHO") -> SEM REDESPACHO | P42: =IFERROR(__xludf.DUMMYFUNCTION("""COMPUTED_VALUE"""),"CLIENTE RETIRA / (0) Obs.Interna: valor da maquina R$ 4.845,42 CLIENTE RETIRA - Entrega em DEZEMBRO PAGAMENTO EM 16/10/25 . / E-mail para nota fiscal: , E-mail de cobrança: , Telefone para contato") -> CLIENTE RETIRA / (0) Obs.Interna: valor da maquina R$ 4.845,42 CLIENTE RETIRA - Entrega em DEZEMBRO PAGAMENTO EM 16/10/25 . / E-mail para nota fiscal: , E-mail de cobrança: , Telefone para contato
A43: =IFERROR(__xludf.DUMMYFUNCTION("""COMPUTED_VALUE"""),"18814-D") -> 18814-D | B43: =IFERROR(__xludf.DUMMYFUNCTION("""COMPUTED_VALUE"""),"W E COMERCIO DE PISCINAS LTDA") -> W E COMERCIO DE PISCINAS LTDA | C43: =IFERROR(__xludf.DUMMYFUNCTION("""COMPUTED_VALUE"""),1.0) -> 1 | E43: =IFERROR(__xludf.DUMMYFUNCTION("""COMPUTED_VALUE"""),"FTI25D40PT") -> FTI25D40PT | F43: =IFERROR(__xludf.DUMMYFUNCTION("""COMPUTED_VALUE"""),"WI-FI") -> WI-FI | G43: =IFERROR(__xludf.DUMMYFUNCTION("""COMPUTED_VALUE"""),"NAO") -> NAO | H43: =IFERROR(__xludf.DUMMYFUNCTION("""COMPUTED_VALUE"""),"NAO") -> NAO | I43: =IFERROR(__xludf.DUMMYFUNCTION("""COMPUTED_VALUE"""),"AGUARDAR CONTAINER") -> AGUARDAR CONTAINER | J43: =IFERROR(__xludf.DUMMYFUNCTION("""COMPUTED_VALUE"""),"RETIRA") -> RETIRA | K43: =IFERROR(__xludf.DUMMYFUNCTION("""COMPUTED_VALUE"""),"SEM REDESPACHO") -> SEM REDESPACHO | P43: =IFERROR(__xludf.DUMMYFUNCTION("""COMPUTED_VALUE"""),"CLIENTE RETIRA / (0) Obs.Interna: valor da maquina R$ 4.845,42 CLIENTE RETIRA - Entrega em DEZEMBRO PAGAMENTO EM 16/10/25 . / E-mail para nota fiscal: , E-mail de cobrança: , Telefone para contato") -> CLIENTE RETIRA / (0) Obs.Interna: valor da maquina R$ 4.845,42 CLIENTE RETIRA - Entrega em DEZEMBRO PAGAMENTO EM 16/10/25 . / E-mail para nota fiscal: , E-mail de cobrança: , Telefone para contato
A44: =IFERROR(__xludf.DUMMYFUNCTION("""COMPUTED_VALUE"""),"18814-E") -> 18814-E | B44: =IFERROR(__xludf.DUMMYFUNCTION("""COMPUTED_VALUE"""),"W E COMERCIO DE PISCINAS LTDA") -> W E COMERCIO DE PISCINAS LTDA | C44: =IFERROR(__xludf.DUMMYFUNCTION("""COMPUTED_VALUE"""),1.0) -> 1 | E44: =IFERROR(__xludf.DUMMYFUNCTION("""COMPUTED_VALUE"""),"FTI25D40PT") -> FTI25D40PT | F44: =IFERROR(__xludf.DUMMYFUNCTION("""COMPUTED_VALUE"""),"WI-FI") -> WI-FI | G44: =IFERROR(__xludf.DUMMYFUNCTION("""COMPUTED_VALUE"""),"NAO") -> NAO | H44: =IFERROR(__xludf.DUMMYFUNCTION("""COMPUTED_VALUE"""),"NAO") -> NAO | I44: =IFERROR(__xludf.DUMMYFUNCTION("""COMPUTED_VALUE"""),"AGUARDAR CONTAINER") -> AGUARDAR CONTAINER | J44: =IFERROR(__xludf.DUMMYFUNCTION("""COMPUTED_VALUE"""),"RETIRA") -> RETIRA | K44: =IFERROR(__xludf.DUMMYFUNCTION("""COMPUTED_VALUE"""),"SEM REDESPACHO") -> SEM REDESPACHO | P44: =IFERROR(__xludf.DUMMYFUNCTION("""COMPUTED_VALUE"""),"CLIENTE RETIRA / (0) Obs.Interna: valor da maquina R$ 4.845,42 CLIENTE RETIRA - Entrega em DEZEMBRO PAGAMENTO EM 16/10/25 . / E-mail para nota fiscal: , E-mail de cobrança: , Telefone para contato") -> CLIENTE RETIRA / (0) Obs.Interna: valor da maquina R$ 4.845,42 CLIENTE RETIRA - Entrega em DEZEMBRO PAGAMENTO EM 16/10/25 . / E-mail para nota fiscal: , E-mail de cobrança: , Telefone para contato
A45: =IFERROR(__xludf.DUMMYFUNCTION("""COMPUTED_VALUE"""),"18814-F") -> 18814-F | B45: =IFERROR(__xludf.DUMMYFUNCTION("""COMPUTED_VALUE"""),"W E COMERCIO DE PISCINAS LTDA") -> W E COMERCIO DE PISCINAS LTDA | C45: =IFERROR(__xludf.DUMMYFUNCTION("""COMPUTED_VALUE"""),1.0) -> 1 | E45: =IFERROR(__xludf.DUMMYFUNCTION("""COMPUTED_VALUE"""),"FTI25D40PT") -> FTI25D40PT | F45: =IFERROR(__xludf.DUMMYFUNCTION("""COMPUTED_VALUE"""),"WI-FI") -> WI-FI | G45: =IFERROR(__xludf.DUMMYFUNCTION("""COMPUTED_VALUE"""),"NAO") -> NAO | H45: =IFERROR(__xludf.DUMMYFUNCTION("""COMPUTED_VALUE"""),"NAO") -> NAO | I45: =IFERROR(__xludf.DUMMYFUNCTION("""COMPUTED_VALUE"""),"AGUARDAR CONTAINER") -> AGUARDAR CONTAINER | J45: =IFERROR(__xludf.DUMMYFUNCTION("""COMPUTED_VALUE"""),"RETIRA") -> RETIRA | K45: =IFERROR(__xludf.DUMMYFUNCTION("""COMPUTED_VALUE"""),"SEM REDESPACHO") -> SEM REDESPACHO | P45: =IFERROR(__xludf.DUMMYFUNCTION("""COMPUTED_VALUE"""),"CLIENTE RETIRA / (0) Obs.Interna: valor da maquina R$ 4.845,42 CLIENTE RETIRA - Entrega em DEZEMBRO PAGAMENTO EM 16/10/25 . / E-mail para nota fiscal: , E-mail de cobrança: , Telefone para contato") -> CLIENTE RETIRA / (0) Obs.Interna: valor da maquina R$ 4.845,42 CLIENTE RETIRA - Entrega em DEZEMBRO PAGAMENTO EM 16/10/25 . / E-mail para nota fiscal: , E-mail de cobrança: , Telefone para contato
A46: =IFERROR(__xludf.DUMMYFUNCTION("""COMPUTED_VALUE"""),"18814-G") -> 18814-G | B46: =IFERROR(__xludf.DUMMYFUNCTION("""COMPUTED_VALUE"""),"W E COMERCIO DE PISCINAS LTDA") -> W E COMERCIO DE PISCINAS LTDA | C46: =IFERROR(__xludf.DUMMYFUNCTION("""COMPUTED_VALUE"""),1.0) -> 1 | E46: =IFERROR(__xludf.DUMMYFUNCTION("""COMPUTED_VALUE"""),"FTI25D40PT") -> FTI25D40PT | F46: =IFERROR(__xludf.DUMMYFUNCTION("""COMPUTED_VALUE"""),"WI-FI") -> WI-FI | G46: =IFERROR(__xludf.DUMMYFUNCTION("""COMPUTED_VALUE"""),"NAO") -> NAO | H46: =IFERROR(__xludf.DUMMYFUNCTION("""COMPUTED_VALUE"""),"NAO") -> NAO | I46: =IFERROR(__xludf.DUMMYFUNCTION("""COMPUTED_VALUE"""),"AGUARDAR CONTAINER") -> AGUARDAR CONTAINER | J46: =IFERROR(__xludf.DUMMYFUNCTION("""COMPUTED_VALUE"""),"RETIRA") -> RETIRA | K46: =IFERROR(__xludf.DUMMYFUNCTION("""COMPUTED_VALUE"""),"SEM REDESPACHO") -> SEM REDESPACHO | P46: =IFERROR(__xludf.DUMMYFUNCTION("""COMPUTED_VALUE"""),"CLIENTE RETIRA / (0) Obs.Interna: valor da maquina R$ 4.845,42 CLIENTE RETIRA - Entrega em DEZEMBRO PAGAMENTO EM 16/10/25 . / E-mail para nota fiscal: , E-mail de cobrança: , Telefone para contato") -> CLIENTE RETIRA / (0) Obs.Interna: valor da maquina R$ 4.845,42 CLIENTE RETIRA - Entrega em DEZEMBRO PAGAMENTO EM 16/10/25 . / E-mail para nota fiscal: , E-mail de cobrança: , Telefone para contato
A47: =IFERROR(__xludf.DUMMYFUNCTION("""COMPUTED_VALUE"""),"18814-H") -> 18814-H | B47: =IFERROR(__xludf.DUMMYFUNCTION("""COMPUTED_VALUE"""),"W E COMERCIO DE PISCINAS LTDA") -> W E COMERCIO DE PISCINAS LTDA | C47: =IFERROR(__xludf.DUMMYFUNCTION("""COMPUTED_VALUE"""),1.0) -> 1 | E47: =IFERROR(__xludf.DUMMYFUNCTION("""COMPUTED_VALUE"""),"FTI25D40PT") -> FTI25D40PT | F47: =IFERROR(__xludf.DUMMYFUNCTION("""COMPUTED_VALUE"""),"WI-FI") -> WI-FI | G47: =IFERROR(__xludf.DUMMYFUNCTION("""COMPUTED_VALUE"""),"NAO") -> NAO | H47: =IFERROR(__xludf.DUMMYFUNCTION("""COMPUTED_VALUE"""),"NAO") -> NAO | I47: =IFERROR(__xludf.DUMMYFUNCTION("""COMPUTED_VALUE"""),"AGUARDAR CONTAINER") -> AGUARDAR CONTAINER | J47: =IFERROR(__xludf.DUMMYFUNCTION("""COMPUTED_VALUE"""),"RETIRA") -> RETIRA | K47: =IFERROR(__xludf.DUMMYFUNCTION("""COMPUTED_VALUE"""),"SEM REDESPACHO") -> SEM REDESPACHO | P47: =IFERROR(__xludf.DUMMYFUNCTION("""COMPUTED_VALUE"""),"CLIENTE RETIRA / (0) Obs.Interna: valor da maquina R$ 4.845,42 CLIENTE RETIRA - Entrega em DEZEMBRO PAGAMENTO EM 16/10/25 . / E-mail para nota fiscal: , E-mail de cobrança: , Telefone para contato") -> CLIENTE RETIRA / (0) Obs.Interna: valor da maquina R$ 4.845,42 CLIENTE RETIRA - Entrega em DEZEMBRO PAGAMENTO EM 16/10/25 . / E-mail para nota fiscal: , E-mail de cobrança: , Telefone para contato
A48: =IFERROR(__xludf.DUMMYFUNCTION("""COMPUTED_VALUE"""),"18814-I") -> 18814-I | B48: =IFERROR(__xludf.DUMMYFUNCTION("""COMPUTED_VALUE"""),"W E COMERCIO DE PISCINAS LTDA") -> W E COMERCIO DE PISCINAS LTDA | C48: =IFERROR(__xludf.DUMMYFUNCTION("""COMPUTED_VALUE"""),1.0) -> 1 | E48: =IFERROR(__xludf.DUMMYFUNCTION("""COMPUTED_VALUE"""),"FTI25D40PT") -> FTI25D40PT | F48: =IFERROR(__xludf.DUMMYFUNCTION("""COMPUTED_VALUE"""),"WI-FI") -> WI-FI | G48: =IFERROR(__xludf.DUMMYFUNCTION("""COMPUTED_VALUE"""),"NAO") -> NAO | H48: =IFERROR(__xludf.DUMMYFUNCTION("""COMPUTED_VALUE"""),"NAO") -> NAO | I48: =IFERROR(__xludf.DUMMYFUNCTION("""COMPUTED_VALUE"""),"AGUARDAR CONTAINER") -> AGUARDAR CONTAINER | J48: =IFERROR(__xludf.DUMMYFUNCTION("""COMPUTED_VALUE"""),"RETIRA") -> RETIRA | K48: =IFERROR(__xludf.DUMMYFUNCTION("""COMPUTED_VALUE"""),"SEM REDESPACHO") -> SEM REDESPACHO | P48: =IFERROR(__xludf.DUMMYFUNCTION("""COMPUTED_VALUE"""),"CLIENTE RETIRA / (0) Obs.Interna: valor da maquina R$ 4.845,42 CLIENTE RETIRA - Entrega em DEZEMBRO PAGAMENTO EM 16/10/25 . / E-mail para nota fiscal: , E-mail de cobrança: , Telefone para contato") -> CLIENTE RETIRA / (0) Obs.Interna: valor da maquina R$ 4.845,42 CLIENTE RETIRA - Entrega em DEZEMBRO PAGAMENTO EM 16/10/25 . / E-mail para nota fiscal: , E-mail de cobrança: , Telefone para contato
A49: =IFERROR(__xludf.DUMMYFUNCTION("""COMPUTED_VALUE"""),"18814-J") -> 18814-J | B49: =IFERROR(__xludf.DUMMYFUNCTION("""COMPUTED_VALUE"""),"W E COMERCIO DE PISCINAS LTDA") -> W E COMERCIO DE PISCINAS LTDA | C49: =IFERROR(__xludf.DUMMYFUNCTION("""COMPUTED_VALUE"""),1.0) -> 1 | E49: =IFERROR(__xludf.DUMMYFUNCTION("""COMPUTED_VALUE"""),"FTI25D40PT") -> FTI25D40PT | F49: =IFERROR(__xludf.DUMMYFUNCTION("""COMPUTED_VALUE"""),"WI-FI") -> WI-FI | G49: =IFERROR(__xludf.DUMMYFUNCTION("""COMPUTED_VALUE"""),"NAO") -> NAO | H49: =IFERROR(__xludf.DUMMYFUNCTION("""COMPUTED_VALUE"""),"NAO") -> NAO | I49: =IFERROR(__xludf.DUMMYFUNCTION("""COMPUTED_VALUE"""),"AGUARDAR CONTAINER") -> AGUARDAR CONTAINER | J49: =IFERROR(__xludf.DUMMYFUNCTION("""COMPUTED_VALUE"""),"RETIRA") -> RETIRA | K49: =IFERROR(__xludf.DUMMYFUNCTION("""COMPUTED_VALUE"""),"SEM REDESPACHO") -> SEM REDESPACHO | P49: =IFERROR(__xludf.DUMMYFUNCTION("""COMPUTED_VALUE"""),"CLIENTE RETIRA / (0) Obs.Interna: valor da maquina R$ 4.845,42 CLIENTE RETIRA - Entrega em DEZEMBRO PAGAMENTO EM 16/10/25 . / E-mail para nota fiscal: , E-mail de cobrança: , Telefone para contato") -> CLIENTE RETIRA / (0) Obs.Interna: valor da maquina R$ 4.845,42 CLIENTE RETIRA - Entrega em DEZEMBRO PAGAMENTO EM 16/10/25 . / E-mail para nota fiscal: , E-mail de cobrança: , Telefone para contato
A50: =IFERROR(__xludf.DUMMYFUNCTION("""COMPUTED_VALUE"""),"18814-K") -> 18814-K | B50: =IFERROR(__xludf.DUMMYFUNCTION("""COMPUTED_VALUE"""),"W E COMERCIO DE PISCINAS LTDA") -> W E COMERCIO DE PISCINAS LTDA | C50: =IFERROR(__xludf.DUMMYFUNCTION("""COMPUTED_VALUE"""),1.0) -> 1 | E50: =IFERROR(__xludf.DUMMYFUNCTION("""COMPUTED_VALUE"""),"FTI25D40PT") -> FTI25D40PT | F50: =IFERROR(__xludf.DUMMYFUNCTION("""COMPUTED_VALUE"""),"WI-FI") -> WI-FI | G50: =IFERROR(__xludf.DUMMYFUNCTION("""COMPUTED_VALUE"""),"NAO") -> NAO | H50: =IFERROR(__xludf.DUMMYFUNCTION("""COMPUTED_VALUE"""),"NAO") -> NAO | I50: =IFERROR(__xludf.DUMMYFUNCTION("""COMPUTED_VALUE"""),"AGUARDAR CONTAINER") -> AGUARDAR CONTAINER | J50: =IFERROR(__xludf.DUMMYFUNCTION("""COMPUTED_VALUE"""),"RETIRA") -> RETIRA | K50: =IFERROR(__xludf.DUMMYFUNCTION("""COMPUTED_VALUE"""),"SEM REDESPACHO") -> SEM REDESPACHO | P50: =IFERROR(__xludf.DUMMYFUNCTION("""COMPUTED_VALUE"""),"CLIENTE RETIRA / (0) Obs.Interna: valor da maquina R$ 4.845,42 CLIENTE RETIRA - Entrega em DEZEMBRO PAGAMENTO EM 16/10/25 . / E-mail para nota fiscal: , E-mail de cobrança: , Telefone para contato") -> CLIENTE RETIRA / (0) Obs.Interna: valor da maquina R$ 4.845,42 CLIENTE RETIRA - Entrega em DEZEMBRO PAGAMENTO EM 16/10/25 . / E-mail para nota fiscal: , E-mail de cobrança: , Telefone para contato
